Workbook

Sheet 2025
B1: JAN | C1: FEB | D1: MAR | E1: APR | F1: MAY | G1: JUN | H1: JUL | I1: AUG | J1: SEP | K1: OCT | L1: NOV | M1: DEC
A2: Common Room | B2: 149718 | C2: 100378 | D2: 110821 | E2: 96858 | F2: 120151 | G2: 132070 | H2: 124470 | I2: 117003 | J2: 112778 | K2: 102137 | L2: 136158 | M2: 391157 | O2: =SUM(B2:F2) -> 577926
A3: Frankie and Friends | B3: 107838 | C3: 35082 | D3: 53097 | E3: 31058 | F3: 52598 | G3: 44813 | H3: 31878 | I3: 38896 | J3: 51940 | K3: 27723 | L3: 68281 | M3: 206238 | O3: =SUM(B3:F3) -> 279673
A4: Craft Central | B4: 8415 | C4: 7547 | D4: 5301 | E4: 5623 | F4: 5343 | G4: 7937 | H4: 4706 | I4: 7705 | J4: 5653 | K4: 5653 | L4: 14587 | M4: 14305 | O4: =SUM(B4:F4) -> 32229
A5: Simula PH | B5: 8467 | C5: 6562 | D5: 6031 | E5: 7311 | F5: 9553 | G5: 4666 | H5: 6122 | I5: 11018 | J5: 7879 | K5: 8069 | L5: 17564 | M5: 18081 | O5: =SUM(B5:F5) -> 37924
A6: 9 Matters | B6: 4117 | C6: 5120 | D6: 2503 | E6: 1817 | F6: 4742 | G6: 5576 | H6: 2115 | I6: 1786 | J6: 4457 | K6: 5587 | L6: 6025 | M6: 7940 | O6: =SUM(B6:F6) -> 18299
A7: Lazada | B7: 37084 | C7: 10641 | D7: 25587 | E7: 25036 | F7: 33962 | G7: 19743 | H7: 26690 | I7: 33401 | J7: 36353 | K7: 16025 | L7: 48918 | M7: 27482 | O7: =SUM(B7:F7) -> 132310
A8: Shopee | B8: 42302 | C8: 35262 | D8: 36184 | E8: 35911 | F8: 37121 | G8: 45294 | H8: 44055 | I8: 77103 | J8: 82374 | K8: 63142 | L8: 104195 | M8: 179518 | O8: =SUM(B8:F8) -> 186780
A9: Shopify | B9: 38603 | C9: 73396 | D9: 29005 | E9: 57156 | F9: 31154 | G9: 45210 | H9: 16551 | I9: 75906 | J9: 11261 | K9: 47911 | L9: 68469 | M9: 267089 | O9: =SUM(B9:F9) -> 229314
A10: Pick-a-roo | B10: 1128 | C10: 0 | E10: 0 | F10: 0 | G10: 878 | O10: =SUM(B10:F10) -> 1128
A11: Tiktok | B11: 2035 | C11: 1547 | D11: 2523 | E11: 609 | F11: 329 | G11: 0 | H11: 329 | I11: 3889 | J11: 5646 | K11: 1576 | L11: 5546 | M11: 1128
A12: World Plaza | B12: 11524.8 | C12: 11524.8 | D12: 11524.8 | E12: 11524.8 | F12: 11524.8 | G12: 11524.8 | H12: 11524.8 | I12: 11524.8 | J12: 11524.8 | K12: 11524.8 | L12: 11524.8 | M12: 11524.8
A13: The Finance | B13: 25000 | C13: 27500 | D13: 27500 | E13: 27500 | G13: 27500 | H13: 27500 | I13: 35000 | J13: 35000 | K13: 35000 | L13: 35000 | M13: 35000
A14: Seibu | B14: 12000 | C14: 12000 | D14: 12000 | E14: 12000 | F14: 12000 | G14: 12000 | H14: 12000 | I14: 12000 | J14: 12000 | K14: 12000 | L14: 12000 | M14: 12000
A15: Grasshopper Concept | B15: 6000
A16: Haleon | H16: 11000 | I16: 11000 | J16: 11000 | K16: 11000 | L16: 11000 | M16: 11000
A17: Bazaar | M17: 310150
A20: TOTAL | B20: 454231.8 | C20: 326559.8 | D20: 322076.8 | E20: 312403.8 | F20: 318477.8 | G20: 357211.8 | H20: 307940.8 | I20: 436231.8 | J20: 387865.8 | K20: 347347.8 | L20: 539267.8

Sheet ACCOUNT PERFORMANCE
B1: % cont | C1: 45659 | D1: Target | F1: vs PY | H1: % cont | I1: JAN YTD | J1: PY | K1: vs PY | L1: % cont | M1: 46060 | N1: Target | P1: vs PY | R1: % cont | S1: FEB YTD | T1: PY | U1: vs PY | V1: % cont | W1: 46093 | X1: Target | Z1: vs PY | AB1: % cont | AC1: MAR YTD | AD1: PY | AE1: vs PY | AF1: % cont | AG1: 46115 | AH1: Target | AJ1: vs PY | AL1: % cont | AM1: APR YTD | AN1: PY | AO1: vs PY | AP1: % cont | AQ1: 46161 | AR1: Target | AT1: vs PY | AV1: % cont | AW1: MAY YTD | AX1: PY | AY1: vs PY
A2: Common Room | B2: =C2/$C$20 -> 0.30944554 | C2: ='COMMONROOM SUMMARY'!Q102 -> 146221 | D2: 146832 | F2: =sum(C2-E2)/E2 -> #DIV/0! | H2: =I2/$I$20 -> 0.3539382 | I2: =C2 -> 146221 | J2: 149718 | K2: =sum(I2-J2)/J2 -> -0.023357245 | L2: =M2/$C$20 -> 0.20241011 | M2: ='COMMONROOM SUMMARY'!R102 -> 95644 | N2: 146832 | P2: =sum(M2-O2)/O2 -> #DIV/0! | R2: =S2/$I$20 -> 0.58545121 | S2: =I2+M2 -> 241865 | T2: ='2025'!B2+'2025'!C2 -> 250096 | U2: =sum(S2-T2)/T2 -> -0.032911362 | V2: =W2/$C$20 -> 0.17275247 | W2: ='COMMONROOM SUMMARY'!S102 -> 81630 | X2: 146832 | Z2: =sum(W2-Y2)/Y2 -> #DIV/0! | AB2: =AC2/$I$20 -> 0.78304236 | AC2: =S2+W2 -> 323495 | AD2: =SUM('2025'!B2:D2) -> 360917 | AE2: =sum(AC2-AD2)/AD2 -> -0.10368589 | AF2: =AG2/$C$20 -> 0.20396347 | AG2: ='COMMONROOM SUMMARY'!T102 -> 96378 | AH2: 146832 | AJ2: =sum(AG2-AI2)/AI2 -> #DIV/0! | AL2: =AM2/$I$20 -> 1.0163321 | AM2: =AC2+AG2 -> 419873 | AN2: =SUM('2025'!B2:E2) -> 457775 | AO2: =sum(AM2-AN2)/AN2 -> -0.082796133 | AP2: =AQ2/$C$20 -> 0 | AR2: 146832 | AT2: =sum(AQ2-AS2)/AS2 -> #DIV/0! | AV2: =AW2/$I$20 -> 1.0163321 | AW2: =AM2+AQ2 -> 419873 | AX2: =SUM('2025'!B2:F2) -> 577926 | AY2: =sum(AW2-AX2)/AX2 -> -0.27348311
A3: Frankie and Friends | B3: =C3/$C$20 -> 0.092634095 | C3: =FRANKIE!A111 -> 43772 | D3: 64977 | F3: =sum(C3-E3)/E3 -> #DIV/0! | H3: =I3/$I$20 -> 0.1059532 | I3: =C3 -> 43772 | J3: 107838 | K3: =sum(I3-J3)/J3 -> -0.59409485 | L3: =M3/$C$20 -> 0.092634095 | M3: ='FRANKIE SUMMARY'!Q102 -> 43772 | N3: 64977 | P3: =sum(M3-O3)/O3 -> #DIV/0! | R3: =S3/$I$20 -> 0.2119064 | S3: =I3+M3 -> 87544 | T3: ='2025'!B3+'2025'!C3 -> 142920 | U3: =sum(S3-T3)/T3 -> -0.38746152 | V3: =W3/$C$20 -> 0.056858271 | W3: ='FRANKIE SUMMARY'!R102 -> 26867 | X3: 64977 | Z3: =sum(W3-Y3)/Y3 -> #DIV/0! | AB3: =AC3/$I$20 -> 0.27693986 | AC3: =S3+W3 -> 114411 | AD3: =SUM('2025'!B3:D3) -> 196017 | AE3: =sum(AC3-AD3)/AD3 -> -0.41632103 | AF3: =AG3/$C$20 -> 0.055715476 | AG3: ='FRANKIE SUMMARY'!T102 -> 26327 | AH3: 64977 | AJ3: =sum(AG3-AI3)/AI3 -> #DIV/0! | AL3: =AM3/$I$20 -> 0.34066621 | AM3: =AC3+AG3 -> 140738 | AN3: =SUM('2025'!B3:E3) -> 227075 | AO3: =sum(AM3-AN3)/AN3 -> -0.38021359 | AP3: =AQ3/$C$20 -> 0 | AQ3: =FRANKIE!AE112 | AR3: 64977 | AT3: =sum(AQ3-AS3)/AS3 -> #DIV/0! | AV3: =AW3/$I$20 -> 0.34066621 | AW3: =AM3+AQ3 -> 140738 | AX3: =SUM('2025'!B3:F3) -> 279673 | AY3: =sum(AW3-AX3)/AX3 -> -0.49677659
A4: Craft Central | B4: =C4/$C$20 -> 0.011349645 | C4: =TCC!C99 -> 5363 | D4: 7975 | F4: =sum(C4-E4)/E4 -> #DIV/0! | H4: =I4/$I$20 -> 0.012981518 | I4: =C4 -> 5363 | J4: 8415 | K4: =sum(I4-J4)/J4 -> -0.36268568 | L4: =M4/$C$20 -> 0.0061710916 | M4: =TCC!A109 -> 2916 | N4: 7975 | P4: =sum(M4-O4)/O4 -> #DIV/0! | R4: =S4/$I$20 -> 0.020039901 | S4: =I4+M4 -> 8279 | T4: ='2025'!B4+'2025'!C4 -> 15962 | U4: =sum(S4-T4)/T4 -> -0.48133066 | V4: =W4/$C$20 -> 0.0061710916 | W4: ='TCC SUMMARY'!R102 -> 2916 | X4: 7975 | Z4: =sum(W4-Y4)/Y4 -> #DIV/0! | AB4: =AC4/$I$20 -> 0.027098283 | AC4: =S4+W4 -> 11195 | AD4: =SUM('2025'!B4:D4) -> 21263 | AE4: =sum(AC4-AD4)/AD4 -> -0.47349857 | AF4: =AG4/$C$20 -> 0 | AG4: ='TCC SUMMARY'!T102 | AH4: 7975 | AJ4: =sum(AG4-AI4)/AI4 -> #DIV/0! | AL4: =AM4/$I$20 -> 0.027098283 | AM4: =AC4+AG4 -> 11195 | AN4: =SUM('2025'!B4:E4) -> 26886 | AO4: =sum(AM4-AN4)/AN4 -> -0.58361229 | AP4: =AQ4/$C$20 -> 0 | AQ4: =TCC!AE109 | AR4: 7975 | AT4: =sum(AQ4-AS4)/AS4 -> #DIV/0! | AV4: =AW4/$I$20 -> 0.027098283 | AW4: =AM4+AQ4 -> 11195 | AX4: =SUM('2025'!B4:F4) -> 32229 | AY4: =sum(AW4-AX4)/AX4 -> -0.65264203
A5: Simula PH | B5: =C5/$C$20 -> 0.0210634 | C5: =SIMULAPH!C102 -> 9953 | D5: 7563 | F5: =sum(C5-E5)/E5 -> #DIV/0! | H5: =I5/$I$20 -> 0.024091935 | I5: =C5 -> 9953 | J5: 8467 | K5: =sum(I5-J5)/J5 -> 0.1755049 | L5: =M5/$C$20 -> 0.010088338 | M5: ='SIMULAPH SUMMARY'!R102 -> 4767 | N5: 7563 | P5: =sum(M5-O5)/O5 -> #DIV/0! | R5: =S5/$I$20 -> 0.035630793 | S5: =I5+M5 -> 14720 | T5: ='2025'!B5+'2025'!C5 -> 15029 | U5: =sum(S5-T5)/T5 -> -0.02056025 | V5: =W5/$C$20 -> 0.010088338 | W5: ='SIMULAPH SUMMARY'!R102 -> 4767 | X5: 7563 | Z5: =sum(W5-Y5)/Y5 -> #DIV/0! | AB5: =AC5/$I$20 -> 0.047169651 | AC5: =S5+W5 -> 19487 | AD5: =SUM('2025'!B5:D5) -> 21060 | AE5: =sum(AC5-AD5)/AD5 -> -0.074691358 | AF5: =AG5/$C$20 -> 0.010975062 | AG5: ='SIMULAPH SUMMARY'!T102 -> 5186 | AH5: 7563 | AJ5: =sum(AG5-AI5)/AI5 -> #DIV/0! | AL5: =AM5/$I$20 -> 0.059722729 | AM5: =AC5+AG5 -> 24673 | AN5: =SUM('2025'!B5:E5) -> 28371 | AO5: =sum(AM5-AN5)/AN5 -> -0.13034437 | AP5: =AQ5/$C$20 -> 0 | AR5: 7563 | AT5: =sum(AQ5-AS5)/AS5 -> #DIV/0! | AV5: =AW5/$I$20 -> 0.059722729 | AW5: =AM5+AQ5 -> 24673 | AX5: =SUM('2025'!B5:F5) -> 37924 | AY5: =sum(AW5-AX5)/AX5 -> -0.34940934
A6: 9 Matters | B6: =C6/$C$20 -> 0.0098534302 | C6: ='9 Matters'!C99 -> 4656 | D6: 9864 | F6: =sum(C6-E6)/E6 -> #DIV/0! | H6: =I6/$I$20 -> 0.011270175 | I6: =C6 -> 4656 | J6: 4117 | K6: =sum(I6-J6)/J6 -> 0.13092057 | L6: =M6/$C$20 -> 0.031805671 | M6: ='9MATTERS SUMMARY'!R102 -> 15029 | N6: 9864 | P6: =sum(M6-O6)/O6 -> #DIV/0! | R6: =S6/$I$20 -> 0.047648924 | S6: =I6+M6 -> 19685 | T6: ='2025'!B6+'2025'!C6 -> 9237 | U6: =sum(S6-T6)/T6 -> 1.1311032 | V6: =W6/$C$20 -> 0.046259908 | W6: ='9MATTERS SUMMARY'!S102 -> 21859 | X6: 9864 | Z6: =sum(W6-Y6)/Y6 -> #DIV/0! | AB6: =AC6/$I$20 -> 0.10056017 | AC6: =S6+W6 -> 41544 | AD6: =SUM('2025'!B6:D6) -> 11740 | AE6: =sum(AC6-AD6)/AD6 -> 2.5386712 | AF6: =AG6/$C$20 -> 0.011087225 | AG6: ='9MATTERS SUMMARY'!T102 -> 5239 | AH6: 9864 | AJ6: =sum(AG6-AI6)/AI6 -> #DIV/0! | AL6: =AM6/$I$20 -> 0.11324154 | AM6: =AC6+AG6 -> 46783 | AN6: =SUM('2025'!B6:E6) -> 13557 | AO6: =sum(AM6-AN6)/AN6 -> 2.4508372 | AP6: =AQ6/$C$20 -> 0 | AR6: 9864 | AT6: =sum(AQ6-AS6)/AS6 -> #DIV/0! | AV6: =AW6/$I$20 -> 0.11324154 | AW6: =AM6+AQ6 -> 46783 | AX6: =SUM('2025'!B6:F6) -> 18299 | AY6: =sum(AW6-AX6)/AX6 -> 1.5565878
A7: Lazada | B7: =C7/$C$20 -> 0.036539804 | C7: =LAZADA!A111 -> 17266 | D7: 47694 | F7: =sum(C7-E7)/E7 -> #DIV/0! | H7: =I7/$I$20 -> 0.041793565 | I7: =C7 -> 17266 | J7: 37084 | K7: =sum(I7-J7)/J7 -> -0.53440837 | L7: =M7/$C$20 -> 0.052524116 | M7: =LAZADA!A112 -> 24819 | N7: 47694 | P7: =sum(M7-O7)/O7 -> #DIV/0! | R7: =S7/$I$20 -> 0.1018697 | S7: =I7+M7 -> 42085 | T7: ='2025'!B7+'2025'!C7 -> 47725 | U7: =sum(S7-T7)/T7 -> -0.11817706 | V7: =W7/$C$20 -> 0.036463617 | W7: =LAZADA!A113 -> 17230 | X7: 47694 | Z7: =sum(W7-Y7)/Y7 -> #DIV/0! | AB7: =AC7/$I$20 -> 0.14357612 | AC7: =S7+W7 -> 59315 | AD7: =SUM('2025'!B7:D7) -> 73312 | AE7: =sum(AC7-AD7)/AD7 -> -0.19092372 | AF7: =AG7/$C$20 -> 0.062874874 | AG7: =LAZADA!A114 -> 29710 | AH7: 47694 | AJ7: =sum(AG7-AI7)/AI7 -> #DIV/0! | AL7: =AM7/$I$20 -> 0.21549126 | AM7: =AC7+AG7 -> 89025 | AN7: =SUM('2025'!B7:E7) -> 98348 | AO7: =sum(AM7-AN7)/AN7 -> -0.09479603 | AP7: =AQ7/$C$20 -> 0.042882315 | AQ7: =LAZADA!A115 -> 20263 | AR7: 47694 | AT7: =sum(AQ7-AS7)/AS7 -> #DIV/0! | AV7: =AW7/$I$20 -> 0.26453928 | AW7: =AM7+AQ7 -> 109288 | AX7: =SUM('2025'!B7:F7) -> 132310 | AY7: =sum(AW7-AX7)/AX7 -> -0.17400045
A8: Shopee | B8: =C8/$C$20 -> 0.11779463 | C8: =SHOPEE!A112 -> 55661 | D8: 66493 | F8: =sum(C8-E8)/E8 -> #DIV/0! | H8: =I8/$I$20 -> 0.13473136 | I8: =C8 -> 55661 | J8: 42302 | K8: =sum(I8-J8)/J8 -> 0.31580067 | L8: =M8/$C$20 -> 0.07204686 | M8: =SHOPEE!A113 -> 34044 | N8: 66493 | P8: =sum(M8-O8)/O8 -> #DIV/0! | R8: =S8/$I$20 -> 0.21713725 | S8: =I8+M8 -> 89705 | T8: ='2025'!B8+'2025'!C8 -> 77564 | U8: =sum(S8-T8)/T8 -> 0.1565288 | V8: =W8/$C$20 -> 0.069699898 | W8: =SHOPEE!A114 -> 32935 | X8: 66493 | Z8: =sum(W8-Y8)/Y8 -> #DIV/0! | AB8: =AC8/$I$20 -> 0.29685873 | AC8: =S8+W8 -> 122640 | AD8: =SUM('2025'!B8:D8) -> 113748 | AE8: =sum(AC8-AD8)/AD8 -> 0.078172803 | AF8: =AG8/$C$20 -> 0.073117701 | AG8: =SHOPEE!A115 -> 34550 | AH8: 66493 | AJ8: =sum(AG8-AI8)/AI8 -> #DIV/0! | AL8: =AM8/$I$20 -> 0.38048943 | AM8: =AC8+AG8 -> 157190 | AN8: =SUM('2025'!B8:E8) -> 149659 | AO8: =sum(AM8-AN8)/AN8 -> 0.050321063 | AP8: =AQ8/$C$20 -> 0.064779532 | AQ8: =SHOPEE!A116 -> 30610 | AR8: 66493 | AT8: =sum(AQ8-AS8)/AS8 -> #DIV/0! | AV8: =AW8/$I$20 -> 0.45458308 | AW8: =AM8+AQ8 -> 187800 | AX8: =SUM('2025'!B8:F8) -> 186780 | AY8: =sum(AW8-AX8)/AX8 -> 0.0054609701
A9: Shopify | B9: =C9/$C$20 -> 0.017728133 | C9: =SHOPIFY!A111 -> 8377 | D9: 92744 | F9: =sum(C9-E9)/E9 -> #DIV/0! | H9: =I9/$I$20 -> 0.020277117 | I9: =C9 -> 8377 | J9: 38603 | K9: =sum(I9-J9)/J9 -> -0.78299614 | L9: =M9/$C$20 -> 0.049444919 | M9: =SHOPIFY!A112 -> 23364 | N9: 92744 | P9: =sum(M9-O9)/O9 -> #DIV/0! | R9: =S9/$I$20 -> 0.076831319 | S9: =I9+M9 -> 31741 | T9: ='2025'!B9+'2025'!C9 -> 111999 | U9: =sum(S9-T9)/T9 -> -0.71659568 | V9: =W9/$C$20 -> 0.069244896 | W9: =SHOPIFY!A113 -> 32720 | X9: 92744 | Z9: =sum(W9-Y9)/Y9 -> #DIV/0! | AB9: =AC9/$I$20 -> 0.15603238 | AC9: =S9+W9 -> 64461 | AD9: =SUM('2025'!B9:D9) -> 141004 | AE9: =sum(AC9-AD9)/AD9 -> -0.54284276 | AF9: =AG9/$C$20 -> 0.073919773 | AG9: =SHOPIFY!A114 -> 34929 | AH9: 92744 | AJ9: =sum(AG9-AI9)/AI9 -> #DIV/0! | AL9: =AM9/$I$20 -> 0.24058047 | AM9: =AC9+AG9 -> 99390 | AN9: =SUM('2025'!B9:E9) -> 198160 | AO9: =sum(AM9-AN9)/AN9 -> -0.49843561 | AP9: =AQ9/$C$20 -> 0.059838003 | AQ9: =SHOPIFY!A115 -> 28275 | AR9: 92744 | AT9: =sum(AQ9-AS9)/AS9 -> #DIV/0! | AV9: =AW9/$I$20 -> 0.30902209 | AW9: =AM9+AQ9 -> 127665 | AX9: =SUM('2025'!B9:F9) -> 229314 | AY9: =sum(AW9-AX9)/AX9 -> -0.44327429
A10: Pick-a-roo | B10: =C10/$C$20 -> 0 | D10: 689 | F10: =sum(C10-E10)/E10 -> #DIV/0! | H10: =I10/$I$20 -> 0 | I10: =C10 | J10: 1128 | K10: =sum(I10-J10)/J10 -> -1 | L10: =M10/$C$20 -> 0 | M10: =PICKAROO!A109 | N10: 689 | P10: =sum(M10-O10)/O10 -> #DIV/0! | R10: =S10/$I$20 -> 0 | S10: =I10+M10 -> 0 | T10: ='2025'!B10+'2025'!C10 -> 1128 | U10: =sum(S10-T10)/T10 -> -1 | V10: =W10/$C$20 -> 0 | X10: 689 | Z10: =sum(W10-Y10)/Y10 -> #DIV/0! | AB10: =AC10/$I$20 -> 0 | AC10: =S10+W10 -> 0 | AD10: =SUM('2025'!B10:D10) -> 1128 | AE10: =sum(AC10-AD10)/AD10 -> -1 | AF10: =AG10/$C$20 -> 0 | AH10: 689 | AJ10: =sum(AG10-AI10)/AI10 -> #DIV/0! | AL10: =AM10/$I$20 -> 0 | AM10: =AC10+AG10 -> 0 | AN10: =SUM('2025'!B10:E10) -> 1128 | AO10: =sum(AM10-AN10)/AN10 -> -1 | AP10: =AQ10/$C$20 -> 0 | AR10: 689 | AT10: =sum(AQ10-AS10)/AS10 -> #DIV/0! | AV10: =AW10/$I$20 -> 0 | AW10: =AM10+AQ10 -> 0 | AX10: =SUM('2025'!B10:F10) -> 1128 | AY10: =sum(AW10-AX10)/AX10 -> -1
A11: Tiktok | B11: =C11/$C$20 -> 0.0051087158 | C11: =TIKTOK!A108 -> 2414 | D11: 689 | F11: =sum(C11-E11)/E11 -> #DIV/0! | H11: =I11/$I$20 -> 0.0058432565 | I11: =C11 -> 2414 | J11: 2035 | K11: =sum(I11-J11)/J11 -> 0.18624079 | L11: =M11/$C$20 -> 0.0088206824 | M11: =TIKTOK!A109 -> 4168 | N11: 689 | P11: =sum(M11-O11)/O11 -> #DIV/0! | R11: =S11/$I$20 -> 0.015932193 | S11: =I11+M11 -> 6582 | T11: ='2025'!B11+'2025'!C11 -> 3582 | U11: =sum(S11-T11)/T11 -> 0.83752094 | V11: =W11/$C$20 -> 0.017979971 | W11: =TIKTOK!A110 -> 8496 | X11: 689 | Z11: =sum(W11-Y11)/Y11 -> #DIV/0! | AB11: =AC11/$I$20 -> 0.036497357 | AC11: =S11+W11 -> 15078 | AD11: =SUM('2025'!B11:D11) -> 6105 | AE11: =sum(AC11-AD11)/AD11 -> 1.4697789 | AF11: =AG11/$C$20 -> 0.027499028 | AG11: =TIKTOK!A111 -> 12994 | AH11: 689 | AJ11: =sum(AG11-AI11)/AI11 -> #DIV/0! | AL11: =AM11/$I$20 -> 0.067950247 | AM11: =AC11+AG11 -> 28072 | AN11: =SUM('2025'!B11:E11) -> 6714 | AO11: =sum(AM11-AN11)/AN11 -> 3.1811141 | AP11: =AQ11/$C$20 -> 0.0019850768 | AQ11: =TIKTOK!A112 -> 938 | AR11: 689 | AT11: =sum(AQ11-AS11)/AS11 -> #DIV/0! | AV11: =AW11/$I$20 -> 0.070220741 | AW11: =AM11+AQ11 -> 29010 | AX11: =SUM('2025'!B11:F11) -> 7043 | AY11: =sum(AW11-AX11)/AX11 -> 3.1189834
A12: World Plaza | B12: =C12/$C$20 -> 0.024389779 | C12: 11524.8 | D12: 11524.8 | F12: =sum(C12-E12)/E12 -> #DIV/0! | H12: =I12/$I$20 -> 0.027896587 | I12: =C12 -> 11524.8 | J12: 11524.8 | K12: =sum(I12-J12)/J12 -> 0 | L12: =M12/$C$20 -> 0.024389779 | M12: 11524.8 | N12: 11524.8 | P12: =sum(M12-O12)/O12 -> #DIV/0! | R12: =S12/$I$20 -> 0.055793175 | S12: =I12+M12 -> 23049.6 | T12: ='2025'!B12+'2025'!C12 -> 23049.6 | U12: =sum(S12-T12)/T12 -> 0 | V12: =W12/$C$20 -> 0.024389779 | W12: 11524.8 | X12: 11524.8 | Z12: =sum(W12-Y12)/Y12 -> #DIV/0! | AB12: =AC12/$I$20 -> 0.083689762 | AC12: =S12+W12 -> 34574.4 | AD12: =SUM('2025'!B12:D12) -> 34574.4 | AE12: =sum(AC12-AD12)/AD12 -> 0 | AF12: =AG12/$C$20 -> 0.024389779 | AG12: 11524.8 | AH12: 11524.8 | AJ12: =sum(AG12-AI12)/AI12 -> #DIV/0! | AL12: =AM12/$I$20 -> 0.11158635 | AM12: =AC12+AG12 -> 46099.2 | AN12: =SUM('2025'!B12:E12) -> 46099.2 | AO12: =sum(AM12-AN12)/AN12 -> 0 | AP12: =AQ12/$C$20 -> 0.024389779 | AQ12: 11524.8 | AR12: 11524.8 | AT12: =sum(AQ12-AS12)/AS12 -> #DIV/0! | AV12: =AW12/$I$20 -> 0.13948294 | AW12: =AM12+AQ12 -> 57624 | AX12: =SUM('2025'!B12:F12) -> 57624 | AY12: =sum(AW12-AX12)/AX12 -> 0
A13: The Finance | B13: =C13/$C$20 -> 0.07407003 | C13: 35000 | D13: 25000 | F13: =sum(C13-E13)/E13 -> #DIV/0! | H13: =I13/$I$20 -> 0.084719957 | I13: =C13 -> 35000 | J13: 25000 | K13: =sum(I13-J13)/J13 -> 0.4 | L13: =M13/$C$20 -> 0.07407003 | M13: 35000 | N13: 25000 | P13: =sum(M13-O13)/O13 -> #DIV/0! | R13: =S13/$I$20 -> 0.16943991 | S13: =I13+M13 -> 70000 | T13: ='2025'!B13+'2025'!C13 -> 52500 | U13: =sum(S13-T13)/T13 -> 0.33333333 | V13: =W13/$C$20 -> 0.07407003 | W13: 35000 | X13: 25000 | Z13: =sum(W13-Y13)/Y13 -> #DIV/0! | AB13: =AC13/$I$20 -> 0.25415987 | AC13: =S13+W13 -> 105000 | AD13: =SUM('2025'!B13:D13) -> 80000 | AE13: =sum(AC13-AD13)/AD13 -> 0.3125 | AF13: =AG13/$C$20 -> 0.07407003 | AG13: 35000 | AH13: 25000 | AJ13: =sum(AG13-AI13)/AI13 -> #DIV/0! | AL13: =AM13/$I$20 -> 0.33887983 | AM13: =AC13+AG13 -> 140000 | AN13: =SUM('2025'!B13:E13) -> 107500 | AO13: =sum(AM13-AN13)/AN13 -> 0.30232558 | AP13: =AQ13/$C$20 -> 0.07407003 | AQ13: 35000 | AR13: 25000 | AT13: =sum(AQ13-AS13)/AS13 -> #DIV/0! | AV13: =AW13/$I$20 -> 0.42359978 | AW13: =AM13+AQ13 -> 175000 | AX13: =SUM('2025'!B13:F13) -> 107500 | AY13: =sum(AW13-AX13)/AX13 -> 0.62790698
A14: Seibu | B14: =C14/$C$20 -> 0.025395439 | C14: 12000 | D14: 12000 | F14: =sum(C14-E14)/E14 -> #DIV/0! | H14: =I14/$I$20 -> 0.029046842 | I14: =C14 -> 12000 | J14: 12000 | K14: =sum(I14-J14)/J14 -> 0 | L14: =M14/$C$20 -> 0.025395439 | M14: 12000 | N14: 12000 | P14: =sum(M14-O14)/O14 -> #DIV/0! | R14: =S14/$I$20 -> 0.058093685 | S14: =I14+M14 -> 24000 | T14: ='2025'!B14+'2025'!C14 -> 24000 | U14: =sum(S14-T14)/T14 -> 0 | V14: =W14/$C$20 -> 0.025395439 | W14: 12000 | X14: 12000 | Z14: =sum(W14-Y14)/Y14 -> #DIV/0! | AB14: =AC14/$I$20 -> 0.087140527 | AC14: =S14+W14 -> 36000 | AD14: =SUM('2025'!B14:D14) -> 36000 | AE14: =sum(AC14-AD14)/AD14 -> 0 | AF14: =AG14/$C$20 -> 0.025395439 | AG14: 12000 | AH14: 12000 | AJ14: =sum(AG14-AI14)/AI14 -> #DIV/0! | AL14: =AM14/$I$20 -> 0.11618737 | AM14: =AC14+AG14 -> 48000 | AN14: =SUM('2025'!B14:E14) -> 48000 | AO14: =sum(AM14-AN14)/AN14 -> 0 | AP14: =AQ14/$C$20 -> 0.025395439 | AQ14: 12000 | AR14: 12000 | AT14: =sum(AQ14-AS14)/AS14 -> #DIV/0! | AV14: =AW14/$I$20 -> 0.14523421 | AW14: =AM14+AQ14 -> 60000 | AX14: =SUM('2025'!B14:F14) -> 60000 | AY14: =sum(AW14-AX14)/AX14 -> 0
A15: Grasshopper Concept | B15: =C15/$C$20 -> 0 | D15: 6000 | F15: =sum(C15-E15)/E15 -> #DIV/0! | H15: =I15/$I$20 -> 0 | I15: =C15 | J15: 6000 | K15: =sum(I15-J15)/J15 -> -1 | L15: =M15/$C$20 -> 0 | N15: 6000 | P15: =sum(M15-O15)/O15 -> #DIV/0! | R15: =S15/$I$20 -> 0 | S15: =I15+M15 -> 0 | T15: ='2025'!B15+'2025'!C15 -> 6000 | U15: =sum(S15-T15)/T15 -> -1 | V15: =W15/$C$20 -> 0 | X15: 6000 | Z15: =sum(W15-Y15)/Y15 -> #DIV/0! | AB15: =AC15/$I$20 -> 0 | AC15: =S15+W15 -> 0 | AD15: =SUM('2025'!B15:D15) -> 6000 | AE15: =sum(AC15-AD15)/AD15 -> -1 | AF15: =AG15/$C$20 -> 0 | AH15: 6000 | AJ15: =sum(AG15-AI15)/AI15 -> #DIV/0! | AL15: =AM15/$I$20 -> 0 | AM15: =AC15+AG15 -> 0 | AN15: =SUM('2025'!B15:E15) -> 6000 | AO15: =sum(AM15-AN15)/AN15 -> -1 | AP15: =AQ15/$C$20 -> 0 | AR15: 6000 | AT15: =sum(AQ15-AS15)/AS15 -> #DIV/0! | AV15: =AW15/$I$20 -> 0 | AW15: =AM15+AQ15 -> 0 | AX15: =SUM('2025'!B15:F15) -> 6000 | AY15: =sum(AW15-AX15)/AX15 -> -1
A16: Haleon | B16: =C16/$C$20 -> 0.023279152 | C16: 11000 | D16: 11000 | F16: =sum(C16-E16)/E16 -> #DIV/0! | H16: =I16/$I$20 -> 0.026626272 | I16: =C16 -> 11000 | K16: =sum(I16-J16)/J16 -> #DIV/0! | L16: =M16/$C$20 -> 0.023279152 | M16: 11000 | N16: 11000 | P16: =sum(M16-O16)/O16 -> #DIV/0! | R16: =S16/$I$20 -> 0.053252544 | S16: =I16+M16 -> 22000 | T16: ='2025'!B16+'2025'!C16 -> 0 | U16: =sum(S16-T16)/T16 -> #DIV/0! | V16: =W16/$C$20 -> 0.023279152 | W16: 11000 | X16: 11000 | Z16: =sum(W16-Y16)/Y16 -> #DIV/0! | AB16: =AC16/$I$20 -> 0.079878817 | AC16: =S16+W16 -> 33000 | AD16: =SUM('2025'!B16:D16) -> 0 | AE16: =sum(AC16-AD16)/AD16 -> #DIV/0! | AF16: =AG16/$C$20 -> 0.023279152 | AG16: 11000 | AH16: 11000 | AJ16: =sum(AG16-AI16)/AI16 -> #DIV/0! | AL16: =AM16/$I$20 -> 0.10650509 | AM16: =AC16+AG16 -> 44000 | AN16: =SUM('2025'!B16:E16) -> 0 | AO16: =sum(AM16-AN16)/AN16 -> #DIV/0! | AP16: =AQ16/$C$20 -> 0.023279152 | AQ16: 11000 | AR16: 11000 | AT16: =sum(AQ16-AS16)/AS16 -> #DIV/0! | AV16: =AW16/$I$20 -> 0.13313136 | AW16: =AM16+AQ16 -> 55000 | AX16: =SUM('2025'!B16:F16) -> 0 | AY16: =sum(AW16-AX16)/AX16 -> #DIV/0!
A17: AyalaLand - One Ayala | B17: =C17/$C$20 -> 0.10564079 | C17: 49918 | F17: =sum(C17-E17)/E17 -> #DIV/0! | H17: =I17/$I$20 -> 0.12083002 | I17: =C17 -> 49918 | L17: =M17/$C$20 -> 0.10564079 | M17: 49918 | P17: =sum(M17-O17)/O17 -> #DIV/0! | R17: =S17/$I$20 -> 0.24166005 | S17: =I17+M17 -> 99836 | T17: ='2025'!B17+'2025'!C17 -> 0 | V17: =W17/$C$20 -> 0.10564079 | W17: 49918 | Z17: =sum(W17-Y17)/Y17 -> #DIV/0! | AB17: =AC17/$I$20 -> 0.36249007 | AC17: =S17+W17 -> 149754 | AD17: =SUM('2025'!B17:D17) -> 0 | AF17: =AG17/$C$20 -> 0.10564079 | AG17: 49918 | AJ17: =sum(AG17-AI17)/AI17 -> #DIV/0! | AL17: =AM17/$I$20 -> 0.48332009 | AM17: =AC17+AG17 -> 199672 | AN17: =SUM('2025'!B17:E17) -> 0 | AP17: =AQ17/$C$20 -> 0.10564079 | AQ17: 49918 | AT17: =sum(AQ17-AS17)/AS17 -> #DIV/0! | AV17: =AW17/$I$20 -> 0.60415012 | AW17: =AM17+AQ17 -> 249590 | AX17: =SUM('2025'!B17:F17) -> 0
A18: AyalaLand - Greenbelt | B18: =C18/$C$20 -> 0.12570742 | C18: 59400 | F18: =sum(C18-E18)/E18 -> #DIV/0! | H18: =I18/$I$20 -> 0 | L18: =M18/$C$20 -> 0.12570742 | M18: 59400 | P18: =sum(M18-O18)/O18 -> #DIV/0! | R18: =S18/$I$20 -> 0.14378187 | S18: =I18+M18 -> 59400 | T18: ='2025'!B20+'2025'!C20 -> 780791.6 | V18: =W18/$C$20 -> 0.12570742 | W18: 59400 | Z18: =sum(W18-Y18)/Y18 -> #DIV/0! | AB18: =AC18/$I$20 -> 0.28756374 | AC18: =S18+W18 -> 118800 | AD18: =SUM('2025'!B18:D18) -> 0 | AF18: =AG18/$C$20 -> 0.12570742 | AG18: 59400 | AJ18: =sum(AG18-AI18)/AI18 -> #DIV/0! | AL18: =AM18/$I$20 -> 0.43134561 | AM18: =AC18+AG18 -> 178200 | AN18: =SUM('2025'!B18:E18) -> 0 | AP18: =AQ18/$C$20 -> 0 | AT18: =sum(AQ18-AS18)/AS18 -> #DIV/0! | AV18: =AW18/$I$20 -> 0.43134561 | AW18: =AM18+AQ18 -> 178200 | AX18: =SUM('2025'!B18:F18) -> 0
A19: Bazaar | B19: =C19/$C$20 -> 0 | F19: =sum(C19-E19)/E19 -> #DIV/0! | H19: =I19/$I$20 -> 0 | I19: =C19 | K19: =sum(I19-J19)/J19 -> #DIV/0! | L19: =M19/$C$20 -> 0 | P19: =sum(M19-O19)/O19 -> #DIV/0! | R19: =S19/$I$20 -> 0 | S19: =I19+M19 -> 0 | U19: =sum(S19-T19)/T19 -> #DIV/0! | V19: =W19/$C$20 -> 0 | Z19: =sum(W19-Y19)/Y19 -> #DIV/0! | AB19: =AC19/$I$20 -> 0 | AC19: =S19+W19 -> 0 | AE19: =sum(AC19-AD19)/AD19 -> #DIV/0! | AF19: =AG19/$C$20 -> 0 | AJ19: =sum(AG19-AI19)/AI19 -> #DIV/0! | AL19: =AM19/$I$20 -> 0 | AM19: =AC19+AG19 -> 0 | AN19: =SUM('2025'!B19:E19) -> 0 | AO19: =sum(AM19-AN19)/AN19 -> #DIV/0! | AP19: =AQ19/$C$20 -> 0 | AT19: =sum(AQ19-AS19)/AS19 -> #DIV/0! | AV19: =AW19/$I$20 -> 0 | AW19: =AM19+AQ19 -> 0 | AX19: =SUM('2025'!B19:F19) -> 0 | AY19: =sum(AW19-AX19)/AX19 -> #DIV/0!
A20: TOTAL WITH INDUSTRIAL | B20: =SUM(B2:B19) -> 1 | C20: =SUM(C2:C19) -> 472525.8 | D20: =SUM(D2:D19) -> 511044.8 | F20: =sum(C20-E20)/E20 -> #DIV/0! | G20: =SUM(G2:G19) -> 0 | H20: =SUM(H2:H19) -> 1 | I20: =SUM(I2:I19) -> 413125.8 | J20: =SUM(J2:J19) -> 454231.8 | K20: =sum(I20-J20)/J20 -> -0.090495646 | L20: =SUM(L2:L19) -> 0.9044285 | M20: =SUM(M2:M19) -> 427365.8 | N20: =SUM(N2:N19) -> 511044.8 | P20: =sum(M20-O20)/O20 -> #DIV/0! | Q20: =SUM(Q2:Q19) -> 0 | R20: =SUM(R2:R19) -> 2.0344689 | S20: =SUM(S2:S19) -> 840491.6 | T20: =SUM(T2:T19) -> 1561583.2 | U20: =sum(S20-T20)/T20 -> -0.46176957 | V20: =SUM(V2:V19) -> 0.86400108 | W20: =SUM(W2:W19) -> 408262.8 | X20: =SUM(X2:X19) -> 511044.8 | Z20: =sum(W20-Y20)/Y20 -> #DIV/0! | AA20: =SUM(AA2:AA19) -> 0 | AB20: =SUM(AB2:AB19) -> 3.0226977 | AC20: =SUM(AC2:AC19) -> 1248754.4 | AD20: =SUM(AD2:AD19) -> 1102868.4 | AE20: =sum(AC20-AD20)/AD20 -> 0.1322787 | AF20: =SUM(AF2:AF19) -> 0.89763522 | AG20: =SUM(AG2:AG19) -> 424155.8 | AH20: =SUM(AH2:AH19) -> 511044.8 | AJ20: =sum(AG20-AI20)/AI20 -> #DIV/0! | AK20: =SUM(AK2:AK19) -> 0 | AL20: =SUM(AL2:AL19) -> 4.0493966 | AM20: =SUM(AM2:AM19) -> 1672910.2 | AN20: =SUM(AN2:AN19) -> 1415272.2 | AO20: =sum(AM20-AN20)/AN20 -> 0.18204131 | AP20: =SUM(AP2:AP19) -> 0.42226012 | AQ20: =SUM(AQ2:AQ19) -> 199528.8 | AR20: =SUM(AR2:AR19) -> 511044.8 | AT20: =sum(AQ20-AS20)/AS20 -> #DIV/0! | AU20: =SUM(AU2:AU19) -> 0 | AV20: =SUM(AV2:AV19) -> 4.53237 | AW20: =SUM(AW2:AW19) -> 1872439 | AX20: =SUM(AX2:AX19) -> 1733750 | AY20: =sum(AW20-AX20)/AX20 -> 0.079993655
A22: INDUSTRIAL | C22: =sum(C12:C16) -> 69524.8 | F22: =sum(C22-E22)/E22 -> #DIV/0! | I22: =sum(I12:I16) -> 69524.8 | J22: =sum(J12:J16) -> 54524.8 | K22: =sum(I22-J22)/J22 -> 0.27510417 | M22: =sum(M12:M16) -> 69524.8 | P22: =sum(M22-O22)/O22 -> #DIV/0! | S22: =sum(S12:S16) -> 139049.6 | T22: =sum(T12:T16) -> 105549.6 | U22: =sum(S22-T22)/T22 -> 0.31738633 | W22: =sum(W12:W16) -> 69524.8 | Z22: =sum(W22-Y22)/Y22 -> #DIV/0! | AC22: =sum(AC12:AC16) -> 208574.4 | AD22: =sum(AD12:AD16) -> 156574.4 | AE22: =sum(AC22-AD22)/AD22 -> 0.33211049 | AG22: =sum(AG12:AG16) -> 69524.8 | AJ22: =sum(AG22-AI22)/AI22 -> #DIV/0! | AM22: =sum(AM12:AM16) -> 278099.2 | AN22: =sum(AN12:AN16) -> 207599.2 | AO22: =sum(AM22-AN22)/AN22 -> 0.33959668 | AQ22: =sum(AQ12:AQ16) -> 69524.8 | AT22: =sum(AQ22-AS22)/AS22 -> #DIV/0! | AW22: =sum(AW12:AW16) -> 347624 | AX22: =sum(AX12:AX16) -> 231124 | AY22: =sum(AW22-AX22)/AX22 -> 0.50405843
A23: RETAIL | C23: =sum(C2:C6) -> 209965 | D23: =sum(D2:D6) -> 237211 | I23: =sum(I2:I6) -> 209965 | J23: =sum(J2:J6) -> 278555 | M23: =sum(M2:M6) -> 162128 | N23: =sum(N2:N6) -> 237211 | S23: =sum(S2:S6) -> 372093 | T23: =sum(T2:T6) -> 433244 | W23: =sum(W2:W6) -> 138039 | X23: =sum(X2:X6) -> 237211 | AC23: =sum(AC2:AC6) -> 510132 | AD23: =sum(AD2:AD6) -> 610997 | AG23: =sum(AG2:AG6) -> 133130 | AH23: =sum(AH2:AH6) -> 237211 | AM23: =sum(AM2:AM6) -> 643262 | AN23: =sum(AN2:AN6) -> 753664 | AQ23: =sum(AQ2:AQ6) -> 0 | AR23: =sum(AR2:AR6) -> 237211 | AW23: =sum(AW2:AW6) -> 643262 | AX23: =sum(AX2:AX6) -> 946051
A24: ECOMMERCE | C24: =sum(C7:C11) -> 83718 | D24: =sum(D7:D11) -> 208309 | F24: =sum(C24-E24)/E24 -> #DIV/0! | G24: =sum(G7:G11) -> 0 | H24: =sum(H7:H11) -> 0.2026453 | I24: =sum(I7:I11) -> 83718 | J24: =sum(J7:J11) -> 121152 | K24: =sum(I24-J24)/J24 -> -0.30898376 | M24: =sum(M7:M11) -> 86395 | N24: =sum(N7:N11) -> 208309 | P24: =sum(M24-O24)/O24 -> #DIV/0! | Q24: =sum(Q7:Q11) -> 0 | R24: =sum(R7:R11) -> 0.41177046 | S24: =sum(S7:S11) -> 170113 | T24: =sum(T7:T11) -> 241998 | U24: =sum(S24-T24)/T24 -> -0.29704791 | W24: =sum(W7:W11) -> 91381 | X24: =sum(X7:X11) -> 208309 | Z24: =sum(W24-Y24)/Y24 -> #DIV/0! | AA24: =sum(AA7:AA11) -> 0 | AB24: =sum(AB7:AB11) -> 0.63296458 | AC24: =sum(AC7:AC11) -> 261494 | AD24: =sum(AD7:AD11) -> 335297 | AE24: =sum(AC24-AD24)/AD24 -> -0.22011232 | AG24: =sum(AG7:AG11) -> 112183 | AH24: =sum(AH7:AH11) -> 208309 | AJ24: =sum(AG24-AI24)/AI24 -> #DIV/0! | AK24: =sum(AK7:AK11) -> 0 | AL24: =sum(AL7:AL11) -> 0.90451141 | AM24: =sum(AM7:AM11) -> 373677 | AN24: =sum(AN7:AN11) -> 454009 | AO24: =sum(AM24-AN24)/AN24 -> -0.17693922 | AQ24: =sum(AQ7:AQ11) -> 80086 | AR24: =sum(AR7:AR11) -> 208309 | AT24: =sum(AQ24-AS24)/AS24 -> #DIV/0! | AU24: =sum(AU7:AU11) -> 0 | AV24: =sum(AV7:AV11) -> 1.0983652 | AW24: =sum(AW7:AW11) -> 453763 | AX24: =sum(AX7:AX11) -> 556575 | AY24: =sum(AW24-AX24)/AX24 -> -0.18472263
A25: TOTAL

Sheet ONLINE SUMMARY
C1: TOTAL SOLD OF STOCKS FOR LAZADA, SHOPEE , SHOPIFY, TIKTOK AND PICKAROO
C2: TOTAL IN VOLUME
A3: VARIANT | B3: PRICE | C3: JAN | D3: FEB | E3: MAR | F3: APR | G3: MAY | H3: JUN | I3: JUL | J3: AUG | K3: SEP | L3: OCT | M3: NOV | N3: DEC
A5: Quiet Elegance | B5: 329
A6: Charming Home | B6: 329
A7: Bright Mornings | B7: 329
A8: Relaxing Naturals | B8: 329 | C8: =LAZADA!U8+SHOPEE!CE8+SHOPIFY!F8+TIKTOK!G8+PICKAROO!N8 -> 16
A9: Mountain Breeze | B9: 329 | C9: =LAZADA!U9+SHOPEE!CE9+SHOPIFY!F9+TIKTOK!G9+PICKAROO!N9 -> 0
A10: Fresh Bamboo | B10: 329 | C10: =LAZADA!U10+SHOPEE!CE10+SHOPIFY!F10+TIKTOK!G10+PICKAROO!N10 -> 30
A11: Beach Escape | B11: 329 | C11: =LAZADA!U11+SHOPEE!CE11+SHOPIFY!F11+TIKTOK!G11+PICKAROO!N11 -> 5
A12: White Tea | B12: 329 | C12: =LAZADA!U12+SHOPEE!CE12+SHOPIFY!F12+TIKTOK!G12+PICKAROO!N12 -> 14
A13: Candy Cane | B13: 329 | C13: =LAZADA!U13+SHOPEE!CE13+SHOPIFY!F13+TIKTOK!G13+PICKAROO!N13 -> 3
A14: Apple Cinnamon | B14: 329 | C14: =LAZADA!U14+SHOPEE!CE14+SHOPIFY!F14+TIKTOK!G14+PICKAROO!N14 -> 9
A15: Easy Drive | B15: 219 | C15: =LAZADA!U15+SHOPEE!CE15+SHOPIFY!F15+TIKTOK!G15+PICKAROO!N15 -> 1
A16: InLove | C16: =LAZADA!U16+SHOPEE!CE16+SHOPIFY!F16+TIKTOK!G16+PICKAROO!N16 -> 0
A17: Bright Mornings HW | C17: =LAZADA!U17+SHOPEE!CE17+SHOPIFY!F17+TIKTOK!G17+PICKAROO!N17 -> 0
C18: =LAZADA!U18+SHOPEE!CE18+SHOPIFY!F18+TIKTOK!G18+PICKAROO!N18 -> 0
A19: Lavender | B19: 239 | C19: =LAZADA!U19+SHOPEE!CE19+SHOPIFY!F19+TIKTOK!G19+PICKAROO!N19 -> 2
A20: Eucalyptus | B20: 239 | C20: =LAZADA!U20+SHOPEE!CE20+SHOPIFY!F20+TIKTOK!G20+PICKAROO!N20 -> 3
A21: Peppermint | B21: 239 | C21: =LAZADA!U21+SHOPEE!CE21+SHOPIFY!F21+TIKTOK!G21+PICKAROO!N21 -> 1
A22: Fresh Bamboo FO | B22: 219 | C22: =LAZADA!U22+SHOPEE!CE22+SHOPIFY!F22+TIKTOK!G22+PICKAROO!N22 -> 3
A23: Beach Escape FO | B23: 219 | C23: =LAZADA!U23+SHOPEE!CE23+SHOPIFY!F23+TIKTOK!G23+PICKAROO!N23 -> 1
A24: White Tea FO | B24: 219 | C24: =LAZADA!U24+SHOPEE!CE24+SHOPIFY!F24+TIKTOK!G24+PICKAROO!N24 -> 0
A25: Bright Mornings FO | B25: 219 | C25: =LAZADA!U25+SHOPEE!CE25+SHOPIFY!F25+TIKTOK!G25+PICKAROO!N25 -> 0
A26: Quiet Elegance FO | B26: 219 | C26: =LAZADA!U26+SHOPEE!CE26+SHOPIFY!F26+TIKTOK!G26+PICKAROO!N26 -> 0
A27: Fresh Bamboo Diffuser | B27: 799 | C27: =LAZADA!U27+SHOPEE!CE27+SHOPIFY!F27+TIKTOK!G27+PICKAROO!N27 -> 2
A28: Clean Air | B28: 609 | C28: =LAZADA!U28+SHOPEE!CE28+SHOPIFY!F28+TIKTOK!G28+PICKAROO!N28 -> 6
A29: Cotton Clean | B29: 329 | C29: =LAZADA!U29+SHOPEE!CE29+SHOPIFY!F29+TIKTOK!G29+PICKAROO!N29 -> 24
A30: Brighter Days | B30: 329 | C30: =LAZADA!U30+SHOPEE!CE30+SHOPIFY!F30+TIKTOK!G30+PICKAROO!N30 -> 0
... A48: Simoy ng Pahiyas | B48: 0 | C48: =LAZADA!U48+SHOPEE!CE48+SHOPIFY!F48+TIKTOK!G48+PICKAROO!N48 -> 0
C49: =LAZADA!U49+SHOPEE!CE49+SHOPIFY!F49+TIKTOK!G49+PICKAROO!N49 -> 0
A50: Fresh Bamboo 500ml | B50: 609 | C50: =LAZADA!U50+SHOPEE!CE50+SHOPIFY!F50+TIKTOK!G50+PICKAROO!N50 -> 13
A51: White Tea 500ml | B51: 609 | C51: =LAZADA!U51+SHOPEE!CE51+SHOPIFY!F51+TIKTOK!G51+PICKAROO!N51 -> 3
A52: Tropical Paradise 200ml | B52: 329 | C52: =LAZADA!U52+SHOPEE!CE52+SHOPIFY!F52+TIKTOK!G52+PICKAROO!N52 -> 2
A53: RN Wash 100ml | B53: 199 | C53: =LAZADA!U53+SHOPEE!CE53+SHOPIFY!F53+TIKTOK!G53+PICKAROO!N53 -> 0
A54: CB Wash 100ml | B54: 199 | C54: =LAZADA!U54+SHOPEE!CE54+SHOPIFY!F54+TIKTOK!G54+PICKAROO!N54 -> 0
A55: Travel With Me | B55: 599 | C55: =LAZADA!U55+SHOPEE!CE55+SHOPIFY!F55+TIKTOK!G55+PICKAROO!N55 -> 0
A56: Handwash: Relaxing Naturals Gallon | B56: 1499 | C56: =LAZADA!U56+SHOPEE!CE56+SHOPIFY!F56+TIKTOK!G56+PICKAROO!N56 -> 0
C57: =LAZADA!U57+SHOPEE!CE57+SHOPIFY!F57+TIKTOK!G57+PICKAROO!N57 -> 0
A58: Creamy Matcha | B58: 329 | C58: =LAZADA!U58+SHOPEE!CE58+SHOPIFY!F58+TIKTOK!G58+PICKAROO!N58 -> 8
A59: White Lavender | B59: 329 | C59: =LAZADA!U59+SHOPEE!CE59+SHOPIFY!F59+TIKTOK!G59+PICKAROO!N59 -> 3
A60: Green Tea | B60: 329 | C60: =LAZADA!U60+SHOPEE!CE60+SHOPIFY!F60+TIKTOK!G60+PICKAROO!N60 -> 8
A61: Clean Air 100ml | B61: 249 | C61: =LAZADA!U61+SHOPEE!CE61+SHOPIFY!F61+TIKTOK!G61+PICKAROO!N61 -> 1
A62: Creamy Matcha Diffuser Refill | B62: 439 | C62: =LAZADA!U62+SHOPEE!CE62+SHOPIFY!F62+TIKTOK!G62+PICKAROO!N62 -> 0
A63: White Lavender Diffuser Refill | B63: 439 | C63: =LAZADA!U63+SHOPEE!CE63+SHOPIFY!F63+TIKTOK!G63+PICKAROO!N63 -> 7
A64: Green Tea Diffuser Refill | B64: 439 | C64: =LAZADA!U64+SHOPEE!CE64+SHOPIFY!F64+TIKTOK!G64+PICKAROO!N64 -> 1
A65: Creamy Matcha Diffuser | B65: 799 | C65: =LAZADA!U65+SHOPEE!CE65+SHOPIFY!F65+TIKTOK!G65+PICKAROO!N65 -> 0
A66: White Lavender Diffuser | B66: 799 | C66: =LAZADA!U66+SHOPEE!CE66+SHOPIFY!F66+TIKTOK!G66+PICKAROO!N66 -> 1
A67: Green Tea Diffuser | B67: 799 | C67: =LAZADA!U67+SHOPEE!CE67+SHOPIFY!F67+TIKTOK!G67+PICKAROO!N67 -> 0
A68: Creamy Matcha + Roomspray | B68: 1299 | C68: =LAZADA!U68+SHOPEE!CE68+SHOPIFY!F68+TIKTOK!G68+PICKAROO!N68 -> 0
A69: White Lavender + Roomspray | B69: 1299 | C69: =LAZADA!U69+SHOPEE!CE69+SHOPIFY!F69+TIKTOK!G69+PICKAROO!N69 -> 0
... A74: Urban Oasis Reed Diffuser | B74: 999 | C74: =LAZADA!U74+SHOPEE!CE74+SHOPIFY!F74+TIKTOK!G74+PICKAROO!N74 -> 0
A75: Clean Air Gallon | C75: =LAZADA!U75+SHOPEE!CE75+SHOPIFY!F75+TIKTOK!G75+PICKAROO!N75 -> 1
C76: =LAZADA!U76+SHOPEE!CE76+SHOPIFY!F76+TIKTOK!G76+PICKAROO!N76 -> 0
A77: Holiday Hugs 200ml | B77: 379 | C77: =LAZADA!U77+SHOPEE!CE77+SHOPIFY!F77+TIKTOK!G77+PICKAROO!N77 -> 6
A78: Holiday Hugs Diffuser Set | B78: 799 | C78: =LAZADA!U78+SHOPEE!CE78+SHOPIFY!F78+TIKTOK!G78+PICKAROO!N78 -> 0
A79: Holiday Hugs Refill | B79: 439 | C79: =LAZADA!U79+SHOPEE!CE79+SHOPIFY!F79+TIKTOK!G79+PICKAROO!N79 -> 0
A80: Bathroom Kit | B80: 599 | C80: =LAZADA!U80+SHOPEE!CE80+SHOPIFY!F80+TIKTOK!G80+PICKAROO!N80 -> 0
A81: Flushie 50ml | B81: 229 | C81: =LAZADA!U81+SHOPEE!CE81+SHOPIFY!F81+TIKTOK!G81+PICKAROO!N81 -> 3
A82: Easy Drive Grapefuit | B82: 219 | C82: =LAZADA!U82+SHOPEE!CE82+SHOPIFY!F82+TIKTOK!G82+PICKAROO!N82 -> 1
A83: Fresh Bamboo Diffuser + Roomspray | B83: 1299 | C83: =LAZADA!U83+SHOPEE!CE83+SHOPIFY!F83+TIKTOK!G83+PICKAROO!N83 -> 1
A84: White Tea Diffuser + Roomspray | B84: 1299 | C84: =LAZADA!U84+SHOPEE!CE84+SHOPIFY!F84+TIKTOK!G84+PICKAROO!N84 -> 0
A85: Cotton Clean Diffuser + Roomspray | B85: 1299 | C85: =LAZADA!U85+SHOPEE!CE85+SHOPIFY!F85+TIKTOK!G85+PICKAROO!N85 -> 0
A86: Holiday Hugs Diffuser + Roomspray | B86: 1299 | C86: =LAZADA!U86+SHOPEE!CE86+SHOPIFY!F86+TIKTOK!G86+PICKAROO!N86 -> 0
C87: =LAZADA!U87+SHOPEE!CE87+SHOPIFY!F87+TIKTOK!G87+PICKAROO!N87 -> 0
A88: Sleep All Day | B88: 679 | C88: =LAZADA!U88+SHOPEE!CE88+SHOPIFY!F88+TIKTOK!G88+PICKAROO!N88 -> 0
A89: One Way Ticket | B89: 679 | C89: =LAZADA!U89+SHOPEE!CE89+SHOPIFY!F89+TIKTOK!G89+PICKAROO!N89 -> 0
A90: Holiday Cheer | B90: 679 | C90: =LAZADA!U90+SHOPEE!CE90+SHOPIFY!F90+TIKTOK!G90+PICKAROO!N90 -> 0
C91: =LAZADA!U91+SHOPEE!CE91+SHOPIFY!F91+TIKTOK!G91+PICKAROO!N91 -> 0
A92: High Enery Gift Set (Essential Oils) | B92: 490 | C92: =LAZADA!U92+SHOPEE!CE92+SHOPIFY!F92+TIKTOK!G92+PICKAROO!N92 -> 0
A93: Romantic Date Gift Set (Essential Oils) | B93: 490 | C93: =LAZADA!U93+SHOPEE!CE93+SHOPIFY!F93+TIKTOK!G93+PICKAROO!N93 -> 0
A94: One Way Ticket Gift Set (Fragrance Oils) | B94: 450 | C94: =LAZADA!U94+SHOPEE!CE94+SHOPIFY!F94+TIKTOK!G94+PICKAROO!N94 -> 0
A95: Family Reunion Gift Set (Fragrance Oils) | B95: 450 | C95: =LAZADA!U95+SHOPEE!CE95+SHOPIFY!F95+TIKTOK!G95+PICKAROO!N95 -> 0
C96: =LAZADA!U96+SHOPEE!CE96+SHOPIFY!F96+TIKTOK!G96+PICKAROO!N96 -> 0
A97: Fresh Start Kit | B97: 1054 | C97: =LAZADA!U97+SHOPEE!CE97+SHOPIFY!F97+TIKTOK!G97+PICKAROO!N97 -> 0
A98: Custom Order

Sheet LAZADA
C2: JANUARY
A3: VARIANT | B3: PRICE | C3: Emily Pugat | D3: Christopher Mark . | E3: Claude Ponce | F3: Nelson Alfonso | G3: Barry Sia Lao Uy | H3: Sittie Aliyyah | I3: Patricia Jo Agarri | J3: Sadiri Eric Sanda. | K3: kenneth.grateco | L3: Jasmine C. villareal | M3: Valerie Ann Arana.. | N3: Myrcel Servano | O3: Christine B Ojeda | P3: Rei | Q3: Gary Galino | R3: Ashley Macabalo | S3: Alma | T3: Rodney Leo Santos | X3: Anna Margarita S | Y3: Hazel delos santos | Z3: Benjie Belotindos | AA3: Freeze Y | AB3: Sofia Galang | AC3: Jenny Lyn Castro | AD3: Julie Anne Garcia | AE3: Paula Madla Tuazon | AF3: Jessa Tabat Aranas | AG3: Grace Pascua | AH3: Marissa San Pedro | AI3: Jacqueline Batala. | AJ3: Melanie Montemayo. | AK3: Christopher Mark | AL3: Roj Tirona | AM3: Paula Madla Tuazon | AN3: Efren Cruz De Castro | AO3: Hermalyne Mediano | AP3: Third-Party-User | AQ3: Noel Joson | AR3: Sharon Garcia Cortez | AS3: China Golez | AT3: Aj Bobiles Naling | AU3: Shirley Petrasant.. | AV3: Rowena Alabado | AW3: Farzad Bahadoran | BA3: Trisha Yu | BB3: Josefino Mapor Co | BC3: Sara Jane Paderes | BD3: Ela Banaag | BE3: Rowleene | BF3: Rowena A. | BG3: Lei M. | BH3: Joji | BI3: TwoHun | BJ3: Sadiri Eric Sanda | BK3: Cynthia Ducalang BD | BL3: Tristram David | BM3: Sadiri Eric Sanda. | BN3: Mary Grace R. | BO3: Jen | BP3: Karen Faye Bathan | BQ3: Christopher | BR3: 917 | BS3: JessaA | BT3: 947 | BU3: Rainer | BV3: Rowlene | BW3: James Holand | BX3: Marlyn | BY3: Mary Grace | CD3: Sheen Patrick S | CE3: Jelen Perlas P | CF3: Marlyn Lao | CG3: Ronald Nepomuceno. | CH3: Mariel Zamora | CI3: Sidney Alan Tagle | CJ3: Derick John Mestio | CK3: Orlando III Cabud | CL3: Dhivya R | CM3: Napoleon banzuela | CN3: Ninty four | CO3: Rowena Alabado | CP3: Danny Santillan | CQ3: Rizalyn Rodriguez | CR3: MF Jawid | CS3: MERLA LAINE FLORE | CT3: Emily Mediodia P | CU3: One Two | CV3: Honelet Cumabig | CW3: Anabel Manuel | CX3: carolyn calanoy | CY3: Nine | CZ3: Maria Crizelda C | DA3: Sheila Constantin. | DB3: Lean Ramirez Angel | DC3: Luisa Rivero | DD3: Prosperity | DE3: Marissa San Pedro | DF3: Ethelene Gamboa | DG3: melody clark | DH3: Leonard Sy Gaw | DL3: Jeanefer RUIZ | DM3: Maria Joy Camacho | DN3: Ruel Linas Dael | DO3: Jaime Olbes | DP3: Nelson Baloloy Og | DQ3: jim contes | DR3: Noel reginald Tam | DS3: Marie Belen Erfe | DT3: Ma Christina Jaci. | DU3: Sixseven | DV3: Stephen Liam Ybud. | DW3: Ma Luisa | DX3: Monchito | DY3: Sixseven | DZ3: Ronel Erpe Eva | EA3: Nory | EB3: Paula Eunice | EC3: Noel reginald T | ED3: Lyn Yumang | EE3: Jonas Polines | EF3: Carmela A. | EG3: Elaine Torrejo | EH3: Sixty | EI3: Tristan Jerome Pa.. | EJ3: Hamid | EK3: Maria Camille Amba | EL3: Love | EM3: Seven8 | EN3: Ken My | EO3: Christine Buenvia | EP3: Sheen Patrick Sor | EQ3: Twohun
C4: 45658 | D4: 45661 | E4: 45662 | F4: 45662 | G4: 45662 | H4: 45663 | I4: 45666 | J4: 45670 | K4: 45670 | L4: 45671 | M4: 45672 | N4: 45676 | O4: 45677 | P4: 45683 | Q4: 45685 | R4: 45687 | S4: 45687 | T4: 45687 | X4: 45689 | Y4: 45690 | Z4: 45691 | AA4: 45691 | AB4: 45691 | AC4: 45691 | AD4: 45692 | AE4: 45693 | AF4: 45694 | AG4: 45695 | AH4: 45696 | AI4: 45696 | AJ4: 45696 | AK4: 45697 | AL4: 45698 | AM4: 45706 | AN4: 45707 | AO4: 45708 | AP4: 45709 | AQ4: 45710 | AR4: 45710 | AS4: 45710 | AT4: 45713 | AU4: 45713 | AV4: 45714 | AW4: 45715 | BA4: 45717 | BB4: 45718 | BC4: 45719 | BD4: 45719 | BE4: 45720 | BF4: 45724 | BG4: 45722 | BH4: 45723 | BI4: 45728 | BJ4: 45730 | BK4: 45731 | BL4: 45732 | BM4: 45733 | BN4: 45734 | BO4: 45736 | BP4: 45737 | BQ4: 45738 | BR4: 45739 | BS4: 45740 | BT4: 45741 | BU4: 45742 | BV4: 45743 | BW4: 45744 | BX4: 45745 | BY4: 45746 | CD4: 45749 | CE4: 45750 | CF4: 45751 | CG4: 45751 | CH4: 45752 | CI4: 45754 | CJ4: 45754 | CK4: 45757 | CL4: 45757 | CM4: 45757 | CN4: 45758 | CO4: 45758 | CP4: 45758 | CQ4: 45759 | CR4: 45759 | CS4: 45760 | CT4: 45760 | CU4: 45761 | CV4: 45762 | CW4: 45763 | CX4: 45767 | CY4: 45769 | CZ4: 45770 | DA4: 45772 | DB4: 45773 | DC4: 45773 | DD4: 45774 | DE4: 45775 | DF4: 45776 | DG4: 45776 | DH4: 45777 | DL4: 45778 | DM4: 45779 | DN4: 45780 | DO4: 45781 | DP4: 45782 | DQ4: 45783 | DR4: 45784 | DS4: 45785 | DT4: 45785 | DU4: 45786 | DV4: 45787 | DW4: 45788 | DX4: 45788 | DY4: 45791 | DZ4: 45793 | EA4: 45793 | EB4: 45793 | EC4: 45793 | ED4: 45794 | EE4: 45794 | EF4: 45795 | EG4: 45795 | EH4: 45796 | EI4: 45796 | EJ4: 45796 | EK4: 45796 | EL4: 45796 | EM4: 45797 | EN4: 45798 | EO4: 45799 | EP4: 45799 | EQ4: 45800
A5: Quiet Elegance | B5: 329
A6: Charming Home | B6: 329
A7: Bright Mornings | B7: 329
A8: Relaxing Naturals | B8: 329 | E8: 1 | N8: 2 | U8: =sum(C8:T8) -> 3 | V8: =U8*B8 -> 987 | AB8: 1 | AJ8: 1 | AX8: =sum(X8:AW8) -> 2 | AY8: =AX8*B8 -> 658 | BE8: 1 | BV8: 1 | BX8: 2 | CA8: =sum(BA8:BY8) -> 4 | CB8: =B8*CA8 -> 1316 | EG8: 1
A9: Mountain Breeze | B9: 329 | U9: =sum(C9:T9) -> 0 | V9: =U9*B9 -> 0 | AX9: =sum(X9:AW9) -> 0 | AY9: =AX9*B9 -> 0 | CA9: =sum(BA9:BE9) -> 0 | CB9: =CA9*AT9 -> 0
A10: Fresh Bamboo | B10: 329 | M10: 1 | N10: 3 | P10: 3 | U10: =sum(C10:T10) -> 7 | V10: =U10*B10 -> 2303 | AJ10: 1 | AO10: 1 | AU10: 1 | AX10: =sum(X10:AW10) -> 3 | AY10: =AX10*B10 -> 987 | CA10: =sum(BA10:BY10) -> 0 | CB10: =B10*CA10 -> 0
A11: Beach Escape | B11: 329 | N11: 2 | U11: =sum(C11:T11) -> 2 | V11: =U11*B11 -> 658 | AX11: =sum(X11:AW11) -> 0 | AY11: =AX11*B11 -> 0 | BB11: 1 | CA11: =sum(BA11:BY11) -> 1 | CB11: =B11*CA11 -> 329 | CL11: 1 | CY11: 1 | DS11: 1
A12: White Tea | B12: 329 | N12: 2 | U12: =sum(C12:T12) -> 2 | V12: =U12*B12 -> 658 | AN12: 1 | AX12: =sum(X12:AW12) -> 1 | AY12: =AX12*B12 -> 329 | BA12: 1 | BC12: 1 | BP12: 1 | CA12: =sum(BA12:BY12) -> 3 | CB12: =B12*CA12 -> 987 | CV12: 1 | DL12: 1 | DU12: 1 | EB12: 1
A13: Candy Cane | B13: 329 | U13: =sum(C13:T13) -> 0 | V13: =U13*B13 -> 0 | AQ13: 3 | AX13: =sum(X13:AW13) -> 3 | AY13: =AX13*B13 -> 987 | BS13: 1 | CA13: =sum(BA13:BY13) -> 1 | CB13: =B13*CA13 -> 329 | DL13: 1 | DW13: 1
A14: Apple Cinnamon | B14: 329 | Q14: 1 | U14: =sum(C14:T14) -> 1 | V14: =U14*B14 -> 329 | AP14: 1 | AX14: =sum(X14:AW14) -> 1 | AY14: =AX14*B14 -> 329 | BI14: 1 | BO14: 1 | BS14: 1 | BT14: 1 | CA14: =sum(BA14:BY14) -> 4 | CB14: =B14*CA14 -> 1316 | CN14: 2 | CV14: 1 | DR14: 1 | DW14: 1 | EC14: 2 | ED14: 1 | EE14: 1 | EL14: 2 | EQ14: 2
A15: Easy Drive | B15: 219 | U15: =sum(C15:T15) -> 0 | V15: =U15*B15 -> 0 | AD15: 1 | AX15: =sum(X15:AW15) -> 1 | AY15: =AX15*B15 -> 219 | CA15: =sum(BA15:BY15) -> 0 | CB15: =B15*CA15 -> 0
A16: InLove | U16: =sum(C16:T16) -> 0 | V16: =U16*B16 -> 0 | AX16: =sum(X16:AW16) -> 0 | AY16: =AX16*B16 -> 0 | CA16: =sum(BA16:BY16) -> 0 | CB16: =B16*CA16 -> 0
A17: Bright Mornings HW | U17: =sum(C17:T17) -> 0 | V17: =U17*B17 -> 0 | AX17: =sum(X17:AW17) -> 0 | AY17: =AX17*B17 -> 0 | CA17: =sum(BA17:BY17) -> 0 | CB17: =B17*CA17 -> 0
U18: =sum(C18:T18) -> 0 | V18: =U18*B18 -> 0 | AX18: =sum(X18:AW18) -> 0 | AY18: =AX18*B18 -> 0 | CA18: =sum(BA18:BY18) -> 0 | CB18: =B18*CA18 -> 0
A19: Lavender | B19: 239 | U19: =sum(C19:T19) -> 0 | V19: =U19*B19 -> 0 | AR19: 1 | AX19: =sum(X19:AW19) -> 1 | AY19: =AX19*B19 -> 239 | CA19: =sum(BA19:BY19) -> 0 | CB19: =B19*CA19 -> 0
A20: Eucalyptus | B20: 239 | C20: 1 | E20: 1 | U20: =sum(C20:T20) -> 2 | V20: =U20*B20 -> 478 | AX20: =sum(X20:AW20) -> 0 | AY20: =AX20*B20 -> 0 | CA20: =sum(BA20:BY20) -> 0 | CB20: =B20*CA20 -> 0
A21: Peppermint | B21: 239 | U21: =sum(C21:T21) -> 0 | V21: =U21*B21 -> 0 | AX21: =sum(X21:AW21) -> 0 | AY21: =AX21*B21 -> 0 | CA21: =sum(BA21:BY21) -> 0 | CB21: =B21*CA21 -> 0 | CD21: 2 | EP21: 1
A22: Fresh Bamboo FO | B22: 219 | U22: =sum(C22:T22) -> 0 | V22: =U22*B22 -> 0 | AX22: =sum(X22:AW22) -> 0 | AY22: =AX22*B22 -> 0 | BH22: 1 | CA22: =sum(BA22:BY22) -> 1 | CB22: =B22*CA22 -> 219
A23: Beach Escape FO | B23: 219 | U23: =sum(C23:T23) -> 0 | V23: =U23*B23 -> 0 | AX23: =sum(X23:AW23) -> 0 | AY23: =AX23*B23 -> 0 | CA23: =sum(BA23:BY23) -> 0 | CB23: =B23*CA23 -> 0
A24: White Tea FO | B24: 219 | U24: =sum(C24:T24) -> 0 | V24: =U24*B24 -> 0 | AX24: =sum(X24:AW24) -> 0 | AY24: =AX24*B24 -> 0 | CA24: =sum(BA24:BY24) -> 0 | CB24: =B24*CA24 -> 0
A25: Bright Mornings FO | B25: 219 | U25: =sum(C25:T25) -> 0 | V25: =U25*B25 -> 0 | AX25: =sum(X25:AW25) -> 0 | AY25: =AX25*B25 -> 0 | CA25: =sum(BA25:BY25) -> 0 | CB25: =B25*CA25 -> 0
A26: Quiet Elegance FO | B26: 219 | U26: =sum(C26:T26) -> 0 | V26: =U26*B26 -> 0 | AX26: =sum(X26:AW26) -> 0 | AY26: =AX26*B26 -> 0 | CA26: =sum(BA26:BY26) -> 0 | CB26: =B26*CA26 -> 0
A27: Fresh Bamboo Diffuser | B27: 799 | U27: =sum(C27:T27) -> 0 | V27: =U27*B27 -> 0 | Y27: 1 | AX27: =sum(X27:AW27) -> 1 | AY27: =AX27*B27 -> 799 | CA27: =sum(BA27:BY27) -> 0 | CB27: =B27*CA27 -> 0
A28: Clean Air | B28: 609 | K28: 1 | N28: 1 | U28: =sum(C28:T28) -> 2 | V28: =U28*B28 -> 1218 | Z28: 1 | AI28: 3 | AX28: =sum(X28:AW28) -> 4 | AY28: =AX28*B28 -> 2436 | CA28: =sum(BA28:BY28) -> 0 | CB28: =B28*CA28 -> 0
A29: Cotton Clean | B29: 329 | G29: 1 | K29: 1 | N29: 3 | Q29: 1 | T29: 1 | U29: =sum(C29:T29) -> 7 | V29: =U29*B29 -> 2303 | AH29: 1 | AS29: 1 | AU29: 3 | AX29: =sum(X29:AW29) -> 5 | AY29: =AX29*B29 -> 1645 | BN29: 2 | CA29: =sum(BA29:BY29) -> 2 | CB29: =B29*CA29 -> 658 | DS29: 1 | DT29: 1 | ED29: 1
A30: Brighter Days | B30: 329 | U30: =sum(C30:T30) -> 0 | V30: =U30*B30 -> 0 | AX30: =sum(X30:AW30) -> 0 | AY30: =AX30*B30 -> 0 | CA30: =sum(BA30:BY30) -> 0 | CB30: =B30*CA30 -> 0
A31: Cotton Clean FO | B31: 219 | U31: =sum(C31:T31) -> 0 | V31: =U31*B31 -> 0 | AX31: =sum(X31:AW31) -> 0 | AY31: =AX31*B31 -> 0 | CA31: =sum(BA31:BY31) -> 0 | CB31: =B31*CA31 -> 0 | EF31: 1
A32: Brighter Days EO | B32: 219 | U32: =sum(C32:T32) -> 0 | V32: =U32*B32 -> 0 | AX32: =sum(X32:AW32) -> 0 | AY32: =AX32*B32 -> 0 | CA32: =sum(BA32:BY32) -> 0 | CB32: =B32*CA32 -> 0
A33: Fresh Bamboo Refill | B33: 439 | O33: 2 | U33: =sum(C33:T33) -> 2 | V33: =U33*B33 -> 878 | AX33: =sum(X33:AW33) -> 0 | AY33: =AX33*B33 -> 0 | CA33: =sum(BA33:BY33) -> 0 | CB33: =B33*CA33 -> 0 | DB33: 1
A34: Clean Air Refill 1000ml | B34: 899 | U34: =sum(C34:T34) -> 0 | V34: =U34*B34 -> 0 | AX34: =sum(X34:AW34) -> 0 | AY34: =AX34*B34 -> 0 | CA34: =sum(BA34:BY34) -> 0 | CB34: =B34*CA34 -> 0
A35: Waterbased: Fresh Bamboo | B35: 549 | R35: 1 | U35: =sum(C35:T35) -> 1 | V35: =U35*B35 -> 549 | AV35: 1 | AX35: =sum(X35:AW35) -> 1 | AY35: =AX35*B35 -> 549 | BF35: 1 | CA35: =sum(BA35:BY35) -> 1 | CB35: =B35*CA35 -> 549 | CO35: 2 | EI35: 1 | EK35: 1
A36: Waterbased: Cotton Clean | B36: 549 | U36: =sum(C36:T36) -> 0 | V36: =U36*B36 -> 0 | AV36: 2 | AX36: =sum(X36:AW36) -> 2 | AY36: =AX36*B36 -> 1098 | BF36: 1 | CA36: =sum(BA36:BY36) -> 1 | CB36: =B36*CA36 -> 549 | CO36: 2
A37: Waterbased: White Tea | B37: 549 | U37: =sum(C37:T37) -> 0 | V37: =U37*B37 -> 0 | AT37: 2 | AX37: =sum(X37:AW37) -> 2 | AY37: =AX37*B37 -> 1098 | CA37: =sum(BA37:BY37) -> 0 | CB37: =B37*CA37 -> 0 | CO37: 2 | EI37: 1
A38: White Tea Diffuser | B38: 799 | U38: =sum(C38:T38) -> 0 | V38: =U38*B38 -> 0 | AX38: =sum(X38:AW38) -> 0 | AY38: =AX38*B38 -> 0 | CA38: =sum(BA38:BY38) -> 0 | CB38: =B38*CA38 -> 0 | EN38: 1
A39: Cotton Clean Diffuser | B39: 799 | U39: =sum(C39:T39) -> 0 | V39: =U39*B39 -> 0 | AX39: =sum(X39:AW39) -> 0 | AY39: =AX39*B39 -> 0 | CA39: =sum(BA39:BY39) -> 0 | CB39: =B39*CA39 -> 0
A40: White Tea Diffuser Refill | B40: 439 | U40: =sum(C40:T40) -> 0 | V40: =U40*B40 -> 0 | AX40: =sum(X40:AW40) -> 0 | AY40: =AX40*B40 -> 0 | CA40: =sum(BA40:BY40) -> 0 | CB40: =B40*CA40 -> 0 | DB40: 1 | EJ40: 1
A41: Cotton Clean Diffuser Refill | B41: 439 | U41: =sum(C41:T41) -> 0 | V41: =U41*B41 -> 0 | AX41: =sum(X41:AW41) -> 0 | AY41: =AX41*B41 -> 0 | CA41: =sum(BA41:BY41) -> 0 | CB41: =B41*CA41 -> 0 | CP41: 1
A42: Reed Sticks | B42: 60 | E42: 2 | U42: =sum(C42:T42) -> 2 | V42: =U42*B42 -> 120 | AA42: 2 | AC42: 3 | AL42: 2 | AX42: =sum(X42:AW42) -> 7 | AY42: =AX42*B42 -> 420 | BQ42: 1 | BY42: 2 | CA42: =sum(BA42:BY42) -> 3 | CB42: =B42*CA42 -> 180 | CX42: 20 | DC42: 3 | DM42: 2 | EM42: 1
A43: Relaxing Naturals 500ml | B43: 609 | I43: 1 | U43: =sum(C43:T43) -> 1 | V43: =U43*B43 -> 609 | X43: 1 | Z43: 1 | AW43: 1 | AX43: =sum(X43:AW43) -> 3 | AY43: =AX43*B43 -> 1827 | BL43: 1 | BR43: 1 | BU43: 2 | CA43: =sum(BA43:BY43) -> 4 | CB43: =B43*CA43 -> 2436 | CF43: 2 | CU43: 1 | DD43: 1
A44: Hand Wash Relaxing Naturals 500ml | B44: 379 | U44: =sum(C44:T44) -> 0 | V44: =U44*B44 -> 0 | AX44: =sum(X44:AW44) -> 0 | AY44: =AX44*B44 -> 0 | CA44: =sum(BA44:BY44) -> 0 | CB44: =B44*CA44 -> 0
A45: Hand Wash Clean & Bright 500ml | B45: 379 | U45: =sum(C45:T45) -> 0 | V45: =U45*B45 -> 0 | AX45: =sum(X45:AW45) -> 0 | AY45: =AX45*B45 -> 0 | CA45: =sum(BA45:BY45) -> 0 | CB45: =B45*CA45 -> 0
A46: Keep it Clean Gift Set | B46: 1299 | U46: =sum(C46:T46) -> 0 | V46: =U46*B46 -> 0 | AX46: =sum(X46:AW46) -> 0 | AY46: =AX46*B46 -> 0 | CA46: =sum(BA46:BY46) -> 0 | CB46: =B46*CA46 -> 0
A47: Relax With Me | B47: 1299 | U47: =sum(C47:T47) -> 0 | V47: =U47*B47 -> 0 | AX47: =sum(X47:AW47) -> 0 | AY47: =AX47*B47 -> 0 | CA47: =sum(BA47:BY47) -> 0 | CB47: =B47*CA47 -> 0
A48: Simoy ng Pahiyas | B48: 0 | U48: =sum(C48:T48) -> 0 | V48: =U48*B48 -> 0 | AX48: =sum(X48:AW48) -> 0 | AY48: =AX48*B48 -> 0 | CA48: =sum(BA48:BY48) -> 0 | CB48: =B48*CA48 -> 0
U49: =sum(C49:T49) -> 0 | V49: =U49*B49 -> 0 | AX49: =sum(X49:AW49) -> 0 | AY49: =AX49*B49 -> 0 | CA49: =sum(BA49:BY49) -> 0 | CB49: =B49*CA49 -> 0
A50: Fresh Bamboo 500ml | B50: 609 | S50: 1 | U50: =sum(C50:T50) -> 1 | V50: =U50*B50 -> 609 | AE50: 3 | AF50: 2 | AM50: 6 | AX50: =sum(X50:AW50) -> 11 | AY50: =AX50*B50 -> 6699 | BG50: 1 | BK50: 1 | BW50: 1 | CA50: =sum(BA50:BY50) -> 3 | CB50: =B50*CA50 -> 1827 | CG50: 1 | CI50: 1 | CJ50: 1 | CK50: 1 | CM50: 1 | CQ50: 1 | CS50: 1 | CW50: 1 | CZ50: 1 | DA50: 1 | DE50: 1 | DO50: 1 | DQ50: 1 | DT50: 1 | DV50: 1 | DX50: 1 | DZ50: 1 | EA50: 1 | EH50: 3 | EK50: 1 | EO50: 1
A51: White Tea 500ml | B51: 609 | U51: =sum(C51:T51) -> 0 | V51: =U51*B51 -> 0 | Z51: 1 | AX51: =sum(X51:AW51) -> 1 | AY51: =AX51*B51 -> 609 | BM51: 1 | CA51: =sum(BA51:BY51) -> 1 | CB51: =B51*CA51 -> 609 | CH51: 2 | EO51: 1
A52: Tropical Paradise 200ml | B52: 329 | H52: 2 | U52: =sum(C52:T52) -> 2 | V52: =U52*B52 -> 658 | AX52: =sum(X52:AW52) -> 0 | AY52: =AX52*B52 -> 0 | CA52: =sum(BA52:BY52) -> 0 | CB52: =B52*CA52 -> 0
A53: RN Wash 50ml | B53: 199 | U53: =sum(C53:T53) -> 0 | V53: =U53*B53 -> 0 | AX53: =sum(X53:AW53) -> 0 | AY53: =AX53*B53 -> 0 | CA53: =sum(BA53:BY53) -> 0 | CB53: =B53*CA53 -> 0
A54: CB Wash 50ml | B54: 199 | U54: =sum(C54:T54) -> 0 | V54: =U54*B54 -> 0 | AX54: =sum(X54:AW54) -> 0 | AY54: =AX54*B54 -> 0 | BD54: 2 | CA54: =sum(BA54:BY54) -> 2 | CB54: =B54*CA54 -> 398 | DP54: 2
A55: Travel With Me | B55: 599 | U55: =sum(C55:T55) -> 0 | V55: =U55*B55 -> 0 | AX55: =sum(X55:AW55) -> 0 | AY55: =AX55*B55 -> 0 | CA55: =sum(BA55:BY55) -> 0 | CB55: =B55*CA55 -> 0
A56: Handwash: Relaxing Naturals Gallon | B56: 1499 | U56: =sum(C56:T56) -> 0 | V56: =U56*B56 -> 0 | AX56: =sum(X56:AW56) -> 0 | AY56: =AX56*B56 -> 0 | CA56: =sum(BA56:BY56) -> 0 | CB56: =B56*CA56 -> 0 | CH56: 1
U57: =sum(C57:T57) -> 0 | V57: =U57*B57 -> 0 | AX57: =sum(X57:AW57) -> 0 | AY57: =AX57*B57 -> 0 | CA57: =sum(BA57:BY57) -> 0 | CB57: =B57*CA57 -> 0
A58: Creamy Matcha | B58: 329 | D58: 2 | U58: =sum(C58:T58) -> 2 | V58: =U58*B58 -> 658 | AX58: =sum(X58:AW58) -> 0 | AY58: =AX58*B58 -> 0 | CA58: =sum(BA58:BY58) -> 0 | CB58: =B58*CA58 -> 0
A59: White Lavender | B59: 329 | U59: =sum(C59:T59) -> 0 | V59: =U59*B59 -> 0 | AX59: =sum(X59:AW59) -> 0 | AY59: =AX59*B59 -> 0 | CA59: =sum(BA59:BY59) -> 0 | CB59: =B59*CA59 -> 0
A60: Green Tea | B60: 329 | J60: 1 | K60: 1 | L60: 2 | T60: 1 | U60: =sum(C60:T60) -> 5 | V60: =U60*B60 -> 1645 | AX60: =sum(X60:AW60) -> 0 | AY60: =AX60*B60 -> 0 | BC60: 1 | BJ60: 2 | CA60: =sum(BA60:BY60) -> 3 | CB60: =B60*CA60 -> 987 | CG60: 1 | CL60: 1 | CR60: 1 | CS60: 5 | CT60: 5 | CY60: 1 | DN60: 1
A61: Clean Air 100ml | B61: 249 | U61: =sum(C61:T61) -> 0 | V61: =U61*B61 -> 0 | AX61: =sum(X61:AW61) -> 0 | AY61: =AX61*B61 -> 0 | BS61: 2 | CA61: =sum(BA61:BY61) -> 2 | CB61: =B61*CA61 -> 498 | DY61: 1
A62: Creamy Matcha Diffuser Refill | B62: 439 | U62: =sum(C62:T62) -> 0 | V62: =U62*B62 -> 0 | AA62: 2 | AX62: =sum(X62:AW62) -> 2 | AY62: =AX62*B62 -> 878 | CA62: =sum(BA62:BY62) -> 0 | CB62: =B62*CA62 -> 0 | DG62: 1
A63: White Lavender Diffuser Refill | B63: 439 | U63: =sum(C63:T63) -> 0 | V63: =U63*B63 -> 0 | AX63: =sum(X63:AW63) -> 0 | AY63: =AX63*B63 -> 0 | BY63: 1 | CA63: =sum(BA63:BY63) -> 1 | CB63: =B63*CA63 -> 439 | CH63: 6
A64: Green Tea Diffuser Refill | B64: 439 | U64: =sum(C64:T64) -> 0 | V64: =U64*B64 -> 0 | AX64: =sum(X64:AW64) -> 0 | AY64: =AX64*B64 -> 0 | CA64: =sum(BA64:BY64) -> 0 | CB64: =B64*CA64 -> 0
A65: Creamy Matcha Diffuser | B65: 799 | U65: =sum(C65:T65) -> 0 | V65: =U65*B65 -> 0 | AX65: =sum(X65:AW65) -> 0 | AY65: =AX65*B65 -> 0 | CA65: =sum(BA65:BY65) -> 0 | CB65: =B65*CA65 -> 0
A66: White Lavender Diffuser | B66: 799 | U66: =sum(C66:T66) -> 0 | V66: =U66*B66 -> 0 | AX66: =sum(X66:AW66) -> 0 | AY66: =AX66*B66 -> 0 | BN66: 1 | CA66: =sum(BA66:BY66) -> 1 | CB66: =B66*CA66 -> 799
A67: Green Tea Diffuser | B67: 799 | U67: =sum(C67:T67) -> 0 | V67: =U67*B67 -> 0 | AX67: =sum(X67:AW67) -> 0 | AY67: =AX67*B67 -> 0 | CA67: =sum(BA67:BY67) -> 0 | CB67: =B67*CA67 -> 0
A68: Creamy Matcha + Roomspray | B68: 1299 | U68: =sum(C68:T68) -> 0 | V68: =U68*B68 -> 0 | AK68: 1 | AX68: =sum(X68:AW68) -> 1 | AY68: =AX68*B68 -> 1299 | CA68: =sum(BA68:BY68) -> 0 | CB68: =B68*CA68 -> 0
A69: White Lavender + Roomspray | B69: 1299 | U69: =sum(C69:T69) -> 0 | V69: =U69*B69 -> 0 | AX69: =sum(X69:AW69) -> 0 | AY69: =AX69*B69 -> 0 | CA69: =sum(BA69:BY69) -> 0 | CB69: =B69*CA69 -> 0
A70: Green Tea + Roomspray | B70: 1299 | U70: =sum(C70:T70) -> 0 | V70: =U70*B70 -> 0 | AX70: =sum(X70:AW70) -> 0 | AY70: =AX70*B70 -> 0 | BM70: 1 | CA70: =sum(BA70:BY70) -> 1 | CB70: =B70*CA70 -> 1299
A71: Cotton Clean 500ml | B71: 609 | U71: =sum(C71:T71) -> 0 | V71: =U71*B71 -> 0 | Z71: 1 | AX71: =sum(X71:AW71) -> 1 | AY71: =AX71*B71 -> 609 | BG71: 1 | CA71: =sum(BA71:BY71) -> 1 | CB71: =B71*CA71 -> 609 | DF71: 1 | EF71: 1
A72: Modern Luxe Reed Diffuser | B72: 1599 | K72: 2 | U72: =sum(C72:T72) -> 2 | V72: =U72*B72 -> 3198 | AX72: =sum(X72:AW72) -> 0 | AY72: =AX72*B72 -> 0 | CA72: =sum(BA72:BY72) -> 0 | CB72: =B72*CA72 -> 0
A73: Serene Sanctuary Reed Diffuser | B73: 1599 | U73: =sum(C73:T73) -> 0 | V73: =U73*B73 -> 0 | AX73: =sum(X73:AW73) -> 0 | AY73: =AX73*B73 -> 0 | CA73: =sum(BA73:BY73) -> 0 | CB73: =B73*CA73 -> 0
A74: Urban Oasis Reed Diffuser | B74: 1599 | U74: =sum(C74:T74) -> 0 | V74: =U74*B74 -> 0 | AX74: =sum(X74:AW74) -> 0 | AY74: =AX74*B74 -> 0 | CA74: =sum(BA74:BY74) -> 0 | CB74: =B74*CA74 -> 0
A75: Clean Air Gallon | U75: =sum(C75:T75) -> 0 | V75: =U75*B75 -> 0 | AX75: =sum(X75:AW75) -> 0 | AY75: =AX75*B75 -> 0 | CA75: =sum(BA75:BY75) -> 0 | CB75: =B75*CA75 -> 0
U76: =sum(C76:T76) -> 0 | V76: =U76*B76 -> 0 | AX76: =sum(X76:AW76) -> 0 | AY76: =AX76*B76 -> 0 | CA76: =sum(BA76:BY76) -> 0 | CB76: =B76*CA76 -> 0
A77: Holiday Hugs 200ml | B77: 379 | F77: 1 | U77: =sum(C77:T77) -> 1 | V77: =U77*B77 -> 379 | AX77: =sum(X77:AW77) -> 0 | AY77: =AX77*B77 -> 0 | CA77: =sum(BA77:BY77) -> 0 | CB77: =B77*CA77 -> 0 | CP77: 1
A78: Holiday Hugs Diffuser Set | B78: 799 | U78: =sum(C78:T78) -> 0 | V78: =U78*B78 -> 0 | AX78: =sum(X78:AW78) -> 0 | AY78: =AX78*B78 -> 0 | CA78: =sum(BA78:BY78) -> 0 | CB78: =B78*CA78 -> 0
A79: Holiday Hugs Refill | B79: 439 | U79: =sum(C79:T79) -> 0 | V79: =U79*B79 -> 0 | AX79: =sum(X79:AW79) -> 0 | AY79: =AX79*B79 -> 0 | CA79: =sum(BA79:BY79) -> 0 | CB79: =B79*CA79 -> 0
A80: Bathroom Kit | B80: 599 | U80: =sum(C80:T80) -> 0 | V80: =U80*B80 -> 0 | AX80: =sum(X80:AW80) -> 0 | AY80: =AX80*B80 -> 0 | CA80: =sum(BA80:BY80) -> 0 | CB80: =B80*CA80 -> 0
A81: Flushie 50ml | B81: 229 | J81: 1 | U81: =sum(C81:T81) -> 1 | V81: =U81*B81 -> 229 | AA81: 1 | AX81: =sum(X81:AW81) -> 1 | AY81: =AX81*B81 -> 229 | BS81: 2 | CA81: =sum(BA81:BY81) -> 2 | CB81: =B81*CA81 -> 458 | CV81: 1
A82: Easy Drive Grapefuit | B82: 219 | U82: =sum(C82:T82) -> 0 | V82: =U82*B82 -> 0 | AG82: 1 | AS82: 3 | AX82: =sum(X82:AW82) -> 4 | AY82: =AX82*B82 -> 876 | CA82: =sum(BA82:BY82) -> 0 | CB82: =B82*CA82 -> 0
A83: Fresh Bamboo Diffuser + Roomspray | B83: 1299 | U83: =sum(C83:T83) -> 0 | V83: =U83*B83 -> 0 | AX83: =sum(X83:AW83) -> 0 | AY83: =AX83*B83 -> 0 | CA83: =sum(BA83:BY83) -> 0 | CB83: =B83*CA83 -> 0
A84: White Tea Diffuser + Roomspray | B84: 1299 | U84: =sum(C84:T84) -> 0 | V84: =U84*B84 -> 0 | AX84: =sum(X84:AW84) -> 0 | AY84: =AX84*B84 -> 0 | CA84: =sum(BA84:BY84) -> 0 | CB84: =B84*CA84 -> 0
A85: Cotton Clean Diffuser + Roomspray | B85: 1299 | U85: =sum(C85:T85) -> 0 | V85: =U85*B85 -> 0 | AX85: =sum(X85:AW85) -> 0 | AY85: =AX85*B85 -> 0 | CA85: =sum(BA85:BY85) -> 0 | CB85: =B85*CA85 -> 0
A86: Holiday Hugs Diffuser + Roomspray | B86: 1299 | U86: =sum(C86:T86) -> 0 | V86: =U86*B86 -> 0 | AX86: =sum(X86:AW86) -> 0 | AY86: =AX86*B86 -> 0 | CA86: =sum(BA86:BY86) -> 0 | CB86: =B86*CA86 -> 0
U87: =sum(C87:T87) -> 0 | V87: =U87*B87 -> 0 | AX87: =sum(X87:AW87) -> 0 | AY87: =AX87*B87 -> 0 | CA87: =sum(BA87:BY87) -> 0 | CB87: =B87*CA87 -> 0
A88: Sleep All Day | B88: 679 | U88: =sum(C88:T88) -> 0 | V88: =U88*B88 -> 0 | AX88: =sum(X88:AW88) -> 0 | AY88: =AX88*B88 -> 0 | CA88: =sum(BA88:BY88) -> 0 | CB88: =B88*CA88 -> 0
A89: One Way Ticket | B89: 679 | U89: =sum(C89:T89) -> 0 | V89: =U89*B89 -> 0 | AX89: =sum(X89:AW89) -> 0 | AY89: =AX89*B89 -> 0 | CA89: =sum(BA89:BY89) -> 0 | CB89: =B89*CA89 -> 0
A90: Holiday Cheer | B90: 679 | U90: =sum(C90:T90) -> 0 | V90: =U90*B90 -> 0 | AX90: =sum(X90:AW90) -> 0 | AY90: =AX90*B90 -> 0 | CA90: =sum(BA90:BY90) -> 0 | CB90: =B90*CA90 -> 0
U91: =sum(C91:T91) -> 0 | V91: =U91*B91 -> 0 | AX91: =sum(X91:AW91) -> 0 | AY91: =AX91*B91 -> 0 | CA91: =sum(BA91:BY91) -> 0 | CB91: =B91*CA91 -> 0
A92: High Enery Gift Set (Essential Oils) | B92: 490 | U92: =sum(C92:T92) -> 0 | V92: =U92*B92 -> 0 | AX92: =sum(X92:AW92) -> 0 | AY92: =AX92*B92 -> 0 | CA92: =sum(BA92:BY92) -> 0 | CB92: =B92*CA92 -> 0
A93: Romantic Date Gift Set (Essential Oils) | B93: 490 | U93: =sum(C93:T93) -> 0 | V93: =U93*B93 -> 0 | AX93: =sum(X93:AW93) -> 0 | AY93: =AX93*B93 -> 0 | CA93: =sum(BA93:BY93) -> 0 | CB93: =B93*CA93 -> 0
A94: One Way Ticket Gift Set (Fragrance Oils) | B94: 450 | U94: =sum(C94:T94) -> 0 | V94: =U94*B94 -> 0 | AX94: =sum(X94:AW94) -> 0 | AY94: =AX94*B94 -> 0 | CA94: =sum(BA94:BY94) -> 0 | CB94: =B94*CA94 -> 0
A95: Quality Time Gift Set (Fragrance Oils) | B95: 450 | U95: =sum(C95:T95) -> 0 | V95: =U95*B95 -> 0 | AX95: =sum(X95:AW95) -> 0 | AY95: =AX95*B95 -> 0 | CA95: =sum(BA95:BY95) -> 0 | CB95: =B95*CA95 -> 0
U96: =sum(C96:T96) -> 0 | V96: =U96*B96 -> 0 | AX96: =sum(X96:AW96) -> 0 | AY96: =AX96*B96 -> 0 | CA96: =sum(BA96:BY96) -> 0 | CB96: =B96*CA96 -> 0
A97: Fresh Start Kit | B97: 1054 | U97: =sum(C97:T97) -> 0 | V97: =U97*B97 -> 0 | AX97: =sum(X97:AW97) -> 0 | AY97: =AX97*B97 -> 0 | CA97: =sum(BA97:BY97) -> 0 | CB97: =B97*CA97 -> 0
A98: Quite Olive RLS | B98: 329 | CA98: =sum(BA98:BY98) -> 0 | CB98: =B98*CA98 -> 0 | CE98: 1 | DY98: 1 | ED98: 1
A99: Quite Olive Refill | B99: 439 | BQ99: 1 | CA99: =sum(BA99:BY99) -> 1 | CB99: =B99*CA99 -> 439
A100: Quite Olive Reed Set | B100: 799 | CA100: =sum(BA100:BY100) -> 0 | CB100: =B100*CA100 -> 0 | DH100: 1
A101: Custom Order | U101: =sum(C101:T101) -> 0 | CA101: =sum(BA101:BY101) -> 0 | CB101: =B101*CA101 -> 0
...

Sheet SHOPEE
CH2: FEBRUARY
A3: VARIANT | B3: PRICE | C3: Veron Migo-Engle | D3: Cristine | E3: Jdavecve | F3: Maureen | G3: Cat Tan | H3: Marie Rose | I3: necitascruz | J3: Romeo | K3: Dawn Silva | L3: Haydee Chan | M3: Erica M. | N3: Joanna | O3: Ella | P3: Gerliz | Q3: Berlyn | R3: Java M. | S3: Diosa D. | T3: Black S. | U3: Ruth M. | V3: Jarssry | W3: Total | X3: Ires | Y3: Rein Magno | Z3: Alex | AA3: Marie J. | AB3: Dyu An | AC3: Jhanel | AD3: Eugene E. Guibao | AE3: Peng p. | AF3: Myra Brockmann | AG3: Pobadora | AH3: Hiro | AI3: Judy | AJ3: Borex | AK3: Cever | AL3: Ferdinand | AM3: Matthew | AN3: Carol | AO3: Green Apple | AP3: Henry Villadares | AQ3: Via bells | AR3: Carol V. | AS3: Che galang | AT3: Dr. Tine | AU3: Page 26 | AV3: Dhan | AW3: Edlyn Mancera | AX3: Sofia | AY3: Veron | AZ3: Rhea V. | BA3: Claudine Manuel | BB3: Ivygail Javier | BC3: Bubbles F. | BD3: Kasumi Inoue | BE3: Jessa Lique | BF3: Karen S. | BG3: Summer Ebo | BH3: Pauline Ann Pablo | BI3: Keyt Q. | BJ3: Jenny D. | BK3: Ron Galde | BL3: Cedric C. | BM3: Junjun L. | BN3: Joseph Mamac | BO3: Sammon | BP3: Threex | BQ3: Paul Dequina | BR3: Maia | BS3: Kingraw | BT3: La Taperia Martinez | BU3: Dani Feliza Caparas | BV3: Celin Gay Balgos | BW3: Ani Freak | BX3: Carrys | BY3: Elle J. | BZ3: Thresex | CA3: Lea Nicole Bagayas | CB3: Gigi | CC3: Faith | CD3: Solution Trading | CH3: Jestoni L. | CI3: Dencice J. | CJ3: Hana | CK3: Jen Irin | CL3: Elle J. | CM3: Leo Rosario | CN3: Belle Santos | CO3: Jestoni Losabia | CP3: Shenna | CQ3: Claire D. | CR3: Pretty D. | CS3: Maksi mutin | CT3: Hilda Rivadelo | CU3: Katlyn | CV3: Jenny Dayon | CW3: Gaby Pama | CX3: Roxanne Dalistan | CY3: Edmaria | CZ3: Ellaine Lois Megia | DA3: Eleonor | DB3: Miles C. | DC3: Aurdey | DD3: Josephine Candaroma | DE3: Edlyn M. | DF3: Hazel C. | DG3: Dani F. | DH3: Flade J. | DI3: Wear H. | DJ3: Gabrielle | DK3: Nikki J. | DL3: VHB Paseo Skin Care Center Inc | DM3: Jef Tumampos | DN3: Cruzer | DO3: Michelle Tan | DP3: Krl franco | DQ3: Jeanne Pauline M Baligod | DR3: Michelle Tan | DS3: Dianna | DT3: Salem | DU3: Barbie Castaneda | DV3: Jenny Dayon | DW3: Leo M. | DX3: Michelle Tan | DY3: Michelle Tan | DZ3: Angela Mae Gilboy | EA3: Janika Laxamana | EB3: Pauline Ann Pablo | EC3: Maria Teresa A. Pacil | ED3: Vanessa Chanyungco | EE3: Carol Villena | EI3: Solution Trading | EJ3: Sandra | EK3: Maek M. | EL3: Anna F. | EM3: Bhie M. | EN3: Lisha | EO3: Jack | EP3: Nessa | EQ3: Thirsty | ER3: Carlie | ES3: Thirsty | ET3: Carlie | EU3: MelBad | EV3: Cervin Benjamin Sarte | EW3: Lee Santos | EX3: Hernan | EY3: Danifel | EZ3: Esbaro | FA3: Theen | FB3: Mylds Corner | FC3: Zarren Lee | FD3: Jhanel | FE3: Niki Mindj | FF3: Mae Joson | FG3: Giigii | FH3: Mary Antoinette Maneja | FI3: Tricia | FJ3: Lorie | FK3: Cindy | FL3: Bonifcio | FM3: Melanie Pilapil | FN3: Raenna | FO3: Leo Rosario | FP3: Pegy | FQ3: Rowena | FR3: Mribeth | FS3: Ness | FT3: Pink | FU3: small | FV3: next level | FW3: Black | FX3: Anne B. | FY3: SD T. | FZ3: Vayie | GA3: Irres | GB3: Gmm | GC3: Mae Nova | GD3: JF24 | GE3: JF24 | GF3: Marian Marites | GG3: Antonette Amancio | GK3: Althea Napod | GL3: Rhea M. | GM3: Carol | GN3: Cpb | GO3: Juliene | GP3: Sleep Les | GQ3: Jennifer | GR3: Lea L. | GS3: Genelyn | GT3: Sugar Plum | GU3: Judith Nicolas | GV3: Julia K. | GW3: Paulo King | GX3: Jess Theway | GY3: Alexa | GZ3: Eowyn | HA3: Robert Cruz | HB3: Pauline Ann Pablo | HC3: Ma. Majella Fides Conti | HD3: Q3pvytn | HE3: Camille | HF3: Dani Feliza Caparas | HG3: Amanda F. | HH3: Sophia | HI3: Fe de Guzman | HJ3: Eunice | HK3: Edlyn Mancera | HL3: Blesilda Dy | HM3: Mickayoo | HN3: Jessica Tan | HO3: Leo Rosario | HP3: Leo Rosario | HQ3: Peace | HR3: One belle | HS3: Yvonne Casabuena | HT3: Takahiro | HU3: Prime | HV3: Armie | HW3: Xyza Ledesma | HX3: Ann Melody Yao | HY3: Maja | HZ3: Battos | IA3: Rhea M | IB3: Budweizen | IC3: Samun | ID3: Mirman | IE3: Michael | II3: Dani F. | IJ3: Catetan | IK3: Kathlyn chaves | IL3: Shane Bacoy | IM3: Ma. Lucilyn Fajanilan | IN3: Merlin | IO3: Anjeline | IP3: Sherlan | IQ3: Martin | IR3: Jinse | IS3: Pablo | IT3: Thebab | IU3: Denice | IV3: Triss | IW3: Sighter | IX3: Siyvie | IY3: King | IZ3: Brie | JA3: Mg Narcisso | JB3: Jenefer ancheta | JC3: Wilma | JD3: Chris Ramos | JE3: Demensyon | JF3: Qep | JG3: Teejay | JH3: Julie | JI3: Bernadette Cadaing | JJ3: Sanmi | JK3: Edmarie | JL3: Beautie | JM3: Patisha | JN3: Sighter | JO3: Euna | JP3: Hazel | JQ3: Jona Francisco | JR3: Pau ramos | JS3: Lisette | JT3: Jacky Guillen | JU3: Mike | JV3: Eloise | JW3: JTakahiro | JX3: Feliz | JY3: Denice Javier | JZ3: Jeremie Tumulak | KA3: Bena Malabanan
C4: 45658 | D4: 45659 | E4: 45659 | F4: 45660 | G4: 45660 | H4: 45661 | I4: 45661 | J4: 45662 | K4: 45663 | L4: 45663 | M4: 45663 | N4: 45663 | O4: 45663 | P4: 45664 | Q4: 45664 | R4: 45664 | S4: 45664 | T4: 45665 | U4: 45666 | V4: 45666 | W4: 45667 | X4: 45667 | Y4: 45668 | Z4: 45668 | AA4: 45668 | AB4: 45669 | AC4: 45670 | AD4: 45671 | AE4: 45672 | AF4: 45672 | AG4: 45672 | AH4: 45672 | AI4: 45672 | AJ4: 45672 | AK4: 45672 | AL4: 45673 | AM4: 45673 | AN4: 45674 | AO4: 45675 | AP4: 45676 | AQ4: 45677 | AR4: 45678 | AS4: 45678 | AT4: 45679 | AU4: 45679 | AV4: 45679 | AW4: 45680 | AX4: 45680 | AY4: 45681 | AZ4: 45681 | BA4: 45681 | BB4: 45681 | BC4: 45681 | BD4: 45682 | BE4: 45683 | BF4: 45683 | BG4: 45683 | BH4: 45684 | BI4: 45684 | BJ4: 45684 | BK4: 45684 | BL4: 45684 | BM4: 45684 | BN4: 45684 | BO4: 45685 | BP4: 45685 | BQ4: 45685 | BR4: 45685 | BS4: 45685 | BT4: 45686 | BU4: 45686 | BV4: 45687 | BW4: 45687 | BX4: 45687 | BY4: 45687 | BZ4: 45688 | CA4: 45688 | CB4: 45688 | CC4: 45688 | CD4: 45688 | CH4: 45689 | CI4: 45689 | CJ4: 45690 | CK4: 45690 | CL4: 45690 | CM4: 45690 | CN4: 45690 | CO4: 45692 | CP4: 45692 | CQ4: 45693 | CR4: 45693 | CS4: 45695 | CT4: 45695 | CU4: 45695 | CV4: 45696 | CW4: 45697 | CX4: 45698 | CY4: 45698 | CZ4: 45699 | DA4: 45700 | DB4: 45701 | DC4: 45702 | DD4: 45703 | DE4: 45703 | DF4: 45703 | DG4: 45703 | DH4: 45703 | DI4: 45703 | DJ4: 45704 | DK4: 45705 | DL4: 45705 | DM4: 45706 | DN4: 45707 | DO4: 45707 | DP4: 45708 | DQ4: 45709 | DR4: 45709 | DS4: 45710 | DT4: 45711 | DU4: 45711 | DV4: 45711 | DW4: 45711 | DX4: 45712 | DY4: 45713 | DZ4: 45713 | EA4: 45713 | EB4: 45713 | EC4: 45714 | ED4: 45715 | EE4: 45716 | EI4: 46082 | EJ4: 46082 | EK4: 46082 | EL4: 46082 | EM4: 46083 | EN4: 46085 | EO4: 46086 | EP4: 46086 | EQ4: 46087 | ER4: 46087 | ES4: 46087 | ET4: 46087 | EU4: 46089 | EV4: 46090 | EW4: 46090 | EX4: 46092 | EY4: 46093 | EZ4: 46094 | FA4: 46094 | FB4: 46095 | FC4: 46096 | FD4: 46096 | FE4: 46096 | FF4: 46096 | FG4: 46097 | FH4: 46097 | FI4: 46097 | FJ4: 46098 | FK4: 46099 | FL4: 46099 | FM4: 46100 | FN4: 46101 | FO4: 46101 | FP4: 46102 | FQ4: 46103 | FR4: 46104 | FS4: 46105 | FT4: 46106 | FU4: 46107 | FV4: 46107 | FW4: 46107 | FX4: 46108 | FY4: 46109 | FZ4: 46111 | GA4: 46111 | GB4: 46111 | GC4: 46111 | GD4: 46112 | GE4: 46112 | GF4: 46112 | GG4: 46112 | GK4: 45748 | GL4: 45748 | GM4: 45751 | GN4: 45751 | GO4: 45751 | GP4: 45751 | GQ4: 45751 | GR4: 45752 | GS4: 45752 | GT4: 45753 | GU4: 45753 | GV4: 45754 | GW4: 45756 | GX4: 45756 | GY4: 45758 | GZ4: 45758 | HA4: 45758 | HB4: 45759 | HC4: 45759 | HD4: 45759 | HE4: 45760 | HF4: 45760 | HG4: 45761 | HH4: 45762 | HI4: 45762 | HJ4: 45763 | HK4: 45763 | HL4: 45764 | HM4: 45764 | HN4: 45766 | HO4: 45768 | HP4: 45768 | HQ4: 45768 | HR4: 45769 | HS4: 45769 | HT4: 45770 | HU4: 45770 | HV4: 45771 | HW4: 45772 | HX4: 45772 | HY4: 45773 | HZ4: 45774 | IA4: 45774 | IB4: 45775 | IC4: 45776 | ID4: 45777 | IE4: 45777 | II4: 45778 | IJ4: 45780 | IK4: 45780 | IL4: 45782 | IM4: 45782 | IN4: 45782 | IO4: 45782 | IP4: 45782 | IQ4: 45783 | IR4: 45783 | IS4: 45783 | IT4: 45784 | IU4: 45784 | IV4: 45785 | IW4: 45786 | IX4: 45786 | IY4: 45786 | IZ4: 45787 | JA4: 45789 | JB4: 45789 | JC4: 45789 | JD4: 45790 | JE4: 45790 | JF4: 45790 | JG4: 45792 | JH4: 45792 | JI4: 45793 | JJ4: 45793 | JK4: 45794 | JL4: 45794 | JM4: 45794 | JN4: 45794 | JO4: 45794 | JP4: 45794 | JQ4: 45795 | JR4: 45796 | JS4: 45798 | JT4: 45798 | JU4: 45799 | JV4: 45799 | JW4: 45799 | JX4: 45800 | JY4: 45801 | JZ4: 45801 | KA4: 45802
A5: Quiet Elegance | B5: 329
A6: Charming Home | B6: 329
A7: Bright Mornings | B7: 329
A8: Relaxing Naturals | B8: 329 | C8: 1 | F8: 1 | AB8: 1 | AH8: 1 | AP8: 2 | AQ8: 1 | AX8: 1 | AY8: 1 | BG8: 1 | BL8: 1 | BN8: 1 | BU8: 1 | CE8: =sum(C8:CD8) -> 13 | CF8: =CE8*B8 -> 4277 | DF8: 1 | DG8: 1 | DH8: 1 | DK8: 1 | DN8: 1 | DT8: 1 | DZ8: 1 | EA8: 1 | ED8: 1 | EF8: =sum(CH8:ED8) -> 9 | EG8: =EF8*B8 -> 2961 | EM8: 1 | FR8: 1 | FX8: 1 | FZ8: 1 | GH8: =sum(EI8:GG8) -> 4 | GI8: =GH8*B8 -> 1316 | HG8: 1 | HM8: 1 | HQ8: 1 | HT8: 1 | HZ8: 1 | IO8: 1 | JR8: 1 | JX8: 2
A9: Mountain Breeze | B9: 329 | CE9: =sum(C9:CD9) -> 0 | CF9: =CE9*B9 -> 0 | EF9: =sum(CH9:ED9) -> 0 | EG9: =EF9*B9 -> 0 | GH9: =sum(EI9:GG9) -> 0 | GI9: =GH9*EA9 -> 0
A10: Fresh Bamboo | B10: 329 | C10: 1 | M10: 1 | P10: 2 | U10: 1 | AA10: 1 | AC10: 1 | AD10: 1 | AE10: 1 | AG10: 1 | AH10: 1 | AI10: 1 | AJ10: 1 | AL10: 1 | BK10: 1 | BP10: 1 | BR10: 1 | BS10: 1 | BZ10: 4 | CE10: =sum(C10:CD10) -> 22 | CF10: =CE10*B10 -> 7238 | CI10: 1 | CJ10: 1 | DI10: 1 | DK10: 1 | EF10: =sum(CH10:ED10) -> 4 | EG10: =EF10*B10 -> 1316 | EP10: 1 | EQ10: 1 | FD10: 1 | FI10: 1 | FP10: 1 | GH10: =sum(EI10:GG10) -> 5 | GI10: =GH10*B10 -> 1645 | GU10: 1 | HH10: 1 | HM10: 1 | HT10: 1 | II10: 1 | IY10: 1 | JA10: 1 | JH10: 1 | JJ10: 2 | JL10: 1 | JO10: 1 | JW10: 1 | JZ10: 1
A11: Beach Escape | B11: 329 | C11: 1 | CE11: =sum(C11:CD11) -> 1 | CF11: =CE11*B11 -> 329 | DS11: 1 | EF11: =sum(CH11:ED11) -> 1 | EG11: =EF11*B11 -> 329 | ER11: 1 | ES11: 1 | ET11: 1 | EU11: 1 | FT11: 2 | FV11: 1 | FX11: 1 | GH11: =sum(EI11:GG11) -> 8 | GI11: =GH11*B11 -> 2632 | GP11: 1 | GV11: 1 | HK11: 1 | HZ11: 1 | JM11: 2 | JU11: 1
A12: White Tea | B12: 329 | C12: 1 | I12: 1 | O12: 1 | AA12: 1 | AT12: 1 | AY12: 1 | BI12: 1 | BT12: 1 | BW12: 1 | BX12: 1 | CC12: 1 | CE12: =sum(C12:CD12) -> 11 | CF12: =CE12*B12 -> 3619 | CI12: 1 | CK12: 1 | CL12: 1 | CP12: 1 | CQ12: 1 | DZ12: 1 | EC12: 1 | EF12: =sum(CH12:ED12) -> 7 | EG12: =EF12*B12 -> 2303 | ER12: 1 | ET12: 1 | FL12: 2 | FX12: 1 | GC12: 1 | GH12: =sum(EI12:GG12) -> 6 | GI12: =GH12*B12 -> 1974 | GP12: 1 | GQ12: 1 | GS12: 1 | HR12: 1 | HU12: 2 | II12: 1 | IR12: 1 | IU12: 1 | IW12: 1 | JC12: 1 | JG12: 1 | JN12: 1 | JO12: 1
A13: Candy Cane | B13: 329 | G13: 1 | X13: 1 | AY13: 1 | CE13: =sum(C13:CD13) -> 3 | CF13: =CE13*B13 -> 987 | EF13: =sum(CH13:ED13) -> 0 | EG13: =EF13*B13 -> 0 | EZ13: 1 | FV13: 1 | GH13: =sum(EI13:GG13) -> 2 | GI13: =GH13*B13 -> 658 | GT13: 1
A14: Apple Cinnamon | B14: 329 | G14: 2 | Q14: 1 | AO14: 1 | CE14: =sum(C14:CD14) -> 4 | CF14: =CE14*B14 -> 1316 | DJ14: 2 | DW14: 1 | EF14: =sum(CH14:ED14) -> 3 | EG14: =EF14*B14 -> 987 | GH14: =sum(EI14:GG14) -> 0 | GI14: =GH14*B14 -> 0 | HH14: 1 | II14: 1 | IN14: 1 | IX14: 1
A15: Easy Drive | B15: 219 | AO15: 1 | CE15: =sum(C15:CD15) -> 1 | CF15: =CE15*B15 -> 219 | CR15: 1 | CT15: 1 | CW15: 1 | EF15: =sum(CH15:ED15) -> 3 | EG15: =EF15*B15 -> 657 | EL15: 2 | EW15: 1 | EZ15: 1 | GH15: =sum(EI15:GG15) -> 4 | GI15: =GH15*B15 -> 876 | IZ15: 1 | JY15: 1
A16: InLove | CE16: =sum(C16:CD16) -> 0 | CF16: =CE16*B16 -> 0 | EF16: =sum(CH16:ED16) -> 0 | EG16: =EF16*B16 -> 0 | GH16: =sum(EI16:GG16) -> 0 | GI16: =GH16*B16 -> 0
A17: Bright Mornings HW | CE17: =sum(C17:CD17) -> 0 | CF17: =CE17*B17 -> 0 | EF17: =sum(CH17:ED17) -> 0 | EG17: =EF17*B17 -> 0 | GH17: =sum(EI17:GG17) -> 0 | GI17: =GH17*B17 -> 0
CE18: =sum(C18:CD18) -> 0 | CF18: =CE18*B18 -> 0 | EF18: =sum(CH18:ED18) -> 0 | EG18: =EF18*B18 -> 0 | GH18: =sum(EI18:GG18) -> 0 | GI18: =GH18*B18 -> 0
A19: Lavender | B19: 239 | BR19: 1 | CE19: =sum(C19:CD19) -> 1 | CF19: =CE19*B19 -> 239 | EF19: =sum(CH19:ED19) -> 0 | EG19: =EF19*B19 -> 0 | GH19: =sum(EI19:GG19) -> 0 | GI19: =GH19*B19 -> 0
A20: Eucalyptus | B20: 239 | CE20: =sum(C20:CD20) -> 0 | CF20: =CE20*B20 -> 0 | EF20: =sum(CH20:ED20) -> 0 | EG20: =EF20*B20 -> 0 | GH20: =sum(EI20:GG20) -> 0 | GI20: =GH20*B20 -> 0
A21: Peppermint | B21: 239 | CE21: =sum(C21:CD21) -> 0 | CF21: =CE21*B21 -> 0 | DC21: 3 | EF21: =sum(CH21:ED21) -> 3 | EG21: =EF21*B21 -> 717 | GC21: 1 | GH21: =sum(EI21:GG21) -> 1 | GI21: =GH21*B21 -> 239
A22: Fresh Bamboo FO | B22: 219 | AU22: 1 | AV22: 1 | AZ22: 1 | CE22: =sum(C22:CD22) -> 3 | CF22: =CE22*B22 -> 657 | EF22: =sum(CH22:ED22) -> 0 | EG22: =EF22*B22 -> 0 | GH22: =sum(EI22:GG22) -> 0 | GI22: =GH22*B22 -> 0
A23: Beach Escape FO | B23: 219 | H23: p | AV23: 1 | CE23: =sum(C23:CD23) -> 1 | CF23: =CE23*B23 -> 219 | EF23: =sum(CH23:ED23) -> 0 | EG23: =EF23*B23 -> 0 | GH23: =sum(EI23:GG23) -> 0 | GI23: =GH23*B23 -> 0 | IQ23: 1
A24: White Tea FO | B24: 219 | CE24: =sum(C24:CD24) -> 0 | CF24: =CE24*B24 -> 0 | EF24: =sum(CH24:ED24) -> 0 | EG24: =EF24*B24 -> 0 | GH24: =sum(EI24:GG24) -> 0 | GI24: =GH24*B24 -> 0 | GY24: 1
A25: Bright Mornings FO | B25: 219 | CE25: =sum(C25:CD25) -> 0 | CF25: =CE25*B25 -> 0 | EF25: =sum(CH25:ED25) -> 0 | EG25: =EF25*B25 -> 0 | GH25: =sum(EI25:GG25) -> 0 | GI25: =GH25*B25 -> 0
A26: Quiet Elegance FO | B26: 219 | CE26: =sum(C26:CD26) -> 0 | CF26: =CE26*B26 -> 0 | EF26: =sum(CH26:ED26) -> 0 | EG26: =EF26*B26 -> 0 | GH26: =sum(EI26:GG26) -> 0 | GI26: =GH26*B26 -> 0
A27: Fresh Bamboo Diffuser | B27: 799 | W27: 1 | CE27: =sum(C27:CD27) -> 1 | CF27: =CE27*B27 -> 799 | EF27: =sum(CH27:ED27) -> 0 | EG27: =EF27*B27 -> 0 | GH27: =sum(EI27:GG27) -> 0 | GI27: =GH27*B27 -> 0 | JI27: 1
A28: Clean Air | B28: 609 | K28: 1 | AN28: 1 | AR28: 1 | BD28: 1 | CE28: =sum(C28:CD28) -> 4 | CF28: =CE28*B28 -> 2436 | DQ28: 1 | EE28: 1 | EF28: =sum(CH28:EE28) -> 2 | EG28: =EF28*B28 -> 1218 | FV28: 1 | GH28: =sum(EI28:GG28) -> 1 | GI28: =GH28*B28 -> 609 | GM28: 1 | GW28: 1 | HF28: 1 | HS28: 1 | HW28: 1 | IE28: 1 | IU28: 1 | JY28: 1
A29: Cotton Clean | B29: 329 | C29: 1 | D29: 1 | P29: 2 | T29: 1 | X29: 1 | Y29: 4 | AJ29: 1 | AQ29: 1 | AX29: 1 | AY29: 1 | BL29: 1 | BR29: 1 | BX29: 1 | CE29: =sum(C29:CD29) -> 17 | CF29: =CE29*B29 -> 5593 | CJ29: 1 | EF29: =sum(CH29:ED29) -> 1 | EG29: =EF29*B29 -> 329 | EN29: 1 | EO29: 2 | ES29: 1 | EU29: 1 | FA29: 1 | FI29: 1 | FK29: 1 | FW29: 1 | GB29: 1 | GH29: =sum(EI29:GG29) -> 10 | GI29: =GH29*B29 -> 3290 | GP29: 1 | HF29: 1 | HJ29: 3 | HS29: 1 | HY29: 1 | HZ29: 1 | IP29: 1 | JY29: 1
A30: Brighter Days | B30: 329 | CE30: =sum(C30:CD30) -> 0 | CF30: =CE30*B30 -> 0 | EF30: =sum(CH30:ED30) -> 0 | EG30: =EF30*B30 -> 0 | GH30: =sum(EI30:GG30) -> 0 | GI30: =GH30*B30 -> 0
A31: Cotton Clean FO | B31: 219 | CE31: =sum(C31:CD31) -> 0 | CF31: =CE31*B31 -> 0 | EF31: =sum(CH31:ED31) -> 0 | EG31: =EF31*B31 -> 0 | GH31: =sum(EI31:GG31) -> 0 | GI31: =GH31*B31 -> 0
A32: Brighter Days EO | B32: 219 | CE32: =sum(C32:CD32) -> 0 | CF32: =CE32*B32 -> 0 | EF32: =sum(CH32:ED32) -> 0 | EG32: =EF32*B32 -> 0 | GH32: =sum(EI32:GG32) -> 0 | GI32: =GH32*B32 -> 0
A33: Fresh Bamboo Refill | B33: 439 | BO33: 1 | CE33: =sum(C33:CD33) -> 1 | CF33: =CE33*B33 -> 439 | CV33: 1 | EF33: =sum(CH33:ED33) -> 1 | EG33: =EF33*B33 -> 439 | FB33: 1 | GH33: =sum(EI33:GG33) -> 1 | GI33: =GH33*B33 -> 439 | GZ33: 1 | IZ33: 1
A34: Clean Air Refill 1000ml | B34: 899 | CE34: =sum(C34:CD34) -> 0 | CF34: =CE34*B34 -> 0 | EF34: =sum(CH34:ED34) -> 0 | EG34: =EF34*B34 -> 0 | GH34: =sum(EI34:GG34) -> 0 | GI34: =GH34*B34 -> 0
A35: Waterbased: Fresh Bamboo | B35: 549 | CE35: =sum(C35:CD35) -> 0 | CF35: =CE35*B35 -> 0 | EF35: =sum(CH35:ED35) -> 0 | EG35: =EF35*B35 -> 0 | GH35: =sum(EI35:GG35) -> 0 | GI35: =GH35*B35 -> 0 | JB35: 1
A36: Waterbased: Cotton Clean | B36: 549 | CE36: =sum(C36:CD36) -> 0 | CF36: =CE36*B36 -> 0 | EF36: =sum(CH36:ED36) -> 0 | EG36: =EF36*B36 -> 0 | EV36: 1 | GH36: =sum(EI36:GG36) -> 1 | GI36: =GH36*B36 -> 549
A37: Waterbased: White Tea | B37: 549 | O37: 1 | V37: 1 | CE37: =sum(C37:CD37) -> 2 | CF37: =CE37*B37 -> 1098 | EF37: =sum(CH37:ED37) -> 0 | EG37: =EF37*B37 -> 0 | FH37: 1 | GH37: =sum(EI37:GG37) -> 1 | GI37: =GH37*B37 -> 549
A38: White Tea Diffuser | B38: 799 | CE38: =sum(C38:CD38) -> 0 | CF38: =CE38*B38 -> 0 | DV38: 1 | EF38: =sum(CH38:ED38) -> 1 | EG38: =EF38*B38 -> 799 | FU38: 1 | GH38: =sum(EI38:GG38) -> 1 | GI38: =GH38*B38 -> 799
A39: Cotton Clean Diffuser | B39: 799 | CE39: =sum(C39:CD39) -> 0 | CF39: =CE39*B39 -> 0 | CV39: 1 | EF39: =sum(CH39:ED39) -> 1 | EG39: =EF39*B39 -> 799 | GH39: =sum(EI39:GG39) -> 0 | GI39: =GH39*B39 -> 0
A40: White Tea Diffuser Refill | B40: 439 | V40: 1 | AS40: 1 | CC40: 1 | CE40: =sum(C40:CD40) -> 3 | CF40: =CE40*B40 -> 1317 | EF40: =sum(CH40:ED40) -> 0 | EG40: =EF40*B40 -> 0 | FB40: 1 | GH40: =sum(EI40:GG40) -> 1 | GI40: =GH40*B40 -> 439 | IV40: 3
A41: Cotton Clean Diffuser Refill | B41: 439 | BC41: 2 | BO41: 1 | CE41: =sum(C41:CD41) -> 3 | CF41: =CE41*B41 -> 1317 | EF41: =sum(CH41:ED41) -> 0 | EG41: =EF41*B41 -> 0 | FB41: 1 | GH41: =sum(EI41:GG41) -> 1 | GI41: =GH41*B41 -> 439
A42: Reed Sticks | B42: 60 | V42: 1 | AF42: 1 | AV42: 1 | BC42: 1 | CE42: =sum(C42:CD42) -> 4 | CF42: =CE42*B42 -> 240 | CV42: 2 | EF42: =sum(CH42:ED42) -> 2 | EG42: =EF42*B42 -> 120 | EV42: 1 | FC42: 3 | FY42: 2 | GH42: =sum(EI42:GG42) -> 6 | GI42: =GH42*B42 -> 360 | JS42: 1
A43: Relaxing Naturals 500ml | B43: 609 | S43: 1 | AM43: 1 | BA43: 1 | CE43: =sum(C43:CD43) -> 3 | CF43: =CE43*B43 -> 1827 | CH43: 1 | CN43: 2 | CU43: 1 | CY43: 4 | DO43: 1 | DR43: 1 | DX43: 1 | DY43: 1 | EF43: =sum(CH43:ED43) -> 12 | EG43: =EF43*B43 -> 7308 | GA43: 1 | GH43: =sum(EI43:GG43) -> 1 | GI43: =GH43*B43 -> 609 | GW43: 1 | HN43: 1 | IE43: 1 | IK43: 1 | IM43: 1 | JD43: 1 | JK43: 4 | JP43: 1
A44: Hand Wash Relaxing Naturals 500ml | B44: 379 | G44: 1 | AF44: 1 | CE44: =sum(C44:CD44) -> 2 | CF44: =CE44*B44 -> 758 | EF44: =sum(CH44:ED44) -> 0 | EG44: =EF44*B44 -> 0 | GH44: =sum(EI44:GG44) -> 0 | GI44: =GH44*B44 -> 0
A45: Hand Wash Clean & Bright 500ml | B45: 379 | CE45: =sum(C45:CD45) -> 0 | CF45: =CE45*B45 -> 0 | DU45: 2 | EF45: =sum(CH45:ED45) -> 2 | EG45: =EF45*B45 -> 758 | EV45: 1 | GH45: =sum(EI45:GG45) -> 1 | GI45: =GH45*B45 -> 379 | IJ45: 1
A46: Keep it Clean Gift Set | B46: 1299 | CE46: =sum(C46:CD46) -> 0 | CF46: =CE46*B46 -> 0 | EF46: =sum(CH46:ED46) -> 0 | EG46: =EF46*B46 -> 0 | GH46: =sum(EI46:GG46) -> 0 | GI46: =GH46*B46 -> 0
A47: Relax With Me | B47: 1299 | CE47: =sum(C47:CD47) -> 0 | CF47: =CE47*B47 -> 0 | EF47: =sum(CH47:ED47) -> 0 | EG47: =EF47*B47 -> 0 | GH47: =sum(EI47:GG47) -> 0 | GI47: =GH47*B47 -> 0 | JI47: 1
A48: Simoy ng Pahiyas | B48: 0 | CE48: =sum(C48:CD48) -> 0 | CF48: =CE48*B48 -> 0 | EF48: =sum(CH48:ED48) -> 0 | EG48: =EF48*B48 -> 0 | GH48: =sum(EI48:GG48) -> 0 | GI48: =GH48*B48 -> 0
CE49: =sum(C49:CD49) -> 0 | CF49: =CE49*B49 -> 0 | EF49: =sum(CH49:ED49) -> 0 | EG49: =EF49*B49 -> 0 | GH49: =sum(EI49:GG49) -> 0 | GI49: =GH49*B49 -> 0
A50: Fresh Bamboo 500ml | B50: 609 | E50: 1 | S50: 2 | Z50: 1 | AW50: 1 | BA50: 1 | BE50: 1 | BH50: 2 | BQ50: 1 | BV50: 1 | CA50: 1 | CE50: =sum(C50:CD50) -> 12 | CF50: =CE50*B50 -> 7308 | CM50: 2 | CS50: 1 | CT50: 1 | CX50: 1 | DE50: 1 | DL50: 1 | DM50: 1 | EB50: 3 | EE50: 1 | EF50: =sum(CH50:EE50) -> 12 | EG50: =EF50*B50 -> 7308 | FM50: 1 | FO50: 2 | GD50: 1 | GE50: 1 | GH50: =sum(EI50:GG50) -> 5 | GI50: =GH50*B50 -> 3045 | HA50: 2 | HB50: 3 | HC50: 2 | HI50: 2 | HK50: 1 | HO50: 1 | HP50: 2 | IS50: 3 | JQ50: 1 | JT50: 1 | KA50: 1
A51: White Tea 500ml | B51: 609 | J51: 1 | N51: 1 | CB51: 1 | CE51: =sum(C51:CD51) -> 3 | CF51: =CE51*B51 -> 1827 | EF51: =sum(CH51:ED51) -> 0 | EG51: =EF51*B51 -> 0 | FG51: 1 | FM51: 1 | GG51: 1 | GH51: =sum(EI51:GG51) -> 3 | GI51: =GH51*B51 -> 1827 | GK51: 1 | HL51: 1 | HN51: 1 | IL51: 2 | JV51: 1 | KA51: 1
A52: Tropical Paradise 200ml | B52: 329 | CE52: =sum(C52:CD52) -> 0 | CF52: =CE52*B52 -> 0 | EF52: =sum(CH52:ED52) -> 0 | EG52: =EF52*B52 -> 0 | GH52: =sum(EI52:GG52) -> 0 | GI52: =GH52*B52 -> 0
A53: RN Wash 50ml | B53: 199 | CE53: =sum(C53:CD53) -> 0 | CF53: =CE53*B53 -> 0 | EF53: =sum(CH53:ED53) -> 0 | EG53: =EF53*B53 -> 0 | GH53: =sum(EI53:GG53) -> 0 | GI53: =GH53*B53 -> 0
A54: CB Wash 50ml | B54: 199 | CE54: =sum(C54:CD54) -> 0 | CF54: =CE54*B54 -> 0 | CW54: 1 | EF54: =sum(CH54:ED54) -> 1 | EG54: =EF54*B54 -> 199 | FE54: 1 | GH54: =sum(EI54:GG54) -> 1 | GI54: =GH54*B54 -> 199
A55: Travel With Me | B55: 599 | CE55: =sum(C55:CD55) -> 0 | CF55: =CE55*B55 -> 0 | EF55: =sum(CH55:ED55) -> 0 | EG55: =EF55*B55 -> 0 | GH55: =sum(EI55:GG55) -> 0 | GI55: =GH55*B55 -> 0
A56: Handwash: Relaxing Naturals Gallon | B56: 1499 | CE56: =sum(C56:CD56) -> 0 | CF56: =CE56*B56 -> 0 | EF56: =sum(CH56:ED56) -> 0 | EG56: =EF56*B56 -> 0 | GH56: =sum(EI56:GG56) -> 0 | GI56: =GH56*B56 -> 0 | HN56: 1
CE57: =sum(C57:CD57) -> 0 | CF57: =CE57*B57 -> 0 | EF57: =sum(CH57:ED57) -> 0 | EG57: =EF57*B57 -> 0 | GH57: =sum(EI57:GG57) -> 0 | GI57: =GH57*B57 -> 0
A58: Creamy Matcha | B58: 329 | C58: 1 | K58: 1 | R58: 1 | AK58: 2 | AY58: 1 | CE58: =sum(C58:CD58) -> 6 | CF58: =CE58*B58 -> 1974 | DP58: 1 | EF58: =sum(CH58:ED58) -> 1 | EG58: =EF58*B58 -> 329 | EX58: 1 | GC58: 1 | GH58: =sum(EI58:GG58) -> 2 | GI58: =GH58*B58 -> 658 | GR58: 1 | GV58: 1 | HD58: 1 | JF58: 2
A59: White Lavender | B59: 329 | AY59: 1 | BU59: 1 | CE59: =sum(C59:CD59) -> 2 | CF59: =CE59*B59 -> 658 | DG59: 1 | EF59: =sum(CH59:ED59) -> 1 | EG59: =EF59*B59 -> 329 | EV59: 1 | EY59: 2 | GH59: =sum(EI59:GG59) -> 3 | GI59: =GH59*B59 -> 987 | HF59: 1
A60: Green Tea | B60: 329 | BF60: 1 | BY60: 1 | CE60: =sum(C60:CD60) -> 2 | CF60: =CE60*B60 -> 658 | EF60: =sum(CH60:ED60) -> 0 | EG60: =EF60*B60 -> 0 | FS60: 1 | GH60: =sum(EI60:GG60) -> 1 | GI60: =GH60*B60 -> 329 | GX60: 1 | HX60: 1 | IT60: 1 | IU60: 1 | IY60: 1 | JO60: 1
A61: Clean Air 100ml | B61: 249 | CE61: =sum(C61:CD61) -> 0 | CF61: =CE61*B61 -> 0 | EF61: =sum(CH61:ED61) -> 0 | EG61: =EF61*B61 -> 0 | FF61: 1 | GH61: =sum(EI61:GG61) -> 1 | GI61: =GH61*B61 -> 249 | ID61: 1 | JE61: 1
A62: Creamy Matcha Diffuser Refill | B62: 439 | CE62: =sum(C62:CD62) -> 0 | CF62: =CE62*B62 -> 0 | EF62: =sum(CH62:ED62) -> 0 | EG62: =EF62*B62 -> 0 | GH62: =sum(EI62:GG62) -> 0 | GI62: =GH62*B62 -> 0
A63: White Lavender Diffuser Refill | B63: 439 | L63: 2 | AF63: 1 | AS63: 1 | AV63: 1 | CD63: 2 | CE63: =sum(C63:CD63) -> 7 | CF63: =CE63*B63 -> 3073 | DB63: 1 | DV63: 1 | EF63: =sum(CH63:ED63) -> 2 | EG63: =EF63*B63 -> 878 | EI63: 3 | EV63: 1 | FJ63: 1 | GH63: =sum(EI63:GG63) -> 5 | GI63: =GH63*B63 -> 2195 | GZ63: 1
A64: Green Tea Diffuser Refill | B64: 439 | CC64: 1 | CE64: =sum(C64:CD64) -> 1 | CF64: =CE64*B64 -> 439 | EF64: =sum(CH64:ED64) -> 0 | EG64: =EF64*B64 -> 0 | GH64: =sum(EI64:GG64) -> 0 | GI64: =GH64*B64 -> 0
A65: Creamy Matcha Diffuser | B65: 799 | CE65: =sum(C65:CD65) -> 0 | CF65: =CE65*B65 -> 0 | EF65: =sum(CH65:ED65) -> 0 | EG65: =EF65*B65 -> 0 | GH65: =sum(EI65:GG65) -> 0 | GI65: =GH65*B65 -> 0
A66: White Lavender Diffuser | B66: 799 | BJ66: 1 | CE66: =sum(C66:CD66) -> 1 | CF66: =CE66*B66 -> 799 | EF66: =sum(CH66:ED66) -> 0 | EG66: =EF66*B66 -> 0 | GH66: =sum(EI66:GG66) -> 0 | GI66: =GH66*B66 -> 0
A67: Green Tea Diffuser | B67: 799 | CE67: =sum(C67:CD67) -> 0 | CF67: =CE67*B67 -> 0 | EF67: =sum(CH67:ED67) -> 0 | EG67: =EF67*B67 -> 0 | GH67: =sum(EI67:GG67) -> 0 | GI67: =GH67*B67 -> 0
A68: Creamy Matcha + Roomspray | B68: 1299 | CE68: =sum(C68:CD68) -> 0 | CF68: =CE68*B68 -> 0 | EF68: =sum(CH68:ED68) -> 0 | EG68: =EF68*B68 -> 0 | GH68: =sum(EI68:GG68) -> 0 | GI68: =GH68*B68 -> 0
A69: White Lavender + Roomspray | B69: 1299 | CE69: =sum(C69:CD69) -> 0 | CF69: =CE69*B69 -> 0 | EF69: =sum(CH69:ED69) -> 0 | EG69: =EF69*B69 -> 0 | GH69: =sum(EI69:GG69) -> 0 | GI69: =GH69*B69 -> 0
A70: Green Tea + Roomspray | B70: 1299 | CE70: =sum(C70:CD70) -> 0 | CF70: =CE70*B70 -> 0 | EF70: =sum(CH70:ED70) -> 0 | EG70: =EF70*B70 -> 0 | GH70: =sum(EI70:GG70) -> 0 | GI70: =GH70*B70 -> 0
A71: Cotton Clean 500ml | B71: 609 | BE71: 1 | CE71: =sum(C71:CD71) -> 1 | CF71: =CE71*B71 -> 609 | CO71: 1 | CW71: 1 | CZ71: 1 | DD71: 1 | DE71: 1 | EF71: =sum(CH71:ED71) -> 5 | EG71: =EF71*B71 -> 3045 | EK71: 1 | FM71: 1 | FZ71: 1 | GH71: =sum(EI71:GG71) -> 3 | GI71: =GH71*B71 -> 1827 | HE71: 1 | HX71: 1 | JV71: 1
A72: Modern Luxe Reed Diffuser | B72: 1599 | CE72: =sum(C72:CD72) -> 0 | CF72: =CE72*B72 -> 0 | EF72: =sum(CH72:ED72) -> 0 | EG72: =EF72*B72 -> 0 | GH72: =sum(EI72:GG72) -> 0 | GI72: =GH72*B72 -> 0
A73: Serene Sanctuary Reed Diffuser | B73: 1599 | CE73: =sum(C73:CD73) -> 0 | CF73: =CE73*B73 -> 0 | EF73: =sum(CH73:ED73) -> 0 | EG73: =EF73*B73 -> 0 | GH73: =sum(EI73:GG73) -> 0 | GI73: =GH73*B73 -> 0
A74: Urban Oasis Reed Diffuser | B74: 1599 | CE74: =sum(C74:CD74) -> 0 | CF74: =CE74*B74 -> 0 | EF74: =sum(CH74:ED74) -> 0 | EG74: =EF74*B74 -> 0 | GH74: =sum(EI74:GG74) -> 0 | GI74: =GH74*B74 -> 0
A75: Clean Air Gallon | CE75: =sum(C75:CD75) -> 0 | CF75: =CE75*B75 -> 0 | EF75: =sum(CH75:ED75) -> 0 | EG75: =EF75*B75 -> 0 | GH75: =sum(EI75:GG75) -> 0 | GI75: =GH75*B75 -> 0
CE76: =sum(C76:CD76) -> 0 | CF76: =CE76*B76 -> 0 | EF76: =sum(CH76:ED76) -> 0 | EG76: =EF76*B76 -> 0 | GH76: =sum(EI76:GG76) -> 0 | GI76: =GH76*B76 -> 0
A77: Holiday Hugs 200ml | B77: 379 | G77: 2 | BM77: 2 | CE77: =sum(C77:CD77) -> 4 | CF77: =CE77*B77 -> 1516 | EF77: =sum(CH77:ED77) -> 0 | EG77: =EF77*B77 -> 0 | GH77: =sum(EI77:GG77) -> 0 | GI77: =GH77*B77 -> 0 | GO77: 1
A78: Holiday Hugs Diffuser Set | B78: 799 | CE78: =sum(C78:CD78) -> 0 | CF78: =CE78*B78 -> 0 | EF78: =sum(CH78:ED78) -> 0 | EG78: =EF78*B78 -> 0 | GH78: =sum(EI78:GG78) -> 0 | GI78: =GH78*B78 -> 0
A79: Holiday Hugs Refill | B79: 439 | CE79: =sum(C79:CD79) -> 0 | CF79: =CE79*B79 -> 0 | EF79: =sum(CH79:ED79) -> 0 | EG79: =EF79*B79 -> 0 | GH79: =sum(EI79:GG79) -> 0 | GI79: =GH79*B79 -> 0
A80: Bathroom Kit | B80: 599 | CE80: =sum(C80:CD80) -> 0 | CF80: =CE80*B80 -> 0 | EF80: =sum(CH80:ED80) -> 0 | EG80: =EF80*B80 -> 0 | GH80: =sum(EI80:GG80) -> 0 | GI80: =GH80*B80 -> 0
A81: Flushie 50ml | B81: 229 | G81: 1 | AF81: 1 | CE81: =sum(C81:CD81) -> 2 | CF81: =CE81*B81 -> 458 | DA81: 4 | EF81: =sum(CH81:ED81) -> 4 | EG81: =EF81*B81 -> 916 | EJ81: 3 | EZ81: 1 | FN81: 1 | FX81: 1 | GH81: =sum(EI81:GG81) -> 6 | GI81: =GH81*B81 -> 1374 | GN81: 2 | HV81: 1 | IC81: 2 | IJ81: 1
A82: Easy Drive Grapefuit | B82: 219 | H82: 1 | CE82: =sum(C82:CD82) -> 1 | CF82: =CE82*B82 -> 219 | EF82: =sum(CH82:ED82) -> 0 | EG82: =EF82*B82 -> 0 | GH82: =sum(EI82:GG82) -> 0 | GI82: =GH82*B82 -> 0
A83: Fresh Bamboo Diffuser + Roomspray | B83: 1299 | BB83: 1 | CE83: =sum(C83:CD83) -> 1 | CF83: =CE83*B83 -> 1299 | EF83: =sum(CH83:ED83) -> 0 | EG83: =EF83*B83 -> 0 | GH83: =sum(EI83:GG83) -> 0 | GI83: =GH83*B83 -> 0
A84: White Tea Diffuser + Roomspray | B84: 1299 | CE84: =sum(C84:CD84) -> 0 | CF84: =CE84*B84 -> 0 | EF84: =sum(CH84:ED84) -> 0 | EG84: =EF84*B84 -> 0 | GH84: =sum(EI84:GG84) -> 0 | GI84: =GH84*B84 -> 0
A85: Cotton Clean Diffuser + Roomspray | B85: 1299 | CE85: =sum(C85:CD85) -> 0 | CF85: =CE85*B85 -> 0 | EF85: =sum(CH85:ED85) -> 0 | EG85: =EF85*B85 -> 0 | GH85: =sum(EI85:GG85) -> 0 | GI85: =GH85*B85 -> 0
A86: Holiday Hugs Diffuser + Roomspray | B86: 1299 | CE86: =sum(C86:CD86) -> 0 | CF86: =CE86*B86 -> 0 | EF86: =sum(CH86:ED86) -> 0 | EG86: =EF86*B86 -> 0 | GH86: =sum(EI86:GG86) -> 0 | GI86: =GH86*B86 -> 0
CE87: =sum(C87:CD87) -> 0 | CF87: =CE87*B87 -> 0 | EF87: =sum(CH87:ED87) -> 0 | EG87: =EF87*B87 -> 0 | GH87: =sum(EI87:GG87) -> 0 | GI87: =GH87*B87 -> 0
A88: Sleep All Day | B88: 679 | CE88: =sum(C88:CD88) -> 0 | CF88: =CE88*B88 -> 0 | EF88: =sum(CH88:ED88) -> 0 | EG88: =EF88*B88 -> 0 | GH88: =sum(EI88:GG88) -> 0 | GI88: =GH88*B88 -> 0
A89: One Way Ticket | B89: 679 | CE89: =sum(C89:CD89) -> 0 | CF89: =CE89*B89 -> 0 | EF89: =sum(CH89:ED89) -> 0 | EG89: =EF89*B89 -> 0 | GH89: =sum(EI89:GG89) -> 0 | GI89: =GH89*B89 -> 0
A90: Holiday Cheer | B90: 679 | CE90: =sum(C90:CD90) -> 0 | CF90: =CE90*B90 -> 0 | EF90: =sum(CH90:ED90) -> 0 | EG90: =EF90*B90 -> 0 | GH90: =sum(EI90:GG90) -> 0 | GI90: =GH90*B90 -> 0
CE91: =sum(C91:CD91) -> 0 | CF91: =CE91*B91 -> 0 | EF91: =sum(CH91:ED91) -> 0 | EG91: =EF91*B91 -> 0 | GH91: =sum(EI91:GG91) -> 0 | GI91: =GH91*B91 -> 0
A92: High Enery Gift Set (Essential Oils) | B92: 490 | CE92: =sum(C92:CD92) -> 0 | CF92: =CE92*B92 -> 0 | EF92: =sum(CH92:ED92) -> 0 | EG92: =EF92*B92 -> 0 | GH92: =sum(EI92:GG92) -> 0 | GI92: =GH92*B92 -> 0
A93: Romantic Date Gift Set (Essential Oils) | B93: 490 | CE93: =sum(C93:CD93) -> 0 | CF93: =CE93*B93 -> 0 | EF93: =sum(CH93:ED93) -> 0 | EG93: =EF93*B93 -> 0 | GH93: =sum(EI93:GG93) -> 0 | GI93: =GH93*B93 -> 0
A94: One Way Ticket Gift Set (Fragrance Oils) | B94: 450 | CE94: =sum(C94:CD94) -> 0 | CF94: =CE94*B94 -> 0 | EF94: =sum(CH94:ED94) -> 0 | EG94: =EF94*B94 -> 0 | GH94: =sum(EI94:GG94) -> 0 | GI94: =GH94*B94 -> 0
A95: Quality Time Gift Set (Fragrance Oils) | B95: 450 | CE95: =sum(C95:CD95) -> 0 | CF95: =CE95*B95 -> 0 | EF95: =sum(CH95:ED95) -> 0 | EG95: =EF95*B95 -> 0 | GH95: =sum(EI95:GG95) -> 0 | GI95: =GH95*B95 -> 0
CE96: =sum(C96:CD96) -> 0 | CF96: =CE96*B96 -> 0 | EF96: =sum(CH96:ED96) -> 0 | EG96: =EF96*B96 -> 0 | GH96: =sum(EI96:GG96) -> 0 | GI96: =GH96*B96 -> 0
A97: Fresh Start Kit | B97: 1054 | CE97: =sum(C97:CD97) -> 0 | CF97: =CE97*B97 -> 0 | EF97: =sum(CH97:ED97) -> 0 | EG97: =EF97*B97 -> 0 | GH97: =sum(EI97:GG97) -> 0 | GI97: =GH97*B97 -> 0
A98: Quite Olive RLS | B98: 329 | FP98: 1 | FQ98: 1 | FY98: 1 | GC98: 1 | GF98: 1 | GH98: =sum(EI98:GG98) -> 5 | GI98: =GH98*B98 -> 1645 | GL98: 1 | GO98: 1 | GX98: 1 | IA98: 1 | IB98: 3
A99: Quite Olive Refill | B99: 439 | GH99: =sum(EI99:GG99) -> 0 | GI99: =GH99*B99 -> 0
A100: Quite Olive Reed Set | B100: 799 | FY100: 1 | GH100: =sum(EI100:GG100) -> 1 | GI100: =GH100*B100 -> 799
A101: Custom Order | GH101: =sum(EI101:GG101) -> 0 | GI101: =GH101*EA101 -> 0
...

Sheet SHOPIFY
X2: april | AH2: MAY
A3: VARIANT | B3: PRICE | C3: Anna Marie Sy | D3: Papoose Olizon | E3: Sarah Gonzalez-Garcia | I3: Bev Joson | J3: Arlette Aguirre-Reyes | K3: Black Tie Events | L3: Travellers International Hotel Group Inc. Hotel Okura | P3: Papoose | Q3: Westlake Medical Center | R3: aggie calubaquib | S3: Claire Clementir- Ariete | T3: Kitchen Pro Concepts and Management Inc | X3: Aisha Rhea Catolico | Y3: Travellers International Hotel Group Inc. Hotel Okura | Z3: Ria Olizon | AA3: ADRIAN OLIZON | AB3: Pareb Munreb | AC3: Olison Corporation | AD3: Ria Olizon | AH3: Black Tie Events | AI3: Ria Olizon | AJ3: Ria Olizon | AK3: Dianne Khu | AL3: Glenda Balatbat
C4: 46028 | D4: 46029 | E4: 46030 | I4: 46057 | J4: 46059 | K4: 46059 | L4: 46060 | P4: 46099 | Q4: 46100 | R4: 46101 | S4: 46102 | T4: 46103
A5: Quiet Elegance | B5: 329
A6: Charming Home | B6: 329
A7: Bright Mornings | B7: 329
A8: Relaxing Naturals | B8: 329 | F8: =sum(C8:E8) -> 0 | G8: =F8*B8 -> 0 | M8: =sum(I8:L8) -> 0 | N8: =M8*B8 -> 0 | U8: =sum(P8:T8) -> 0 | V8: =U8*J8 -> 0 | AB8: 1 | AD8: 5 | AI8: 2
A9: Mountain Breeze | B9: 329 | F9: =sum(C9:E9) -> 0 | G9: =F9*B9 -> 0 | M9: =sum(I9:L9) -> 0 | N9: =M9*B9 -> 0 | U9: =sum(P9:T9) -> 0 | V9: =U9*J9 -> 0
A10: Fresh Bamboo | B10: 329 | F10: =sum(C10:E10) -> 0 | G10: =F10*B10 -> 0 | M10: =sum(I10:L10) -> 0 | N10: =M10*B10 -> 0 | U10: =sum(P10:T10) -> 0 | V10: =U10*J10 -> 0
A11: Beach Escape | B11: 329 | D11: 1 | F11: =sum(C11:E11) -> 1 | G11: =F11*B11 -> 329 | J11: 2 | M11: =sum(I11:L11) -> 2 | N11: =M11*B11 -> 658 | U11: =sum(P11:T11) -> 0 | V11: =U11*J11 -> 0
A12: White Tea | B12: 329 | D12: 1 | F12: =sum(C12:E12) -> 1 | G12: =F12*B12 -> 329 | M12: =sum(I12:L12) -> 0 | N12: =M12*B12 -> 0 | R12: 2 | S12: 1 | U12: =sum(P12:T12) -> 3 | V12: =U12*J12 -> 0
A13: Candy Cane | B13: 329 | F13: =sum(C13:E13) -> 0 | G13: =F13*B13 -> 0 | M13: =sum(I13:L13) -> 0 | N13: =M13*B13 -> 0 | U13: =sum(P13:T13) -> 0 | V13: =U13*J13 -> 0
A14: Apple Cinnamon | B14: 329 | D14: 3 | F14: =sum(C14:E14) -> 3 | G14: =F14*B14 -> 987 | M14: =sum(I14:L14) -> 0 | N14: =M14*B14 -> 0 | U14: =sum(P14:T14) -> 0 | V14: =U14*J14 -> 0
A15: Easy Drive | B15: 219 | F15: =sum(C15:E15) -> 0 | G15: =F15*B15 -> 0 | M15: =sum(I15:L15) -> 0 | N15: =M15*B15 -> 0 | U15: =sum(P15:T15) -> 0 | V15: =U15*J15 -> 0 | AI15: 2
A16: InLove | F16: =sum(C16:E16) -> 0 | G16: =F16*B16 -> 0 | M16: =sum(I16:L16) -> 0 | N16: =M16*B16 -> 0 | U16: =sum(P16:T16) -> 0 | V16: =U16*J16 -> 0
A17: Bright Mornings HW | F17: =sum(C17:E17) -> 0 | G17: =F17*B17 -> 0 | M17: =sum(I17:L17) -> 0 | N17: =M17*B17 -> 0 | U17: =sum(P17:T17) -> 0 | V17: =U17*J17 -> 0
F18: =sum(C18:E18) -> 0 | G18: =F18*B18 -> 0 | M18: =sum(I18:L18) -> 0 | N18: =M18*B18 -> 0 | U18: =sum(P18:T18) -> 0 | V18: =U18*J18 -> 0
A19: Lavender | B19: 239 | D19: 1 | F19: =sum(C19:E19) -> 1 | G19: =F19*B19 -> 239 | M19: =sum(I19:L19) -> 0 | N19: =M19*B19 -> 0 | U19: =sum(P19:T19) -> 0 | V19: =U19*J19 -> 0
A20: Eucalyptus | B20: 239 | D20: 1 | F20: =sum(C20:E20) -> 1 | G20: =F20*B20 -> 239 | M20: =sum(I20:L20) -> 0 | N20: =M20*B20 -> 0 | U20: =sum(P20:T20) -> 0 | V20: =U20*J20 -> 0
A21: Peppermint | B21: 239 | D21: 1 | F21: =sum(C21:E21) -> 1 | G21: =F21*B21 -> 239 | M21: =sum(I21:L21) -> 0 | N21: =M21*B21 -> 0 | U21: =sum(P21:T21) -> 0 | V21: =U21*J21 -> 0
A22: Fresh Bamboo FO | B22: 219 | F22: =sum(C22:E22) -> 0 | G22: =F22*B22 -> 0 | M22: =sum(I22:L22) -> 0 | N22: =M22*B22 -> 0 | U22: =sum(P22:T22) -> 0 | V22: =U22*J22 -> 0
A23: Beach Escape FO | B23: 219 | F23: =sum(C23:E23) -> 0 | G23: =F23*B23 -> 0 | M23: =sum(I23:L23) -> 0 | N23: =M23*B23 -> 0 | U23: =sum(P23:T23) -> 0 | V23: =U23*J23 -> 0
A24: White Tea FO | B24: 219 | F24: =sum(C24:E24) -> 0 | G24: =F24*B24 -> 0 | M24: =sum(I24:L24) -> 0 | N24: =M24*B24 -> 0 | U24: =sum(P24:T24) -> 0 | V24: =U24*J24 -> 0
A25: Bright Mornings FO | B25: 219 | F25: =sum(C25:E25) -> 0 | G25: =F25*B25 -> 0 | M25: =sum(I25:L25) -> 0 | N25: =M25*B25 -> 0 | U25: =sum(P25:T25) -> 0 | V25: =U25*J25 -> 0
A26: Quiet Elegance FO | B26: 219 | F26: =sum(C26:E26) -> 0 | G26: =F26*B26 -> 0 | M26: =sum(I26:L26) -> 0 | N26: =M26*B26 -> 0 | U26: =sum(P26:T26) -> 0 | V26: =U26*J26 -> 0
A27: Fresh Bamboo Diffuser | B27: 799 | F27: =sum(C27:E27) -> 0 | G27: =F27*B27 -> 0 | J27: 2 | M27: =sum(I27:L27) -> 2 | N27: =M27*B27 -> 1598 | U27: =sum(P27:T27) -> 0 | V27: =U27*J27 -> 0
A28: Clean Air | B28: 609 | F28: =sum(C28:E28) -> 0 | G28: =F28*B28 -> 0 | M28: =sum(I28:L28) -> 0 | N28: =M28*B28 -> 0 | P28: 1 | U28: =sum(P28:T28) -> 1 | V28: =U28*J28 -> 0 | AI28: 2
A29: Cotton Clean | B29: 329 | F29: =sum(C29:E29) -> 0 | G29: =F29*B29 -> 0 | J29: 2 | M29: =sum(I29:L29) -> 2 | N29: =M29*B29 -> 658 | U29: =sum(P29:T29) -> 0 | V29: =U29*J29 -> 0
A30: Brighter Days | B30: 329 | F30: =sum(C30:E30) -> 0 | G30: =F30*B30 -> 0 | M30: =sum(I30:L30) -> 0 | N30: =M30*B30 -> 0 | U30: =sum(P30:T30) -> 0 | V30: =U30*J30 -> 0
A31: Cotton Clean FO | B31: 219 | F31: =sum(C31:E31) -> 0 | G31: =F31*B31 -> 0 | M31: =sum(I31:L31) -> 0 | N31: =M31*B31 -> 0 | U31: =sum(P31:T31) -> 0 | V31: =U31*J31 -> 0
A32: Brighter Days EO | B32: 219 | F32: =sum(C32:E32) -> 0 | G32: =F32*B32 -> 0 | M32: =sum(I32:L32) -> 0 | N32: =M32*B32 -> 0 | U32: =sum(P32:T32) -> 0 | V32: =U32*J32 -> 0
A33: Fresh Bamboo Refill | B33: 439 | F33: =sum(C33:E33) -> 0 | G33: =F33*B33 -> 0 | M33: =sum(I33:L33) -> 0 | N33: =M33*B33 -> 0 | U33: =sum(P33:T33) -> 0 | V33: =U33*J33 -> 0
A34: Clean Air Refill 1000ml | B34: 899 | F34: =sum(C34:E34) -> 0 | G34: =F34*B34 -> 0 | M34: =sum(I34:L34) -> 0 | N34: =M34*B34 -> 0 | U34: =sum(P34:T34) -> 0 | V34: =U34*J34 -> 0
A35: Waterbased: Fresh Bamboo | B35: 549 | F35: =sum(C35:E35) -> 0 | G35: =F35*B35 -> 0 | M35: =sum(I35:L35) -> 0 | N35: =M35*B35 -> 0 | U35: =sum(P35:T35) -> 0 | V35: =U35*J35 -> 0
A36: Waterbased: Cotton Clean | B36: 549 | F36: =sum(C36:E36) -> 0 | G36: =F36*B36 -> 0 | M36: =sum(I36:L36) -> 0 | N36: =M36*B36 -> 0 | U36: =sum(P36:T36) -> 0 | V36: =U36*J36 -> 0
A37: Waterbased: White Tea | B37: 549 | F37: =sum(C37:E37) -> 0 | G37: =F37*B37 -> 0 | M37: =sum(I37:L37) -> 0 | N37: =M37*B37 -> 0 | U37: =sum(P37:T37) -> 0 | V37: =U37*J37 -> 0
A38: White Tea Diffuser | B38: 799 | F38: =sum(C38:E38) -> 0 | G38: =F38*B38 -> 0 | M38: =sum(I38:L38) -> 0 | N38: =M38*B38 -> 0 | U38: =sum(P38:T38) -> 0 | V38: =U38*J38 -> 0
A39: Cotton Clean Diffuser | B39: 799 | F39: =sum(C39:E39) -> 0 | G39: =F39*B39 -> 0 | M39: =sum(I39:L39) -> 0 | N39: =M39*B39 -> 0 | U39: =sum(P39:T39) -> 0 | V39: =U39*J39 -> 0
A40: White Tea Diffuser Refill | B40: 439 | F40: =sum(C40:E40) -> 0 | G40: =F40*B40 -> 0 | M40: =sum(I40:L40) -> 0 | N40: =M40*B40 -> 0 | U40: =sum(P40:T40) -> 0 | V40: =U40*J40 -> 0
A41: Cotton Clean Diffuser Refill | B41: 439 | F41: =sum(C41:E41) -> 0 | G41: =F41*B41 -> 0 | M41: =sum(I41:L41) -> 0 | N41: =M41*B41 -> 0 | U41: =sum(P41:T41) -> 0 | V41: =U41*J41 -> 0
A42: Reed Sticks | B42: 60 | F42: =sum(C42:E42) -> 0 | G42: =F42*B42 -> 0 | M42: =sum(I42:L42) -> 0 | N42: =M42*B42 -> 0 | T42: 3 | U42: =sum(P42:T42) -> 3 | V42: =U42*J42 -> 0
A43: Relaxing Naturals 500ml | B43: 609 | F43: =sum(C43:E43) -> 0 | G43: =F43*B43 -> 0 | M43: =sum(I43:L43) -> 0 | N43: =M43*B43 -> 0 | U43: =sum(P43:T43) -> 0 | V43: =U43*J43 -> 0
A44: Hand Wash Relaxing Naturals 500ml | B44: 379 | F44: =sum(C44:E44) -> 0 | G44: =F44*B44 -> 0 | M44: =sum(I44:L44) -> 0 | N44: =M44*B44 -> 0 | U44: =sum(P44:T44) -> 0 | V44: =U44*J44 -> 0 | AB44: 1 | AI44: 2
A45: Hand Wash Clean & Bright 500ml | B45: 379 | F45: =sum(C45:E45) -> 0 | G45: =F45*B45 -> 0 | M45: =sum(I45:L45) -> 0 | N45: =M45*B45 -> 0 | U45: =sum(P45:T45) -> 0 | V45: =U45*J45 -> 0
A46: Keep it Clean Gift Set | B46: 1299 | E46: 1 | F46: =sum(C46:E46) -> 1 | G46: =F46*B46 -> 1299 | M46: =sum(I46:L46) -> 0 | N46: =M46*B46 -> 0 | P46: 1 | U46: =sum(P46:T46) -> 1 | V46: =U46*J46 -> 0
A47: Relax With Me | B47: 1299 | F47: =sum(C47:E47) -> 0 | G47: =F47*B47 -> 0 | M47: =sum(I47:L47) -> 0 | N47: =M47*B47 -> 0 | U47: =sum(P47:T47) -> 0 | V47: =U47*J47 -> 0
A48: Simoy ng Pahiyas | B48: 0 | F48: =sum(C48:E48) -> 0 | G48: =F48*B48 -> 0 | M48: =sum(I48:L48) -> 0 | N48: =M48*B48 -> 0 | U48: =sum(P48:T48) -> 0 | V48: =U48*J48 -> 0
F49: =sum(C49:E49) -> 0 | G49: =F49*B49 -> 0 | M49: =sum(I49:L49) -> 0 | N49: =M49*B49 -> 0 | U49: =sum(P49:T49) -> 0 | V49: =U49*J49 -> 0
A50: Fresh Bamboo 500ml | B50: 609 | F50: =sum(C50:E50) -> 0 | G50: =F50*B50 -> 0 | M50: =sum(I50:L50) -> 0 | N50: =M50*B50 -> 0 | U50: =sum(P50:T50) -> 0 | V50: =U50*J50 -> 0
A51: White Tea 500ml | B51: 609 | F51: =sum(C51:E51) -> 0 | G51: =F51*B51 -> 0 | M51: =sum(I51:L51) -> 0 | N51: =M51*B51 -> 0 | U51: =sum(P51:T51) -> 0 | V51: =U51*J51 -> 0
A52: Tropical Paradise 200ml | B52: 329 | F52: =sum(C52:E52) -> 0 | G52: =F52*B52 -> 0 | J52: 2 | M52: =sum(I52:L52) -> 2 | N52: =M52*B52 -> 658 | U52: =sum(P52:T52) -> 0 | V52: =U52*J52 -> 0
A53: RN Wash 50ml | B53: 199 | F53: =sum(C53:E53) -> 0 | G53: =F53*B53 -> 0 | I53: 10 | M53: =sum(I53:L53) -> 10 | N53: =M53*B53 -> 1990 | U53: =sum(P53:T53) -> 0 | V53: =U53*J53 -> 0
A54: CB Wash 50ml | B54: 199 | F54: =sum(C54:E54) -> 0 | G54: =F54*B54 -> 0 | M54: =sum(I54:L54) -> 0 | N54: =M54*B54 -> 0 | U54: =sum(P54:T54) -> 0 | V54: =U54*J54 -> 0
A55: Travel With Me | B55: 599 | F55: =sum(C55:E55) -> 0 | G55: =F55*B55 -> 0 | M55: =sum(I55:L55) -> 0 | N55: =M55*B55 -> 0 | U55: =sum(P55:T55) -> 0 | V55: =U55*J55 -> 0
A56: Handwash: Relaxing Naturals Gallon | B56: 1499 | F56: =sum(C56:E56) -> 0 | G56: =F56*B56 -> 0 | M56: =sum(I56:L56) -> 0 | N56: =M56*B56 -> 0 | T56: 1 | U56: =sum(P56:T56) -> 1 | V56: =U56*J56 -> 0 | Z56: 1
F57: =sum(C57:E57) -> 0 | G57: =F57*B57 -> 0 | M57: =sum(I57:L57) -> 0 | N57: =M57*B57 -> 0 | U57: =sum(P57:T57) -> 0 | V57: =U57*J57 -> 0
A58: Creamy Matcha | B58: 329 | F58: =sum(C58:E58) -> 0 | G58: =F58*B58 -> 0 | J58: 2 | M58: =sum(I58:L58) -> 2 | N58: =M58*B58 -> 658 | U58: =sum(P58:T58) -> 0 | V58: =U58*J58 -> 0
A59: White Lavender | B59: 329 | D59: 1 | F59: =sum(C59:E59) -> 1 | G59: =F59*B59 -> 329 | J59: 2 | M59: =sum(I59:L59) -> 2 | N59: =M59*B59 -> 658 | U59: =sum(P59:T59) -> 0 | V59: =U59*J59 -> 0
A60: Green Tea | B60: 329 | D60: 1 | F60: =sum(C60:E60) -> 1 | G60: =F60*B60 -> 329 | M60: =sum(I60:L60) -> 0 | N60: =M60*B60 -> 0 | U60: =sum(P60:T60) -> 0 | V60: =U60*J60 -> 0
A61: Clean Air 100ml | B61: 249 | F61: =sum(C61:E61) -> 0 | G61: =F61*B61 -> 0 | M61: =sum(I61:L61) -> 0 | N61: =M61*B61 -> 0 | U61: =sum(P61:T61) -> 0 | V61: =U61*J61 -> 0
A62: Creamy Matcha Diffuser Refill | B62: 439 | F62: =sum(C62:E62) -> 0 | G62: =F62*B62 -> 0 | M62: =sum(I62:L62) -> 0 | N62: =M62*B62 -> 0 | T62: 3 | U62: =sum(P62:T62) -> 3 | V62: =U62*J62 -> 0
A63: White Lavender Diffuser Refill | B63: 439 | F63: =sum(C63:E63) -> 0 | G63: =F63*B63 -> 0 | M63: =sum(I63:L63) -> 0 | N63: =M63*B63 -> 0 | U63: =sum(P63:T63) -> 0 | V63: =U63*J63 -> 0
A64: Green Tea Diffuser Refill | B64: 439 | F64: =sum(C64:E64) -> 0 | G64: =F64*B64 -> 0 | M64: =sum(I64:L64) -> 0 | N64: =M64*B64 -> 0 | U64: =sum(P64:T64) -> 0 | V64: =U64*J64 -> 0
A65: Creamy Matcha Diffuser | B65: 799 | F65: =sum(C65:E65) -> 0 | G65: =F65*B65 -> 0 | M65: =sum(I65:L65) -> 0 | N65: =M65*B65 -> 0 | U65: =sum(P65:T65) -> 0 | V65: =U65*J65 -> 0
A66: White Lavender Diffuser | B66: 799 | F66: =sum(C66:E66) -> 0 | G66: =F66*B66 -> 0 | M66: =sum(I66:L66) -> 0 | N66: =M66*B66 -> 0 | U66: =sum(P66:T66) -> 0 | V66: =U66*J66 -> 0 | X66: 1
A67: Green Tea Diffuser | B67: 799 | F67: =sum(C67:E67) -> 0 | G67: =F67*B67 -> 0 | M67: =sum(I67:L67) -> 0 | N67: =M67*B67 -> 0 | U67: =sum(P67:T67) -> 0 | V67: =U67*J67 -> 0
A68: Creamy Matcha + Roomspray | B68: 1299 | F68: =sum(C68:E68) -> 0 | G68: =F68*B68 -> 0 | M68: =sum(I68:L68) -> 0 | N68: =M68*B68 -> 0 | U68: =sum(P68:T68) -> 0 | V68: =U68*J68 -> 0
A69: White Lavender + Roomspray | B69: 1299 | F69: =sum(C69:E69) -> 0 | G69: =F69*B69 -> 0 | M69: =sum(I69:L69) -> 0 | N69: =M69*B69 -> 0 | U69: =sum(P69:T69) -> 0 | V69: =U69*J69 -> 0
A70: Green Tea + Roomspray | B70: 1299 | F70: =sum(C70:E70) -> 0 | G70: =F70*B70 -> 0 | M70: =sum(I70:L70) -> 0 | N70: =M70*B70 -> 0 | U70: =sum(P70:T70) -> 0 | V70: =U70*J70 -> 0
A71: Cotton Clean 500ml | B71: 609 | F71: =sum(C71:E71) -> 0 | G71: =F71*B71 -> 0 | M71: =sum(I71:L71) -> 0 | N71: =M71*B71 -> 0 | U71: =sum(P71:T71) -> 0 | V71: =U71*J71 -> 0
A72: Modern Luxe Reed Diffuser | B72: 1599 | F72: =sum(C72:E72) -> 0 | G72: =F72*B72 -> 0 | M72: =sum(I72:L72) -> 0 | N72: =M72*B72 -> 0 | U72: =sum(P72:T72) -> 0 | V72: =U72*J72 -> 0
A73: Serene Sanctuary Reed Diffuser | B73: 1599 | C73: 1 | F73: =sum(C73:E73) -> 1 | G73: =F73*B73 -> 1599 | M73: =sum(I73:L73) -> 0 | N73: =M73*B73 -> 0 | U73: =sum(P73:T73) -> 0 | V73: =U73*J73 -> 0
A74: Urban Oasis Reed Diffuser | B74: 1599 | F74: =sum(C74:E74) -> 0 | G74: =F74*B74 -> 0 | M74: =sum(I74:L74) -> 0 | N74: =M74*B74 -> 0 | U74: =sum(P74:T74) -> 0 | V74: =U74*J74 -> 0
A75: Clean Air Gallon | E75: 1 | F75: =sum(C75:E75) -> 1 | G75: =F75*B75 -> 0 | I75: 1 | M75: =sum(I75:L75) -> 1 | N75: =M75*B75 -> 0 | U75: =sum(P75:T75) -> 0 | V75: =U75*J75 -> 0 | Z75: 1
F76: =sum(C76:E76) -> 0 | G76: =F76*B76 -> 0 | M76: =sum(I76:L76) -> 0 | N76: =M76*B76 -> 0 | U76: =sum(P76:T76) -> 0 | V76: =U76*J76 -> 0
A77: Holiday Hugs 200ml | B77: 379 | F77: =sum(C77:E77) -> 0 | G77: =F77*B77 -> 0 | M77: =sum(I77:L77) -> 0 | N77: =M77*B77 -> 0 | U77: =sum(P77:T77) -> 0 | V77: =U77*J77 -> 0
A78: Holiday Hugs Diffuser Set | B78: 799 | F78: =sum(C78:E78) -> 0 | G78: =F78*B78 -> 0 | M78: =sum(I78:L78) -> 0 | N78: =M78*B78 -> 0 | U78: =sum(P78:T78) -> 0 | V78: =U78*J78 -> 0
A79: Holiday Hugs Refill | B79: 439 | F79: =sum(C79:E79) -> 0 | G79: =F79*B79 -> 0 | M79: =sum(I79:L79) -> 0 | N79: =M79*B79 -> 0 | U79: =sum(P79:T79) -> 0 | V79: =U79*J79 -> 0
A80: Bathroom Kit | B80: 599 | F80: =sum(C80:E80) -> 0 | G80: =F80*B80 -> 0 | M80: =sum(I80:L80) -> 0 | N80: =M80*B80 -> 0 | U80: =sum(P80:T80) -> 0 | V80: =U80*J80 -> 0
A81: Flushie 50ml | B81: 229 | F81: =sum(C81:E81) -> 0 | G81: =F81*B81 -> 0 | I81: 10 | M81: =sum(I81:L81) -> 10 | N81: =M81*B81 -> 2290 | U81: =sum(P81:T81) -> 0 | V81: =U81*J81 -> 0 | AI81: 2 | AJ81: 3
A82: Easy Drive Grapefuit | B82: 219 | F82: =sum(C82:E82) -> 0 | G82: =F82*B82 -> 0 | I82: 2 | M82: =sum(I82:L82) -> 2 | N82: =M82*B82 -> 438 | U82: =sum(P82:T82) -> 0 | V82: =U82*J82 -> 0
A83: Fresh Bamboo Diffuser + Roomspray | B83: 1299 | F83: =sum(C83:E83) -> 0 | G83: =F83*B83 -> 0 | M83: =sum(I83:L83) -> 0 | N83: =M83*B83 -> 0 | P83: 1 | U83: =sum(P83:T83) -> 1 | V83: =U83*J83 -> 0
A84: White Tea Diffuser + Roomspray | B84: 1299 | F84: =sum(C84:E84) -> 0 | G84: =F84*B84 -> 0 | M84: =sum(I84:L84) -> 0 | N84: =M84*B84 -> 0 | U84: =sum(P84:T84) -> 0 | V84: =U84*J84 -> 0 | AA84: 4
A85: Cotton Clean Diffuser + Roomspray | B85: 1299 | F85: =sum(C85:E85) -> 0 | G85: =F85*B85 -> 0 | M85: =sum(I85:L85) -> 0 | N85: =M85*B85 -> 0 | U85: =sum(P85:T85) -> 0 | V85: =U85*J85 -> 0
A86: Holiday Hugs Diffuser + Roomspray | B86: 1299 | F86: =sum(C86:E86) -> 0 | G86: =F86*B86 -> 0 | M86: =sum(I86:L86) -> 0 | N86: =M86*B86 -> 0 | U86: =sum(P86:T86) -> 0 | V86: =U86*J86 -> 0
F87: =sum(C87:E87) -> 0 | G87: =F87*B87 -> 0 | M87: =sum(I87:L87) -> 0 | N87: =M87*B87 -> 0 | U87: =sum(P87:T87) -> 0 | V87: =U87*J87 -> 0
A88: Sleep All Day | B88: 679 | F88: =sum(C88:E88) -> 0 | G88: =F88*B88 -> 0 | M88: =sum(I88:L88) -> 0 | N88: =M88*B88 -> 0 | U88: =sum(P88:T88) -> 0 | V88: =U88*J88 -> 0
A89: One Way Ticket | B89: 679 | F89: =sum(C89:E89) -> 0 | G89: =F89*B89 -> 0 | M89: =sum(I89:L89) -> 0 | N89: =M89*B89 -> 0 | U89: =sum(P89:T89) -> 0 | V89: =U89*J89 -> 0
A90: Holiday Cheer | B90: 679 | F90: =sum(C90:E90) -> 0 | G90: =F90*B90 -> 0 | M90: =sum(I90:L90) -> 0 | N90: =M90*B90 -> 0 | U90: =sum(P90:T90) -> 0 | V90: =U90*J90 -> 0
F91: =sum(C91:E91) -> 0 | G91: =F91*B91 -> 0 | M91: =sum(I91:L91) -> 0 | N91: =M91*B91 -> 0 | U91: =sum(P91:T91) -> 0 | V91: =U91*J91 -> 0
A92: High Enery Gift Set (Essential Oils) | B92: 490 | F92: =sum(C92:E92) -> 0 | G92: =F92*B92 -> 0 | M92: =sum(I92:L92) -> 0 | N92: =M92*B92 -> 0 | U92: =sum(P92:T92) -> 0 | V92: =U92*J92 -> 0
A93: Romantic Date Gift Set (Essential Oils) | B93: 490 | F93: =sum(C93:E93) -> 0 | G93: =F93*B93 -> 0 | M93: =sum(I93:L93) -> 0 | N93: =M93*B93 -> 0 | U93: =sum(P93:T93) -> 0 | V93: =U93*J93 -> 0
A94: One Way Ticket Gift Set (Fragrance Oils) | B94: 450 | F94: =sum(C94:E94) -> 0 | G94: =F94*B94 -> 0 | M94: =sum(I94:L94) -> 0 | N94: =M94*B94 -> 0 | U94: =sum(P94:T94) -> 0 | V94: =U94*J94 -> 0
A95: Quality Time Gift Set (Fragrance Oils) | B95: 450 | F95: =sum(C95:E95) -> 0 | G95: =F95*B95 -> 0 | M95: =sum(I95:L95) -> 0 | N95: =M95*B95 -> 0 | U95: =sum(P95:T95) -> 0 | V95: =U95*J95 -> 0
F96: =sum(C96:E96) -> 0 | G96: =F96*B96 -> 0 | M96: =sum(I96:L96) -> 0 | N96: =M96*B96 -> 0 | U96: =sum(P96:T96) -> 0 | V96: =U96*J96 -> 0
A97: Fresh Start Kit | B97: 1054 | F97: =sum(C97:E97) -> 0 | G97: =F97*B97 -> 0 | M97: =sum(I97:L97) -> 0 | N97: =M97*B97 -> 0 | U97: =sum(P97:T97) -> 0 | V97: =U97*J97 -> 0
A98: Quite Olive RLS | B98: 329 | S98: 2 | X98: 1 | AD98: 5 | AI98: 2
A99: Quite Olive Refill | B99: 439
A100: Quite Olive Reed Set | B100: 799
A101: Custom Order | K101: 2 | L101: 1 | M101: =sum(I101:L101) -> 3 | N101: =M101*B101 -> 0 | Q101: 9 | U101: =sum(P101:T101) -> 9 | V101: =U101*J101 -> 0 | Y101: 12 | AC101: 1 | AH101: 2 | AK101: 2
...

Sheet TIKTOK
C2: 46024 | J2: 46054 | W2: 46095 | AG2: APRIL
A3: VARIANT | B3: PRICE | C3: Jessa | D3: YanaO. | E3: Bethty | F3: Maurine | J3: Catherine | K3: Ellane | L3: Sandee | M3: James | N3: Zandro | O3: Elma | P3: Major_bank | Q3: Scarlett | R3: Patrice | S3: Luannepenano | W3: Janet | X3: PATIENT FIRST MEDICAL CLINIC AND DIAGNOSTICS CENTER. | Y3: Ana H. | Z3: Gina Vina | AA3: Erlie Ocampo | AB3: Connie | AG3: Urica | AH3: Mirriam | AI3: Analyn | AJ3: Inu | AK3: Damian | AO3: Feliz | AP3: carolnicolevillen
C4: 46024 | D4: 46026 | E4: 46026 | F4: 46048 | J4: 45696 | K4: 45698 | L4: 45698 | M4: 45699 | N4: 45699 | O4: 45701 | P4: 45710 | Q4: 45711 | R4: 45712 | S4: 45715 | W4: 45717 | X4: 45720 | Y4: 45731 | Z4: 45730 | AA4: 45736 | AB4: 46112 | AG4: 45748 | AH4: 45749 | AI4: 45751 | AJ4: 45751 | AK4: 45752
A5: Quiet Elegance | B5: 329
A6: Charming Home | B6: 329
A7: Bright Mornings | B7: 329
A8: Relaxing Naturals | B8: 329 | G8: =SUM(C8:F8) -> 0 | H8: =G8*B8 -> 0 | L8: 1 | N8: 1 | O8: 1 | R8: 1 | T8: =SUM(J8:S8) -> 4 | U8: =T8*B8 -> 1316 | AC8: =SUM(W8:AB8) -> 0 | AD8: =AC8*I8 -> 0 | AI8: 1 | AL8: =SUM(Y8:AK8) -> 1 | AM8: =AL8*Q8 -> 0 | AO8: 1 | AS8: =SUM(AH8:AR8) -> 3 | AT8: =AS8*X8 -> 0
A9: Mountain Breeze | B9: 329 | G9: =SUM(C9:F9) -> 0 | H9: =G9*B9 -> 0 | T9: =SUM(J9:S9) -> 0 | U9: =T9*B9 -> 0 | AC9: =SUM(Q9:AB9) -> 0 | AD9: =AC9*I9 -> 0 | AL9: =SUM(Y9:AK9) -> 0 | AM9: =AL9*Q9 -> 0 | AS9: =SUM(AH9:AR9) -> 0 | AT9: =AS9*X9 -> 0
A10: Fresh Bamboo | B10: 329 | E10: 1 | G10: =SUM(C10:F10) -> 1 | H10: =G10*B10 -> 329 | T10: =SUM(J10:S10) -> 0 | U10: =T10*B10 -> 0 | Z10: 1 | AC10: =SUM(W10:AB10) -> 1 | AD10: =AC10*I10 -> 0 | AH10: 1 | AL10: =SUM(Y10:AK10) -> 3 | AM10: =AL10*Q10 -> 0 | AS10: =SUM(AH10:AR10) -> 4 | AT10: =AS10*X10 -> 0
A11: Beach Escape | B11: 329 | E11: 1 | G11: =SUM(C11:F11) -> 1 | H11: =G11*B11 -> 329 | T11: =SUM(J11:S11) -> 0 | U11: =T11*B11 -> 0 | AC11: =SUM(W11:AB11) -> 0 | AD11: =AC11*I11 -> 0 | AL11: =SUM(Y11:AK11) -> 0 | AM11: =AL11*Q11 -> 0 | AS11: =SUM(AH11:AR11) -> 0 | AT11: =AS11*X11 -> 0
A12: White Tea | B12: 329 | G12: =SUM(C12:F12) -> 0 | H12: =G12*B12 -> 0 | S12: 1 | T12: =SUM(J12:S12) -> 1 | U12: =T12*B12 -> 329 | AC12: =SUM(W12:AB12) -> 0 | AD12: =AC12*I12 -> 0 | AI12: 1 | AL12: =SUM(Y12:AK12) -> 1 | AM12: =AL12*Q12 -> 0 | AS12: =SUM(AH12:AR12) -> 2 | AT12: =AS12*X12 -> 0
A13: Candy Cane | B13: 329 | G13: =SUM(C13:F13) -> 0 | H13: =G13*B13 -> 0 | T13: =SUM(J13:S13) -> 0 | U13: =T13*B13 -> 0 | AC13: =SUM(W13:AB13) -> 0 | AD13: =AC13*I13 -> 0 | AL13: =SUM(Y13:AK13) -> 0 | AM13: =AL13*Q13 -> 0 | AS13: =SUM(AH13:AR13) -> 0 | AT13: =AS13*X13 -> 0
A14: Apple Cinnamon | B14: 329 | F14: 1 | G14: =SUM(C14:F14) -> 1 | H14: =G14*B14 -> 329 | T14: =SUM(J14:S14) -> 0 | U14: =T14*B14 -> 0 | AC14: =SUM(W14:AB14) -> 0 | AD14: =AC14*I14 -> 0 | AL14: =SUM(Y14:AK14) -> 0 | AM14: =AL14*Q14 -> 0 | AS14: =SUM(AH14:AR14) -> 0 | AT14: =AS14*X14 -> 0
A15: Easy Drive | B15: 219 | G15: =SUM(C15:F15) -> 0 | H15: =G15*B15 -> 0 | T15: =SUM(J15:S15) -> 0 | U15: =T15*B15 -> 0 | W15: 1 | AC15: =SUM(W15:AB15) -> 1 | AD15: =AC15*I15 -> 0 | AL15: =SUM(Y15:AK15) -> 1 | AM15: =AL15*Q15 -> 0 | AS15: =SUM(AH15:AR15) -> 1 | AT15: =AS15*X15 -> 0
A16: InLove | G16: =SUM(C16:F16) -> 0 | H16: =G16*B16 -> 0 | T16: =SUM(J16:S16) -> 0 | U16: =T16*B16 -> 0 | AC16: =SUM(W16:AB16) -> 0 | AD16: =AC16*I16 -> 0 | AL16: =SUM(Y16:AK16) -> 0 | AM16: =AL16*Q16 -> 0 | AS16: =SUM(AH16:AR16) -> 0 | AT16: =AS16*X16 -> 0
A17: Bright Mornings HW | G17: =SUM(C17:F17) -> 0 | H17: =G17*B17 -> 0 | T17: =SUM(J17:S17) -> 0 | U17: =T17*B17 -> 0 | AC17: =SUM(W17:AB17) -> 0 | AD17: =AC17*I17 -> 0 | AL17: =SUM(Y17:AK17) -> 0 | AM17: =AL17*Q17 -> 0 | AS17: =SUM(AH17:AR17) -> 0 | AT17: =AS17*X17 -> 0
G18: =SUM(C18:F18) -> 0 | H18: =G18*B18 -> 0 | T18: =SUM(J18:S18) -> 0 | U18: =T18*B18 -> 0 | AC18: =SUM(W18:AB18) -> 0 | AD18: =AC18*I18 -> 0 | AL18: =SUM(Y18:AK18) -> 0 | AM18: =AL18*Q18 -> 0 | AS18: =SUM(AH18:AR18) -> 0 | AT18: =AS18*X18 -> 0
A19: Lavender | B19: 239 | G19: =SUM(C19:F19) -> 0 | H19: =G19*B19 -> 0 | T19: =SUM(J19:S19) -> 0 | U19: =T19*B19 -> 0 | AC19: =SUM(W19:AB19) -> 0 | AD19: =AC19*I19 -> 0 | AL19: =SUM(Y19:AK19) -> 0 | AM19: =AL19*Q19 -> 0 | AS19: =SUM(AH19:AR19) -> 0 | AT19: =AS19*X19 -> 0
A20: Eucalyptus | B20: 239 | G20: =SUM(C20:F20) -> 0 | H20: =G20*B20 -> 0 | T20: =SUM(J20:S20) -> 0 | U20: =T20*B20 -> 0 | AC20: =SUM(W20:AB20) -> 0 | AD20: =AC20*I20 -> 0 | AL20: =SUM(Y20:AK20) -> 0 | AM20: =AL20*Q20 -> 0 | AS20: =SUM(AH20:AR20) -> 0 | AT20: =AS20*X20 -> 0
A21: Peppermint | B21: 239 | G21: =SUM(C21:F21) -> 0 | H21: =G21*B21 -> 0 | T21: =SUM(J21:S21) -> 0 | U21: =T21*B21 -> 0 | AC21: =SUM(W21:AB21) -> 0 | AD21: =AC21*I21 -> 0 | AL21: =SUM(Y21:AK21) -> 0 | AM21: =AL21*Q21 -> 0 | AS21: =SUM(AH21:AR21) -> 0 | AT21: =AS21*X21 -> 0
A22: Fresh Bamboo FO | B22: 219 | G22: =SUM(C22:F22) -> 0 | H22: =G22*B22 -> 0 | T22: =SUM(J22:S22) -> 0 | U22: =T22*B22 -> 0 | AC22: =SUM(W22:AB22) -> 0 | AD22: =AC22*I22 -> 0 | AL22: =SUM(Y22:AK22) -> 0 | AM22: =AL22*Q22 -> 0 | AS22: =SUM(AH22:AR22) -> 0 | AT22: =AS22*X22 -> 0
A23: Beach Escape FO | B23: 219 | G23: =SUM(C23:F23) -> 0 | H23: =G23*B23 -> 0 | T23: =SUM(J23:S23) -> 0 | U23: =T23*B23 -> 0 | AC23: =SUM(W23:AB23) -> 0 | AD23: =AC23*I23 -> 0 | AL23: =SUM(Y23:AK23) -> 0 | AM23: =AL23*Q23 -> 0 | AS23: =SUM(AH23:AR23) -> 0 | AT23: =AS23*X23 -> 0
A24: White Tea FO | B24: 219 | G24: =SUM(C24:F24) -> 0 | H24: =G24*B24 -> 0 | T24: =SUM(J24:S24) -> 0 | U24: =T24*B24 -> 0 | AC24: =SUM(W24:AB24) -> 0 | AD24: =AC24*I24 -> 0 | AL24: =SUM(Y24:AK24) -> 0 | AM24: =AL24*Q24 -> 0 | AS24: =SUM(AH24:AR24) -> 0 | AT24: =AS24*X24 -> 0
A25: Bright Mornings FO | B25: 219 | G25: =SUM(C25:F25) -> 0 | H25: =G25*B25 -> 0 | T25: =SUM(J25:S25) -> 0 | U25: =T25*B25 -> 0 | AC25: =SUM(W25:AB25) -> 0 | AD25: =AC25*I25 -> 0 | AL25: =SUM(Y25:AK25) -> 0 | AM25: =AL25*Q25 -> 0 | AS25: =SUM(AH25:AR25) -> 0 | AT25: =AS25*X25 -> 0
A26: Quiet Elegance FO | B26: 219 | G26: =SUM(C26:F26) -> 0 | H26: =G26*B26 -> 0 | T26: =SUM(J26:S26) -> 0 | U26: =T26*B26 -> 0 | AC26: =SUM(W26:AB26) -> 0 | AD26: =AC26*I26 -> 0 | AL26: =SUM(Y26:AK26) -> 0 | AM26: =AL26*Q26 -> 0 | AS26: =SUM(AH26:AR26) -> 0 | AT26: =AS26*X26 -> 0
A27: Fresh Bamboo Diffuser | B27: 799 | C27: 1 | G27: =SUM(C27:F27) -> 1 | H27: =G27*B27 -> 799 | T27: =SUM(J27:S27) -> 0 | U27: =T27*B27 -> 0 | AC27: =SUM(W27:AB27) -> 0 | AD27: =AC27*I27 -> 0 | AL27: =SUM(Y27:AK27) -> 0 | AM27: =AL27*Q27 -> 0 | AS27: =SUM(AH27:AR27) -> 0 | AT27: =AS27*X27 -> 0
A28: Clean Air | B28: 609 | G28: =SUM(C28:F28) -> 0 | H28: =G28*B28 -> 0 | T28: =SUM(J28:S28) -> 0 | U28: =T28*B28 -> 0 | AC28: =SUM(W28:AB28) -> 0 | AD28: =AC28*I28 -> 0 | AK28: 1 | AL28: =SUM(Y28:AK28) -> 1 | AM28: =AL28*Q28 -> 0 | AP28: 1 | AS28: =SUM(AH28:AR28) -> 3 | AT28: =AS28*X28 -> 0
A29: Cotton Clean | B29: 329 | G29: =SUM(C29:F29) -> 0 | H29: =G29*B29 -> 0 | J29: 1 | O29: 1 | Q29: 2 | T29: =SUM(J29:S29) -> 4 | U29: =T29*B29 -> 1316 | AA29: 1 | AB29: 3 | AC29: =SUM(W29:AB29) -> 4 | AD29: =AC29*I29 -> 0 | AG29: 1 | AL29: =SUM(Y29:AK29) -> 9 | AM29: =AL29*Q29 -> 18 | AS29: =SUM(AH29:AR29) -> 27 | AT29: =AS29*X29 -> 0
A30: Brighter Days | B30: 329 | G30: =SUM(C30:F30) -> 0 | H30: =G30*B30 -> 0 | T30: =SUM(J30:S30) -> 0 | U30: =T30*B30 -> 0 | AC30: =SUM(W30:AB30) -> 0 | AD30: =AC30*I30 -> 0 | AL30: =SUM(Y30:AK30) -> 0 | AM30: =AL30*Q30 -> 0 | AS30: =SUM(AH30:AR30) -> 0 | AT30: =AS30*X30 -> 0
A31: Cotton Clean FO | B31: 219 | G31: =SUM(C31:F31) -> 0 | H31: =G31*B31 -> 0 | T31: =SUM(J31:S31) -> 0 | U31: =T31*B31 -> 0 | AC31: =SUM(W31:AB31) -> 0 | AD31: =AC31*I31 -> 0 | AL31: =SUM(Y31:AK31) -> 0 | AM31: =AL31*Q31 -> 0 | AS31: =SUM(AH31:AR31) -> 0 | AT31: =AS31*X31 -> 0
A32: Brighter Days EO | B32: 219 | G32: =SUM(C32:F32) -> 0 | H32: =G32*B32 -> 0 | T32: =SUM(J32:S32) -> 0 | U32: =T32*B32 -> 0 | AC32: =SUM(W32:AB32) -> 0 | AD32: =AC32*I32 -> 0 | AL32: =SUM(Y32:AK32) -> 0 | AM32: =AL32*Q32 -> 0 | AS32: =SUM(AH32:AR32) -> 0 | AT32: =AS32*X32 -> 0
A33: Fresh Bamboo Refill | B33: 439 | G33: =SUM(C33:F33) -> 0 | H33: =G33*B33 -> 0 | M33: 1 | T33: =SUM(J33:S33) -> 1 | U33: =T33*B33 -> 439 | AC33: =SUM(W33:AB33) -> 0 | AD33: =AC33*I33 -> 0 | AL33: =SUM(Y33:AK33) -> 0 | AM33: =AL33*Q33 -> 0 | AS33: =SUM(AH33:AR33) -> 0 | AT33: =AS33*X33 -> 0
A34: Clean Air Refill 1000ml | B34: 899 | G34: =SUM(C34:F34) -> 0 | H34: =G34*B34 -> 0 | T34: =SUM(J34:S34) -> 0 | U34: =T34*B34 -> 0 | AC34: =SUM(W34:AB34) -> 0 | AD34: =AC34*I34 -> 0 | AL34: =SUM(Y34:AK34) -> 0 | AM34: =AL34*Q34 -> 0 | AS34: =SUM(AH34:AR34) -> 0 | AT34: =AS34*X34 -> 0
A35: Waterbased: Fresh Bamboo | B35: 549 | G35: =SUM(C35:F35) -> 0 | H35: =G35*B35 -> 0 | T35: =SUM(J35:S35) -> 0 | U35: =T35*B35 -> 0 | AC35: =SUM(W35:AB35) -> 0 | AD35: =AC35*I35 -> 0 | AL35: =SUM(Y35:AK35) -> 0 | AM35: =AL35*Q35 -> 0 | AS35: =SUM(AH35:AR35) -> 0 | AT35: =AS35*X35 -> 0
A36: Waterbased: Cotton Clean | B36: 549 | G36: =SUM(C36:F36) -> 0 | H36: =G36*B36 -> 0 | T36: =SUM(J36:S36) -> 0 | U36: =T36*B36 -> 0 | AC36: =SUM(W36:AB36) -> 0 | AD36: =AC36*I36 -> 0 | AL36: =SUM(Y36:AK36) -> 0 | AM36: =AL36*Q36 -> 0 | AS36: =SUM(AH36:AR36) -> 0 | AT36: =AS36*X36 -> 0
A37: Waterbased: White Tea | B37: 549 | G37: =SUM(C37:F37) -> 0 | H37: =G37*B37 -> 0 | T37: =SUM(J37:S37) -> 0 | U37: =T37*B37 -> 0 | X37: 1 | AC37: =SUM(W37:AB37) -> 1 | AD37: =AC37*I37 -> 0 | AL37: =SUM(Y37:AK37) -> 1 | AM37: =AL37*Q37 -> 0 | AS37: =SUM(AH37:AR37) -> 1 | AT37: =AS37*X37 -> 1
A38: White Tea Diffuser | B38: 799 | G38: =SUM(C38:F38) -> 0 | H38: =G38*B38 -> 0 | T38: =SUM(J38:S38) -> 0 | U38: =T38*B38 -> 0 | AC38: =SUM(W38:AB38) -> 0 | AD38: =AC38*I38 -> 0 | AL38: =SUM(Y38:AK38) -> 0 | AM38: =AL38*Q38 -> 0 | AS38: =SUM(AH38:AR38) -> 0 | AT38: =AS38*X38 -> 0
A39: Cotton Clean Diffuser | B39: 799 | G39: =SUM(C39:F39) -> 0 | H39: =G39*B39 -> 0 | T39: =SUM(J39:S39) -> 0 | U39: =T39*B39 -> 0 | AC39: =SUM(W39:AB39) -> 0 | AD39: =AC39*I39 -> 0 | AL39: =SUM(Y39:AK39) -> 0 | AM39: =AL39*Q39 -> 0 | AS39: =SUM(AH39:AR39) -> 0 | AT39: =AS39*X39 -> 0
A40: White Tea Diffuser Refill | B40: 439 | G40: =SUM(C40:F40) -> 0 | H40: =G40*B40 -> 0 | T40: =SUM(J40:S40) -> 0 | U40: =T40*B40 -> 0 | AC40: =SUM(W40:AB40) -> 0 | AD40: =AC40*I40 -> 0 | AL40: =SUM(Y40:AK40) -> 0 | AM40: =AL40*Q40 -> 0 | AS40: =SUM(AH40:AR40) -> 0 | AT40: =AS40*X40 -> 0
A41: Cotton Clean Diffuser Refill | B41: 439 | G41: =SUM(C41:F41) -> 0 | H41: =G41*B41 -> 0 | T41: =SUM(J41:S41) -> 0 | U41: =T41*B41 -> 0 | AC41: =SUM(W41:AB41) -> 0 | AD41: =AC41*I41 -> 0 | AL41: =SUM(Y41:AK41) -> 0 | AM41: =AL41*Q41 -> 0 | AS41: =SUM(AH41:AR41) -> 0 | AT41: =AS41*X41 -> 0
A42: Reed Sticks | B42: 60 | G42: =SUM(C42:F42) -> 0 | H42: =G42*B42 -> 0 | T42: =SUM(J42:S42) -> 0 | U42: =T42*B42 -> 0 | AC42: =SUM(W42:AB42) -> 0 | AD42: =AC42*I42 -> 0 | AL42: =SUM(Y42:AK42) -> 0 | AM42: =AL42*Q42 -> 0 | AS42: =SUM(AH42:AR42) -> 0 | AT42: =AS42*X42 -> 0
A43: Relaxing Naturals 500ml | B43: 609 | G43: =SUM(C43:F43) -> 0 | H43: =G43*B43 -> 0 | T43: =SUM(J43:S43) -> 0 | U43: =T43*B43 -> 0 | AC43: =SUM(W43:AB43) -> 0 | AD43: =AC43*I43 -> 0 | AL43: =SUM(Y43:AK43) -> 0 | AM43: =AL43*Q43 -> 0 | AS43: =SUM(AH43:AR43) -> 0 | AT43: =AS43*X43 -> 0
A44: Hand Wash Relaxing Naturals 500ml | B44: 379 | G44: =SUM(C44:F44) -> 0 | H44: =G44*B44 -> 0 | T44: =SUM(J44:S44) -> 0 | U44: =T44*B44 -> 0 | AC44: =SUM(W44:AB44) -> 0 | AD44: =AC44*I44 -> 0 | AL44: =SUM(Y44:AK44) -> 0 | AM44: =AL44*Q44 -> 0 | AS44: =SUM(AH44:AR44) -> 0 | AT44: =AS44*X44 -> 0
A45: Hand Wash Clean & Bright 500ml | B45: 379 | G45: =SUM(C45:F45) -> 0 | H45: =G45*B45 -> 0 | T45: =SUM(J45:S45) -> 0 | U45: =T45*B45 -> 0 | AC45: =SUM(W45:AB45) -> 0 | AD45: =AC45*I45 -> 0 | AL45: =SUM(Y45:AK45) -> 0 | AM45: =AL45*Q45 -> 0 | AS45: =SUM(AH45:AR45) -> 0 | AT45: =AS45*X45 -> 0
A46: Keep it Clean Gift Set | B46: 1299 | G46: =SUM(C46:F46) -> 0 | H46: =G46*B46 -> 0 | T46: =SUM(J46:S46) -> 0 | U46: =T46*B46 -> 0 | AC46: =SUM(W46:AB46) -> 0 | AD46: =AC46*I46 -> 0 | AL46: =SUM(Y46:AK46) -> 0 | AM46: =AL46*Q46 -> 0 | AS46: =SUM(AH46:AR46) -> 0 | AT46: =AS46*X46 -> 0
A47: Relax With Me | B47: 1299 | G47: =SUM(C47:F47) -> 0 | H47: =G47*B47 -> 0 | T47: =SUM(J47:S47) -> 0 | U47: =T47*B47 -> 0 | AC47: =SUM(W47:AB47) -> 0 | AD47: =AC47*I47 -> 0 | AL47: =SUM(Y47:AK47) -> 0 | AM47: =AL47*Q47 -> 0 | AS47: =SUM(AH47:AR47) -> 0 | AT47: =AS47*X47 -> 0
A48: Simoy ng Pahiyas | B48: 0 | G48: =SUM(C48:F48) -> 0 | H48: =G48*B48 -> 0 | T48: =SUM(J48:S48) -> 0 | U48: =T48*B48 -> 0 | AC48: =SUM(W48:AB48) -> 0 | AD48: =AC48*I48 -> 0 | AL48: =SUM(Y48:AK48) -> 0 | AM48: =AL48*Q48 -> 0 | AS48: =SUM(AH48:AR48) -> 0 | AT48: =AS48*X48 -> 0
G49: =SUM(C49:F49) -> 0 | H49: =G49*B49 -> 0 | T49: =SUM(J49:S49) -> 0 | U49: =T49*B49 -> 0 | AC49: =SUM(W49:AB49) -> 0 | AD49: =AC49*I49 -> 0 | AL49: =SUM(Y49:AK49) -> 0 | AM49: =AL49*Q49 -> 0 | AS49: =SUM(AH49:AR49) -> 0 | AT49: =AS49*X49 -> 0
A50: Fresh Bamboo 500ml | B50: 609 | G50: =SUM(C50:F50) -> 0 | H50: =G50*B50 -> 0 | T50: =SUM(J50:S50) -> 0 | U50: =T50*B50 -> 0 | AC50: =SUM(W50:AB50) -> 0 | AD50: =AC50*I50 -> 0 | AL50: =SUM(Y50:AK50) -> 0 | AM50: =AL50*Q50 -> 0 | AS50: =SUM(AH50:AR50) -> 0 | AT50: =AS50*X50 -> 0
A51: White Tea 500ml | B51: 609 | G51: =SUM(C51:F51) -> 0 | H51: =G51*B51 -> 0 | T51: =SUM(J51:S51) -> 0 | U51: =T51*B51 -> 0 | AC51: =SUM(W51:AB51) -> 0 | AD51: =AC51*I51 -> 0 | AL51: =SUM(Y51:AK51) -> 0 | AM51: =AL51*Q51 -> 0 | AS51: =SUM(AH51:AR51) -> 0 | AT51: =AS51*X51 -> 0
A52: Tropical Paradise 200ml | B52: 329 | G52: =SUM(C52:F52) -> 0 | H52: =G52*B52 -> 0 | T52: =SUM(J52:S52) -> 0 | U52: =T52*B52 -> 0 | AC52: =SUM(W52:AB52) -> 0 | AD52: =AC52*I52 -> 0 | AL52: =SUM(Y52:AK52) -> 0 | AM52: =AL52*Q52 -> 0 | AS52: =SUM(AH52:AR52) -> 0 | AT52: =AS52*X52 -> 0
A53: RN Wash 50ml | B53: 199 | G53: =SUM(C53:F53) -> 0 | H53: =G53*B53 -> 0 | T53: =SUM(J53:S53) -> 0 | U53: =T53*B53 -> 0 | AC53: =SUM(W53:AB53) -> 0 | AD53: =AC53*I53 -> 0 | AL53: =SUM(Y53:AK53) -> 0 | AM53: =AL53*Q53 -> 0 | AS53: =SUM(AH53:AR53) -> 0 | AT53: =AS53*X53 -> 0
A54: CB Wash 50ml | B54: 199 | G54: =SUM(C54:F54) -> 0 | H54: =G54*B54 -> 0 | T54: =SUM(J54:S54) -> 0 | U54: =T54*B54 -> 0 | AC54: =SUM(W54:AB54) -> 0 | AD54: =AC54*I54 -> 0 | AL54: =SUM(Y54:AK54) -> 0 | AM54: =AL54*Q54 -> 0 | AS54: =SUM(AH54:AR54) -> 0 | AT54: =AS54*X54 -> 0
A55: Travel With Me | B55: 599 | G55: =SUM(C55:F55) -> 0 | H55: =G55*B55 -> 0 | T55: =SUM(J55:S55) -> 0 | U55: =T55*B55 -> 0 | AC55: =SUM(W55:AB55) -> 0 | AD55: =AC55*I55 -> 0 | AL55: =SUM(Y55:AK55) -> 0 | AM55: =AL55*Q55 -> 0 | AS55: =SUM(AH55:AR55) -> 0 | AT55: =AS55*X55 -> 0
A56: Handwash: Relaxing Naturals Gallon | B56: 1499 | G56: =SUM(C56:F56) -> 0 | H56: =G56*B56 -> 0 | T56: =SUM(J56:S56) -> 0 | U56: =T56*B56 -> 0 | AC56: =SUM(W56:AB56) -> 0 | AD56: =AC56*I56 -> 0 | AL56: =SUM(Y56:AK56) -> 0 | AM56: =AL56*Q56 -> 0 | AS56: =SUM(AH56:AR56) -> 0 | AT56: =AS56*X56 -> 0
G57: =SUM(C57:F57) -> 0 | H57: =G57*B57 -> 0 | T57: =SUM(J57:S57) -> 0 | U57: =T57*B57 -> 0 | AC57: =SUM(W57:AB57) -> 0 | AD57: =AC57*I57 -> 0 | AL57: =SUM(Y57:AK57) -> 0 | AM57: =AL57*Q57 -> 0 | AS57: =SUM(AH57:AR57) -> 0 | AT57: =AS57*X57 -> 0
A58: Creamy Matcha | B58: 329 | G58: =SUM(C58:F58) -> 0 | H58: =G58*B58 -> 0 | T58: =SUM(J58:S58) -> 0 | U58: =T58*B58 -> 0 | AC58: =SUM(W58:AB58) -> 0 | AD58: =AC58*I58 -> 0 | AL58: =SUM(Y58:AK58) -> 0 | AM58: =AL58*Q58 -> 0 | AS58: =SUM(AH58:AR58) -> 0 | AT58: =AS58*X58 -> 0
A59: White Lavender | B59: 329 | G59: =SUM(C59:F59) -> 0 | H59: =G59*B59 -> 0 | P59: 1 | T59: =SUM(J59:S59) -> 1 | U59: =T59*B59 -> 329 | AC59: =SUM(W59:AB59) -> 0 | AD59: =AC59*I59 -> 0 | AL59: =SUM(Y59:AK59) -> 0 | AM59: =AL59*Q59 -> 0 | AS59: =SUM(AH59:AR59) -> 0 | AT59: =AS59*X59 -> 0
A60: Green Tea | B60: 329 | G60: =SUM(C60:F60) -> 0 | H60: =G60*B60 -> 0 | T60: =SUM(J60:S60) -> 0 | U60: =T60*B60 -> 0 | AC60: =SUM(W60:AB60) -> 0 | AD60: =AC60*I60 -> 0 | AJ60: 1 | AL60: =SUM(Y60:AK60) -> 1 | AM60: =AL60*Q60 -> 0 | AS60: =SUM(AH60:AR60) -> 2 | AT60: =AS60*X60 -> 0
A61: Clean Air 100ml | B61: 249 | D61: 1 | G61: =SUM(C61:F61) -> 1 | H61: =G61*B61 -> 249 | T61: =SUM(J61:S61) -> 0 | U61: =T61*B61 -> 0 | AC61: =SUM(W61:AB61) -> 0 | AD61: =AC61*I61 -> 0 | AL61: =SUM(Y61:AK61) -> 0 | AM61: =AL61*Q61 -> 0 | AS61: =SUM(AH61:AR61) -> 0 | AT61: =AS61*X61 -> 0
A62: Creamy Matcha Diffuser Refill | B62: 439 | G62: =SUM(C62:F62) -> 0 | H62: =G62*B62 -> 0 | T62: =SUM(J62:S62) -> 0 | U62: =T62*B62 -> 0 | AC62: =SUM(W62:AB62) -> 0 | AD62: =AC62*I62 -> 0 | AL62: =SUM(Y62:AK62) -> 0 | AM62: =AL62*Q62 -> 0 | AS62: =SUM(AH62:AR62) -> 0 | AT62: =AS62*X62 -> 0
A63: White Lavender Diffuser Refill | B63: 439 | G63: =SUM(C63:F63) -> 0 | H63: =G63*B63 -> 0 | T63: =SUM(J63:S63) -> 0 | U63: =T63*B63 -> 0 | AC63: =SUM(W63:AB63) -> 0 | AD63: =AC63*I63 -> 0 | AL63: =SUM(Y63:AK63) -> 0 | AM63: =AL63*Q63 -> 0 | AS63: =SUM(AH63:AR63) -> 0 | AT63: =AS63*X63 -> 0
A64: Green Tea Diffuser Refill | B64: 439 | G64: =SUM(C64:F64) -> 0 | H64: =G64*B64 -> 0 | K64: 1 | T64: =SUM(J64:S64) -> 1 | U64: =T64*B64 -> 439 | AC64: =SUM(W64:AB64) -> 0 | AD64: =AC64*I64 -> 0 | AL64: =SUM(Y64:AK64) -> 0 | AM64: =AL64*Q64 -> 0 | AS64: =SUM(AH64:AR64) -> 0 | AT64: =AS64*X64 -> 0
A65: Creamy Matcha Diffuser | B65: 799 | G65: =SUM(C65:F65) -> 0 | H65: =G65*B65 -> 0 | T65: =SUM(J65:S65) -> 0 | U65: =T65*B65 -> 0 | AC65: =SUM(W65:AB65) -> 0 | AD65: =AC65*I65 -> 0 | AL65: =SUM(Y65:AK65) -> 0 | AM65: =AL65*Q65 -> 0 | AS65: =SUM(AH65:AR65) -> 0 | AT65: =AS65*X65 -> 0
A66: White Lavender Diffuser | B66: 799 | G66: =SUM(C66:F66) -> 0 | H66: =G66*B66 -> 0 | T66: =SUM(J66:S66) -> 0 | U66: =T66*B66 -> 0 | AC66: =SUM(W66:AB66) -> 0 | AD66: =AC66*I66 -> 0 | AL66: =SUM(Y66:AK66) -> 0 | AM66: =AL66*Q66 -> 0 | AS66: =SUM(AH66:AR66) -> 0 | AT66: =AS66*X66 -> 0
A67: Green Tea Diffuser | B67: 799 | G67: =SUM(C67:F67) -> 0 | H67: =G67*B67 -> 0 | T67: =SUM(J67:S67) -> 0 | U67: =T67*B67 -> 0 | AC67: =SUM(W67:AB67) -> 0 | AD67: =AC67*I67 -> 0 | AL67: =SUM(Y67:AK67) -> 0 | AM67: =AL67*Q67 -> 0 | AS67: =SUM(AH67:AR67) -> 0 | AT67: =AS67*X67 -> 0
A68: Creamy Matcha + Roomspray | B68: 1299 | G68: =SUM(C68:F68) -> 0 | H68: =G68*B68 -> 0 | T68: =SUM(J68:S68) -> 0 | U68: =T68*B68 -> 0 | AC68: =SUM(W68:AB68) -> 0 | AD68: =AC68*I68 -> 0 | AL68: =SUM(Y68:AK68) -> 0 | AM68: =AL68*Q68 -> 0 | AS68: =SUM(AH68:AR68) -> 0 | AT68: =AS68*X68 -> 0
A69: White Lavender + Roomspray | B69: 1299 | G69: =SUM(C69:F69) -> 0 | H69: =G69*B69 -> 0 | T69: =SUM(J69:S69) -> 0 | U69: =T69*B69 -> 0 | AC69: =SUM(W69:AB69) -> 0 | AD69: =AC69*I69 -> 0 | AL69: =SUM(Y69:AK69) -> 0 | AM69: =AL69*Q69 -> 0 | AS69: =SUM(AH69:AR69) -> 0 | AT69: =AS69*X69 -> 0
A70: Green Tea + Roomspray | B70: 1299 | G70: =SUM(C70:F70) -> 0 | H70: =G70*B70 -> 0 | T70: =SUM(J70:S70) -> 0 | U70: =T70*B70 -> 0 | AC70: =SUM(W70:AB70) -> 0 | AD70: =AC70*I70 -> 0 | AL70: =SUM(Y70:AK70) -> 0 | AM70: =AL70*Q70 -> 0 | AS70: =SUM(AH70:AR70) -> 0 | AT70: =AS70*X70 -> 0
A71: Cotton Clean 500ml | B71: 609 | G71: =SUM(C71:F71) -> 0 | H71: =G71*B71 -> 0 | T71: =SUM(J71:S71) -> 0 | U71: =T71*B71 -> 0 | AC71: =SUM(W71:AB71) -> 0 | AD71: =AC71*I71 -> 0 | AL71: =SUM(Y71:AK71) -> 0 | AM71: =AL71*Q71 -> 0 | AS71: =SUM(AH71:AR71) -> 0 | AT71: =AS71*X71 -> 0
A72: Modern Luxe Reed Diffuser | B72: 1599 | G72: =SUM(C72:F72) -> 0 | H72: =G72*B72 -> 0 | T72: =SUM(J72:S72) -> 0 | U72: =T72*B72 -> 0 | AC72: =SUM(W72:AB72) -> 0 | AD72: =AC72*I72 -> 0 | AL72: =SUM(Y72:AK72) -> 0 | AM72: =AL72*Q72 -> 0 | AS72: =SUM(AH72:AR72) -> 0 | AT72: =AS72*X72 -> 0
A73: Serene Sanctuary Reed Diffuser | B73: 1599 | G73: =SUM(C73:F73) -> 0 | H73: =G73*B73 -> 0 | T73: =SUM(J73:S73) -> 0 | U73: =T73*B73 -> 0 | AC73: =SUM(W73:AB73) -> 0 | AD73: =AC73*I73 -> 0 | AL73: =SUM(Y73:AK73) -> 0 | AM73: =AL73*Q73 -> 0 | AS73: =SUM(AH73:AR73) -> 0 | AT73: =AS73*X73 -> 0
A74: Urban Oasis Reed Diffuser | B74: 1599 | G74: =SUM(C74:F74) -> 0 | H74: =G74*B74 -> 0 | T74: =SUM(J74:S74) -> 0 | U74: =T74*B74 -> 0 | AC74: =SUM(W74:AB74) -> 0 | AD74: =AC74*I74 -> 0 | AL74: =SUM(Y74:AK74) -> 0 | AM74: =AL74*Q74 -> 0 | AS74: =SUM(AH74:AR74) -> 0 | AT74: =AS74*X74 -> 0
A75: Clean Air Gallon | G75: =SUM(C75:F75) -> 0 | H75: =G75*B75 -> 0 | T75: =SUM(J75:S75) -> 0 | U75: =T75*B75 -> 0 | AC75: =SUM(W75:AB75) -> 0 | AD75: =AC75*I75 -> 0 | AL75: =SUM(Y75:AK75) -> 0 | AM75: =AL75*Q75 -> 0 | AS75: =SUM(AH75:AR75) -> 0 | AT75: =AS75*X75 -> 0
G76: =SUM(C76:F76) -> 0 | H76: =G76*B76 -> 0 | T76: =SUM(J76:S76) -> 0 | U76: =T76*B76 -> 0 | AC76: =SUM(W76:AB76) -> 0 | AD76: =AC76*I76 -> 0 | AL76: =SUM(Y76:AK76) -> 0 | AM76: =AL76*Q76 -> 0 | AS76: =SUM(AH76:AR76) -> 0 | AT76: =AS76*X76 -> 0
A77: Holiday Hugs 200ml | B77: 379 | F77: 1 | G77: =SUM(C77:F77) -> 1 | H77: =G77*B77 -> 379 | T77: =SUM(J77:S77) -> 0 | U77: =T77*B77 -> 0 | AC77: =SUM(W77:AB77) -> 0 | AD77: =AC77*I77 -> 0 | AL77: =SUM(Y77:AK77) -> 0 | AM77: =AL77*Q77 -> 0 | AS77: =SUM(AH77:AR77) -> 0 | AT77: =AS77*X77 -> 0
A78: Holiday Hugs Diffuser Set | B78: 799 | G78: =SUM(C78:F78) -> 0 | H78: =G78*B78 -> 0 | T78: =SUM(J78:S78) -> 0 | U78: =T78*B78 -> 0 | AC78: =SUM(W78:AB78) -> 0 | AD78: =AC78*I78 -> 0 | AL78: =SUM(Y78:AK78) -> 0 | AM78: =AL78*Q78 -> 0 | AS78: =SUM(AH78:AR78) -> 0 | AT78: =AS78*X78 -> 0
A79: Holiday Hugs Refill | B79: 439 | G79: =SUM(C79:F79) -> 0 | H79: =G79*B79 -> 0 | T79: =SUM(J79:S79) -> 0 | U79: =T79*B79 -> 0 | AC79: =SUM(W79:AB79) -> 0 | AD79: =AC79*I79 -> 0 | AL79: =SUM(Y79:AK79) -> 0 | AM79: =AL79*Q79 -> 0 | AS79: =SUM(AH79:AR79) -> 0 | AT79: =AS79*X79 -> 0
A80: Bathroom Kit | B80: 599 | G80: =SUM(C80:F80) -> 0 | H80: =G80*B80 -> 0 | T80: =SUM(J80:S80) -> 0 | U80: =T80*B80 -> 0 | Y80: 1 | AC80: =SUM(W80:AB80) -> 1 | AD80: =AC80*I80 -> 0 | AL80: =SUM(Y80:AK80) -> 2 | AM80: =AL80*Q80 -> 0 | AS80: =SUM(AH80:AR80) -> 2 | AT80: =AS80*X80 -> 0
A81: Flushie 50ml | B81: 229 | G81: =SUM(C81:F81) -> 0 | H81: =G81*B81 -> 0 | T81: =SUM(J81:S81) -> 0 | U81: =T81*B81 -> 0 | AC81: =SUM(W81:AB81) -> 0 | AD81: =AC81*I81 -> 0 | AL81: =SUM(Y81:AK81) -> 0 | AM81: =AL81*Q81 -> 0 | AS81: =SUM(AH81:AR81) -> 0 | AT81: =AS81*X81 -> 0
A82: Easy Drive Grapefuit | B82: 219 | G82: =SUM(C82:F82) -> 0 | H82: =G82*B82 -> 0 | T82: =SUM(J82:S82) -> 0 | U82: =T82*B82 -> 0 | AC82: =SUM(W82:AB82) -> 0 | AD82: =AC82*I82 -> 0 | AL82: =SUM(Y82:AK82) -> 0 | AM82: =AL82*Q82 -> 0 | AS82: =SUM(AH82:AR82) -> 0 | AT82: =AS82*X82 -> 0
A83: Fresh Bamboo Diffuser + Roomspray | B83: 1299 | G83: =SUM(C83:F83) -> 0 | H83: =G83*B83 -> 0 | T83: =SUM(J83:S83) -> 0 | U83: =T83*B83 -> 0 | AC83: =SUM(W83:AB83) -> 0 | AD83: =AC83*I83 -> 0 | AL83: =SUM(Y83:AK83) -> 0 | AM83: =AL83*Q83 -> 0 | AS83: =SUM(AH83:AR83) -> 0 | AT83: =AS83*X83 -> 0
A84: White Tea Diffuser + Roomspray | B84: 1299 | G84: =SUM(C84:F84) -> 0 | H84: =G84*B84 -> 0 | T84: =SUM(J84:S84) -> 0 | U84: =T84*B84 -> 0 | AC84: =SUM(W84:AB84) -> 0 | AD84: =AC84*I84 -> 0 | AL84: =SUM(Y84:AK84) -> 0 | AM84: =AL84*Q84 -> 0 | AS84: =SUM(AH84:AR84) -> 0 | AT84: =AS84*X84 -> 0
A85: Cotton Clean Diffuser + Roomspray | B85: 1299 | G85: =SUM(C85:F85) -> 0 | H85: =G85*B85 -> 0 | T85: =SUM(J85:S85) -> 0 | U85: =T85*B85 -> 0 | AC85: =SUM(W85:AB85) -> 0 | AD85: =AC85*I85 -> 0 | AL85: =SUM(Y85:AK85) -> 0 | AM85: =AL85*Q85 -> 0 | AS85: =SUM(AH85:AR85) -> 0 | AT85: =AS85*X85 -> 0
A86: Holiday Hugs Diffuser + Roomspray | B86: 1299 | G86: =SUM(C86:F86) -> 0 | H86: =G86*B86 -> 0 | T86: =SUM(J86:S86) -> 0 | U86: =T86*B86 -> 0 | AC86: =SUM(W86:AB86) -> 0 | AD86: =AC86*I86 -> 0 | AL86: =SUM(Y86:AK86) -> 0 | AM86: =AL86*Q86 -> 0 | AS86: =SUM(AH86:AR86) -> 0 | AT86: =AS86*X86 -> 0
G87: =SUM(C87:F87) -> 0 | H87: =G87*B87 -> 0 | T87: =SUM(J87:S87) -> 0 | U87: =T87*B87 -> 0 | AC87: =SUM(W87:AB87) -> 0 | AD87: =AC87*I87 -> 0 | AL87: =SUM(Y87:AK87) -> 0 | AM87: =AL87*Q87 -> 0 | AS87: =SUM(AH87:AR87) -> 0 | AT87: =AS87*X87 -> 0
A88: Sleep All Day | B88: 679 | G88: =SUM(C88:F88) -> 0 | H88: =G88*B88 -> 0 | T88: =SUM(J88:S88) -> 0 | U88: =T88*B88 -> 0 | AC88: =SUM(W88:AB88) -> 0 | AD88: =AC88*I88 -> 0 | AL88: =SUM(Y88:AK88) -> 0 | AM88: =AL88*Q88 -> 0 | AS88: =SUM(AH88:AR88) -> 0 | AT88: =AS88*X88 -> 0
A89: One Way Ticket | B89: 679 | G89: =SUM(C89:F89) -> 0 | H89: =G89*B89 -> 0 | T89: =SUM(J89:S89) -> 0 | U89: =T89*B89 -> 0 | AC89: =SUM(W89:AB89) -> 0 | AD89: =AC89*I89 -> 0 | AL89: =SUM(Y89:AK89) -> 0 | AM89: =AL89*Q89 -> 0 | AS89: =SUM(AH89:AR89) -> 0 | AT89: =AS89*X89 -> 0
A90: Holiday Cheer | B90: 679 | G90: =SUM(C90:F90) -> 0 | H90: =G90*B90 -> 0 | T90: =SUM(J90:S90) -> 0 | U90: =T90*B90 -> 0 | AC90: =SUM(W90:AB90) -> 0 | AD90: =AC90*I90 -> 0 | AL90: =SUM(Y90:AK90) -> 0 | AM90: =AL90*Q90 -> 0 | AS90: =SUM(AH90:AR90) -> 0 | AT90: =AS90*X90 -> 0
G91: =SUM(C91:F91) -> 0 | H91: =G91*B91 -> 0 | T91: =SUM(J91:S91) -> 0 | U91: =T91*B91 -> 0 | AC91: =SUM(W91:AB91) -> 0 | AD91: =AC91*I91 -> 0 | AL91: =SUM(Y91:AK91) -> 0 | AM91: =AL91*Q91 -> 0 | AS91: =SUM(AH91:AR91) -> 0 | AT91: =AS91*X91 -> 0
A92: High Enery Gift Set (Essential Oils) | B92: 490 | G92: =SUM(C92:F92) -> 0 | H92: =G92*B92 -> 0 | T92: =SUM(J92:S92) -> 0 | U92: =T92*B92 -> 0 | AC92: =SUM(W92:AB92) -> 0 | AD92: =AC92*I92 -> 0 | AL92: =SUM(Y92:AK92) -> 0 | AM92: =AL92*Q92 -> 0 | AS92: =SUM(AH92:AR92) -> 0 | AT92: =AS92*X92 -> 0
A93: Romantic Date Gift Set (Essential Oils) | B93: 490 | G93: =SUM(C93:F93) -> 0 | H93: =G93*B93 -> 0 | T93: =SUM(J93:S93) -> 0 | U93: =T93*B93 -> 0 | AC93: =SUM(W93:AB93) -> 0 | AD93: =AC93*I93 -> 0 | AL93: =SUM(Y93:AK93) -> 0 | AM93: =AL93*Q93 -> 0 | AS93: =SUM(AH93:AR93) -> 0 | AT93: =AS93*X93 -> 0
A94: One Way Ticket Gift Set (Fragrance Oils) | B94: 450 | G94: =SUM(C94:F94) -> 0 | H94: =G94*B94 -> 0 | T94: =SUM(J94:S94) -> 0 | U94: =T94*B94 -> 0 | AC94: =SUM(W94:AB94) -> 0 | AD94: =AC94*I94 -> 0 | AL94: =SUM(Y94:AK94) -> 0 | AM94: =AL94*Q94 -> 0 | AS94: =SUM(AH94:AR94) -> 0 | AT94: =AS94*X94 -> 0
A95: Quality Time Gift Set (Fragrance Oils) | B95: 450 | G95: =SUM(C95:F95) -> 0 | H95: =G95*B95 -> 0 | T95: =SUM(J95:S95) -> 0 | U95: =T95*B95 -> 0 | AC95: =SUM(W95:AB95) -> 0 | AD95: =AC95*I95 -> 0 | AL95: =SUM(Y95:AK95) -> 0 | AM95: =AL95*Q95 -> 0 | AS95: =SUM(AH95:AR95) -> 0 | AT95: =AS95*X95 -> 0
G96: =SUM(C96:F96) -> 0 | H96: =G96*B96 -> 0 | T96: =SUM(J96:S96) -> 0 | U96: =T96*B96 -> 0 | AC96: =SUM(W96:AB96) -> 0 | AD96: =AC96*I96 -> 0 | AL96: =SUM(Y96:AK96) -> 0 | AM96: =AL96*Q96 -> 0 | AS96: =SUM(AH96:AR96) -> 0 | AT96: =AS96*X96 -> 0
A97: Fresh Start Kit | B97: 1054 | G97: =SUM(C97:F97) -> 0 | H97: =G97*B97 -> 0 | T97: =SUM(J97:S97) -> 0 | U97: =T97*B97 -> 0 | AC97: =SUM(W97:AB97) -> 0 | AD97: =AC97*I97 -> 0 | AL97: =SUM(Y97:AK97) -> 0 | AM97: =AL97*Q97 -> 0 | AS97: =SUM(AH97:AR97) -> 0 | AT97: =AS97*X97 -> 0
A98: Custom Order
C99: =SUM(C8:C14)*329+SUM(C15)*219+SUM(C19:C21)*239+SUM(C22:C24)*219+SUM(C27)*799+SUM(C28)*609+SUM(C29:C30)*329+SUM(C31:C32)*219+SUM(C33)*439+SUM(C34)*899+SUM(C35:C37)*549+SUM(C38:C39)*799+SUM(C40:C41)*439+SUM(C42)*60+SUM(C43)*609+SUM(C44:C45)*379+SUM(C46:C47)*1299+SUM(C50:C51)*609+SUM(C52)*329+SUM(C55)*599+SUM(C58:C60)*329+SUM(C61)*249+SUM(C62:C64)*439+SUM(C65:C67)*799+SUM(C68:C70)*1299+SUM(C71)*609+SUM(C72:C74)*1599+SUM(C75)*3059+SUM(C77)*379+SUM(C78)*799+SUM(C79)*439+SUM(C80)*599+SUM(C81)*229+SUM(C82)*219+SUM(C83:C86)*1299+SUM(C88:C90)*679+SUM(C92:C93)*490+SUM(C94:C95)*450+SUM(C97)*1054 -> 799 | D99: =SUM(D8:D14)*329+SUM(D15)*219+SUM(D19:D21)*239+SUM(D22:D24)*219+SUM(D27)*799+SUM(D28)*609+SUM(D29:D30)*329+SUM(D31:D32)*219+SUM(D33)*439+SUM(D34)*899+SUM(D35:D37)*549+SUM(D38:D39)*799+SUM(D40:D41)*439+SUM(D42)*60+SUM(D43)*609+SUM(D44:D45)*379+SUM(D46:D47)*1299+SUM(D50:D51)*609+SUM(D52)*329+SUM(D55)*599+SUM(D58:D60)*329+SUM(D61)*249+SUM(D62:D64)*439+SUM(D65:D67)*799+SUM(D68:D70)*1299+SUM(D71)*609+SUM(D72:D74)*1599+SUM(D75)*3059+SUM(D77)*379+SUM(D78)*799+SUM(D79)*439+SUM(D80)*599+SUM(D81)*229+SUM(D82)*219+SUM(D83:D86)*1299+SUM(D88:D90)*679+SUM(D92:D93)*490+SUM(D94:D95)*450+SUM(D97)*1054 -> 249 | E99: =SUM(E8:E14)*329+SUM(E15)*219+SUM(E19:E21)*239+SUM(E22:E24)*219+SUM(E27)*799+SUM(E28)*609+SUM(E29:E30)*329+SUM(E31:E32)*219+SUM(E33)*439+SUM(E34)*899+SUM(E35:E37)*549+SUM(E38:E39)*799+SUM(E40:E41)*439+SUM(E42)*60+SUM(E43)*609+SUM(E44:E45)*379+SUM(E46:E47)*1299+SUM(E50:E51)*609+SUM(E52)*329+SUM(E55)*599+SUM(E58:E60)*329+SUM(E61)*249+SUM(E62:E64)*439+SUM(E65:E67)*799+SUM(E68:E70)*1299+SUM(E71)*609+SUM(E72:E74)*1599+SUM(E75)*3059+SUM(E77)*379+SUM(E78)*799+SUM(E79)*439+SUM(E80)*599+SUM(E81)*229+SUM(E82)*219+SUM(E83:E86)*1299+SUM(E88:E90)*679+SUM(E92:E93)*490+SUM(E94:E95)*450+SUM(E97)*1054 -> 658 | F99: =SUM(F8:F14)*329+SUM(F15)*219+SUM(F19:F21)*239+SUM(F22:F24)*219+SUM(F27)*799+SUM(F28)*609+SUM(F29:F30)*329+SUM(F31:F32)*219+SUM(F33)*439+SUM(F34)*899+SUM(F35:F37)*549+SUM(F38:F39)*799+SUM(F40:F41)*439+SUM(F42)*60+SUM(F43)*609+SUM(F44:F45)*379+SUM(F46:F47)*1299+SUM(F50:F51)*609+SUM(F52)*329+SUM(F55)*599+SUM(F58:F60)*329+SUM(F61)*249+SUM(F62:F64)*439+SUM(F65:F67)*799+SUM(F68:F70)*1299+SUM(F71)*609+SUM(F72:F74)*1599+SUM(F75)*3059+SUM(F77)*379+SUM(F78)*799+SUM(F79)*439+SUM(F80)*599+SUM(F81)*229+SUM(F82)*219+SUM(F83:F86)*1299+SUM(F88:F90)*679+SUM(F92:F93)*490+SUM(F94:F95)*450+SUM(F97)*1054 -> 708 | H99: =SUM(C99:F99) -> 2414 | J99: =SUM(J8:J14)*329+SUM(J15)*219+SUM(J19:J21)*239+SUM(J22:J24)*219+SUM(J27)*799+SUM(J28)*609+SUM(J29:J30)*329+SUM(J31:J32)*219+SUM(J33)*439+SUM(J34)*899+SUM(J35:J37)*549+SUM(J38:J39)*799+SUM(J40:J41)*439+SUM(J42)*60+SUM(J43)*609+SUM(J44:J45)*379+SUM(J46:J47)*1299+SUM(J50:J51)*609+SUM(J52)*329+SUM(J55)*599+SUM(J58:J60)*329+SUM(J61)*249+SUM(J62:J64)*439+SUM(J65:J67)*799+SUM(J68:J70)*1299+SUM(J71)*609+SUM(J72:J74)*1599+SUM(J75)*3059+SUM(J77)*379+SUM(J78)*799+SUM(J79)*439+SUM(J80)*599+SUM(J81)*229+SUM(J82)*219+SUM(J83:J86)*1299+SUM(J88:J90)*679+SUM(J92:J93)*490+SUM(J94:J95)*450+SUM(J97)*1054 -> 329 | K99: =SUM(K8:K14)*329+SUM(K15)*219+SUM(K19:K21)*239+SUM(K22:K24)*219+SUM(K27)*799+SUM(K28)*609+SUM(K29:K30)*329+SUM(K31:K32)*219+SUM(K33)*439+SUM(K34)*899+SUM(K35:K37)*549+SUM(K38:K39)*799+SUM(K40:K41)*439+SUM(K42)*60+SUM(K43)*609+SUM(K44:K45)*379+SUM(K46:K47)*1299+SUM(K50:K51)*609+SUM(K52)*329+SUM(K55)*599+SUM(K58:K60)*329+SUM(K61)*249+SUM(K62:K64)*439+SUM(K65:K67)*799+SUM(K68:K70)*1299+SUM(K71)*609+SUM(K72:K74)*1599+SUM(K75)*3059+SUM(K77)*379+SUM(K78)*799+SUM(K79)*439+SUM(K80)*599+SUM(K81)*229+SUM(K82)*219+SUM(K83:K86)*1299+SUM(K88:K90)*679+SUM(K92:K93)*490+SUM(K94:K95)*450+SUM(K97)*1054 -> 439 | L99: =SUM(L8:L14)*329+SUM(L15)*219+SUM(L19:L21)*239+SUM(L22:L24)*219+SUM(L27)*799+SUM(L28)*609+SUM(L29:L30)*329+SUM(L31:L32)*219+SUM(L33)*439+SUM(L34)*899+SUM(L35:L37)*549+SUM(L38:L39)*799+SUM(L40:L41)*439+SUM(L42)*60+SUM(L43)*609+SUM(L44:L45)*379+SUM(L46:L47)*1299+SUM(L50:L51)*609+SUM(L52)*329+SUM(L55)*599+SUM(L58:L60)*329+SUM(L61)*249+SUM(L62:L64)*439+SUM(L65:L67)*799+SUM(L68:L70)*1299+SUM(L71)*609+SUM(L72:L74)*1599+SUM(L75)*3059+SUM(L77)*379+SUM(L78)*799+SUM(L79)*439+SUM(L80)*599+SUM(L81)*229+SUM(L82)*219+SUM(L83:L86)*1299+SUM(L88:L90)*679+SUM(L92:L93)*490+SUM(L94:L95)*450+SUM(L97)*1054 -> 329 | M99: =SUM(M8:M14)*329+SUM(M15)*219+SUM(M19:M21)*239+SUM(M22:M24)*219+SUM(M27)*799+SUM(M28)*609+SUM(M29:M30)*329+SUM(M31:M32)*219+SUM(M33)*439+SUM(M34)*899+SUM(M35:M37)*549+SUM(M38:M39)*799+SUM(M40:M41)*439+SUM(M42)*60+SUM(M43)*609+SUM(M44:M45)*379+SUM(M46:M47)*1299+SUM(M50:M51)*609+SUM(M52)*329+SUM(M55)*599+SUM(M58:M60)*329+SUM(M61)*249+SUM(M62:M64)*439+SUM(M65:M67)*799+SUM(M68:M70)*1299+SUM(M71)*609+SUM(M72:M74)*1599+SUM(M75)*3059+SUM(M77)*379+SUM(M78)*799+SUM(M79)*439+SUM(M80)*599+SUM(M81)*229+SUM(M82)*219+SUM(M83:M86)*1299+SUM(M88:M90)*679+SUM(M92:M93)*490+SUM(M94:M95)*450+SUM(M97)*1054 -> 439 | N99: =SUM(N8:N14)*329+SUM(N15)*219+SUM(N19:N21)*239+SUM(N22:N24)*219+SUM(N27)*799+SUM(N28)*609+SUM(N29:N30)*329+SUM(N31:N32)*219+SUM(N33)*439+SUM(N34)*899+SUM(N35:N37)*549+SUM(N38:N39)*799+SUM(N40:N41)*439+SUM(N42)*60+SUM(N43)*609+SUM(N44:N45)*379+SUM(N46:N47)*1299+SUM(N50:N51)*609+SUM(N52)*329+SUM(N55)*599+SUM(N58:N60)*329+SUM(N61)*249+SUM(N62:N64)*439+SUM(N65:N67)*799+SUM(N68:N70)*1299+SUM(N71)*609+SUM(N72:N74)*1599+SUM(N75)*3059+SUM(N77)*379+SUM(N78)*799+SUM(N79)*439+SUM(N80)*599+SUM(N81)*229+SUM(N82)*219+SUM(N83:N86)*1299+SUM(N88:N90)*679+SUM(N92:N93)*490+SUM(N94:N95)*450+SUM(N97)*1054 -> 329 | O99: =SUM(O8:O14)*329+SUM(O15)*219+SUM(O19:O21)*239+SUM(O22:O24)*219+SUM(O27)*799+SUM(O28)*609+SUM(O29:O30)*329+SUM(O31:O32)*219+SUM(O33)*439+SUM(O34)*899+SUM(O35:O37)*549+SUM(O38:O39)*799+SUM(O40:O41)*439+SUM(O42)*60+SUM(O43)*609+SUM(O44:O45)*379+SUM(O46:O47)*1299+SUM(O50:O51)*609+SUM(O52)*329+SUM(O55)*599+SUM(O58:O60)*329+SUM(O61)*249+SUM(O62:O64)*439+SUM(O65:O67)*799+SUM(O68:O70)*1299+SUM(O71)*609+SUM(O72:O74)*1599+SUM(O75)*3059+SUM(O77)*379+SUM(O78)*799+SUM(O79)*439+SUM(O80)*599+SUM(O81)*229+SUM(O82)*219+SUM(O83:O86)*1299+SUM(O88:O90)*679+SUM(O92:O93)*490+SUM(O94:O95)*450+SUM(O97)*1054 -> 658 | P99: =SUM(P8:P14)*329+SUM(P15)*219+SUM(P19:P21)*239+SUM(P22:P24)*219+SUM(P27)*799+SUM(P28)*609+SUM(P29:P30)*329+SUM(P31:P32)*219+SUM(P33)*439+SUM(P34)*899+SUM(P35:P37)*549+SUM(P38:P39)*799+SUM(P40:P41)*439+SUM(P42)*60+SUM(P43)*609+SUM(P44:P45)*379+SUM(P46:P47)*1299+SUM(P50:P51)*609+SUM(P52)*329+SUM(P55)*599+SUM(P58:P60)*329+SUM(P61)*249+SUM(P62:P64)*439+SUM(P65:P67)*799+SUM(P68:P70)*1299+SUM(P71)*609+SUM(P72:P74)*1599+SUM(P75)*3059+SUM(P77)*379+SUM(P78)*799+SUM(P79)*439+SUM(P80)*599+SUM(P81)*229+SUM(P82)*219+SUM(P83:P86)*1299+SUM(P88:P90)*679+SUM(P92:P93)*490+SUM(P94:P95)*450+SUM(P97)*1054 -> 329 | Q99: =SUM(Q8:Q14)*329+SUM(Q15)*219+SUM(Q19:Q21)*239+SUM(Q22:Q24)*219+SUM(Q27)*799+SUM(Q28)*609+SUM(Q29:Q30)*329+SUM(Q31:Q32)*219+SUM(Q33)*439+SUM(Q34)*899+SUM(Q35:Q37)*549+SUM(Q38:Q39)*799+SUM(Q40:Q41)*439+SUM(Q42)*60+SUM(Q43)*609+SUM(Q44:Q45)*379+SUM(Q46:Q47)*1299+SUM(Q50:Q51)*609+SUM(Q52)*329+SUM(Q55)*599+SUM(Q58:Q60)*329+SUM(Q61)*249+SUM(Q62:Q64)*439+SUM(Q65:Q67)*799+SUM(Q68:Q70)*1299+SUM(Q71)*609+SUM(Q72:Q74)*1599+SUM(Q75)*3059+SUM(Q77)*379+SUM(Q78)*799+SUM(Q79)*439+SUM(Q80)*599+SUM(Q81)*229+SUM(Q82)*219+SUM(Q83:Q86)*1299+SUM(Q88:Q90)*679+SUM(Q92:Q93)*490+SUM(Q94:Q95)*450+SUM(Q97)*1054 -> 658 | ... S99: =SUM(S8:S14)*329+SUM(S15)*219+SUM(S19:S21)*239+SUM(S22:S24)*219+SUM(S27)*799+SUM(S28)*609+SUM(S29:S30)*329+SUM(S31:S32)*219+SUM(S33)*439+SUM(S34)*899+SUM(S35:S37)*549+SUM(S38:S39)*799+SUM(S40:S41)*439+SUM(S42)*60+SUM(S43)*609+SUM(S44:S45)*379+SUM(S46:S47)*1299+SUM(S50:S51)*609+SUM(S52)*329+SUM(S55)*599+SUM(S58:S60)*329+SUM(S61)*249+SUM(S62:S64)*439+SUM(S65:S67)*799+SUM(S68:S70)*1299+SUM(S71)*609+SUM(S72:S74)*1599+SUM(S75)*3059+SUM(S77)*379+SUM(S78)*799+SUM(S79)*439+SUM(S80)*599+SUM(S81)*229+SUM(S82)*219+SUM(S83:S86)*1299+SUM(S88:S90)*679+SUM(S92:S93)*490+SUM(S94:S95)*450+SUM(S97)*1054 -> 329 | U99: =SUM(J99:S99) -> 4168 | W99: 219 | X99: 549 | Y99: 599 | Z99: 329 | AA99: 329 | AB99: =329*3 -> 987 | AD99: =SUM(Q99:AB99) -> 8496 | AG99: 329 | AH99: 329 | AI99: 658 | AJ99: 329 | AK99: 609 | AM99: =SUM(Y99:AK99) -> 12994 | AT99: =SUM(AO99:AR99) -> 0
AO100: 329 | AP100: 609 | AT100: =sum(AO100:AQ100) -> 938
A101: (+) shipping fee :
...

Sheet PICKAROO
C2: 46024 | J2: 46054 | Q2: 46095 | X2: 46122 | AE2: 46054 | AL2: 46095
A3: VARIANT | B3: PRICE
A5: Quiet Elegance | B5: 329
A6: Charming Home | B6: 329
A7: Bright Mornings | B7: 329
A8: Relaxing Naturals | B8: 329
A9: Mountain Breeze | B9: 329
A10: Fresh Bamboo | B10: 329
A11: Beach Escape | B11: 329
A12: White Tea | B12: 329
A13: Candy Cane | B13: 329
A14: Apple Cinnamon | B14: 329
A15: Easy Drive | B15: 219
A16: InLove
A17: Bright Mornings HW
A19: Lavender | B19: 239
A20: Eucalyptus | B20: 239
A21: Peppermint | B21: 239
A22: Fresh Bamboo FO | B22: 219
A23: Beach Escape FO | B23: 219
A24: White Tea FO | B24: 219
A25: Bright Mornings FO | B25: 219
A26: Quiet Elegance FO | B26: 219
A27: Fresh Bamboo Diffuser | B27: 799
A28: Clean Air | B28: 609
A29: Cotton Clean | B29: 329
A30: Brighter Days | B30: 329
... A74: Urban Oasis Reed Diffuser | B74: 1599
A75: Clean Air Gallon
A77: Holiday Hugs 200ml | B77: 379
A78: Holiday Hugs Diffuser Set | B78: 799
A79: Holiday Hugs Refill | B79: 439
A80: Bathroom Kit | B80: 599
A81: Flushie 50ml | B81: 229
A82: Easy Drive Grapefuit | B82: 219
A83: Fresh Bamboo Diffuser + Roomspray | B83: 1299
A84: White Tea Diffuser + Roomspray | B84: 1299
A85: Cotton Clean Diffuser + Roomspray | B85: 1299
A86: Holiday Hugs Diffuser + Roomspray | B86: 1299
A88: Sleep All Day | B88: 679
A89: One Way Ticket | B89: 679
... A97: Fresh Start Kit | B97: 1054
A98: Custom Order
A101: (+) shipping fee :
B102: (+) customize fee:
A103: (-) discount:
A104: (-) paymongo fee:
A105: (-) payment fee:
A106: To be remitted:
A108: =BI99 | B108: JANUARY
A109: =CC99 | B109: FEBRUARY
A110: =DV99 | B110: MARCH
A111: =FI99 | B111: APRIL
A112: =GX99 | B112: MAY
A113: =IH99 | B113: JUNE
A114: =JX99 | B114: JULY
A115: =LS99 | B115: AUGUST
A116: =NP99 | B116: SEPTEMBER
A117: =PA99 | B117: OCTOBER
A118: =QU99 | B118: NOVEMBER
A119: =ART100 | B119: DECEMBER
A120: =sum(A108:A116) -> 0

Sheet COMMONROOM  SUMMARY
C1: COMMON ROOM | Q1: TOTAL SOLD OF STOCKS FOR COMMON ROOMS
C2: TOTAL IN VOLUME | Q2: TOTAL IN VALUE
A3: VARIANT | B3: PRICE | C3: JAN | D3: FEB | E3: MAR | F3: APR | G3: MAY | H3: JUN | I3: JUL | J3: AUG | K3: SEP | L3: OCT | M3: NOV | N3: DEC | Q3: JAN | R3: FEB | S3: MAR | T3: APR | U3: MAY | V3: JUN | W3: JUL | X3: AUG | Y3: SEP | Z3: OCT | AA3: NOV | AB3: DEC
A5: Quiet Elegance | B5: 329
A6: Charming Home | B6: 329
A7: Bright Mornings | B7: 329
A8: Relaxing Naturals | B8: 349 | C8: ='COMMON ROOM'!C8+'COMMON ROOM'!O8+'COMMON ROOM'!AA8+'COMMON ROOM'!AM8+'COMMON ROOM'!AY8 -> 38 | D8: ='COMMON ROOM'!D8+'COMMON ROOM'!P8+'COMMON ROOM'!AB8+'COMMON ROOM'!AN8+'COMMON ROOM'!AZ8 -> 17 | E8: ='COMMON ROOM'!E8+'COMMON ROOM'!Q8+'COMMON ROOM'!AC8+'COMMON ROOM'!AO8+'COMMON ROOM'!BA8 -> 13 | F8: ='COMMON ROOM'!F8+'COMMON ROOM'!R8+'COMMON ROOM'!AD8+'COMMON ROOM'!AP8+'COMMON ROOM'!BB8 -> 15 | Q8: =B8*C8 -> 13262 | R8: =B8*D8 -> 5933 | S8: =B8*E8 -> 4537 | T8: =B8*F8 -> 5235 | U8: =B8*G8 -> 0 | V8: =B8*H8 -> 0 | W8: =B8*I8 -> 0 | X8: =B8*J8 -> 0 | Y8: =K8*B8 -> 0 | Z8: =B8*L8 -> 0 | AA8: =B8*M8 -> 0 | AB8: =B8*N8 -> 0
A9: Mountain Breeze | B9: 329 | C9: ='COMMON ROOM'!C9+'COMMON ROOM'!O9+'COMMON ROOM'!AA9+'COMMON ROOM'!AM9+'COMMON ROOM'!AY9 -> 0 | D9: ='COMMON ROOM'!D9+'COMMON ROOM'!P9+'COMMON ROOM'!AB9+'COMMON ROOM'!AN9+'COMMON ROOM'!AZ9 -> 0 | E9: ='COMMON ROOM'!E9+'COMMON ROOM'!Q9+'COMMON ROOM'!AC9+'COMMON ROOM'!AO9+'COMMON ROOM'!BA9 -> 0 | F9: ='COMMON ROOM'!F9+'COMMON ROOM'!R9+'COMMON ROOM'!AD9+'COMMON ROOM'!AP9+'COMMON ROOM'!BB9 -> 0 | Q9: =B9*C9 -> 0 | R9: =B9*D9 -> 0 | S9: =B9*E9 -> 0 | T9: =B9*F9 -> 0 | U9: =B9*G9 -> 0 | V9: =B9*H9 -> 0 | W9: =B9*I9 -> 0 | X9: =B9*J9 -> 0 | Y9: =K9*B9 -> 0 | Z9: =B9*L9 -> 0 | AA9: =B9*M9 -> 0 | AB9: =B9*N9 -> 0
A10: Fresh Bamboo | B10: 349 | C10: ='COMMON ROOM'!C10+'COMMON ROOM'!O10+'COMMON ROOM'!AA10+'COMMON ROOM'!AM10+'COMMON ROOM'!AY10 -> 23 | D10: ='COMMON ROOM'!D10+'COMMON ROOM'!P10+'COMMON ROOM'!AB10+'COMMON ROOM'!AN10+'COMMON ROOM'!AZ10 -> 3 | E10: ='COMMON ROOM'!E10+'COMMON ROOM'!Q10+'COMMON ROOM'!AC10+'COMMON ROOM'!AO10+'COMMON ROOM'!BA10 -> 9 | F10: ='COMMON ROOM'!F10+'COMMON ROOM'!R10+'COMMON ROOM'!AD10+'COMMON ROOM'!AP10+'COMMON ROOM'!BB10 -> 34 | Q10: =B10*C10 -> 8027 | R10: =B10*D10 -> 1047 | S10: =B10*E10 -> 3141 | T10: =B10*F10 -> 11866 | U10: =B10*G10 -> 0 | V10: =B10*H10 -> 0 | W10: =B10*I10 -> 0 | X10: =B10*J10 -> 0 | Y10: =K10*B10 -> 0 | Z10: =B10*L10 -> 0 | AA10: =B10*M10 -> 0 | AB10: =B10*N10 -> 0
A11: Beach Escape | B11: 349 | C11: ='COMMON ROOM'!C11+'COMMON ROOM'!O11+'COMMON ROOM'!AA11+'COMMON ROOM'!AM11+'COMMON ROOM'!AY11 -> 24 | D11: ='COMMON ROOM'!D11+'COMMON ROOM'!P11+'COMMON ROOM'!AB11+'COMMON ROOM'!AN11+'COMMON ROOM'!AZ11 -> 2 | E11: ='COMMON ROOM'!E11+'COMMON ROOM'!Q11+'COMMON ROOM'!AC11+'COMMON ROOM'!AO11+'COMMON ROOM'!BA11 -> 11 | F11: ='COMMON ROOM'!F11+'COMMON ROOM'!R11+'COMMON ROOM'!AD11+'COMMON ROOM'!AP11+'COMMON ROOM'!BB11 -> 21 | Q11: =B11*C11 -> 8376 | R11: =B11*D11 -> 698 | S11: =B11*E11 -> 3839 | T11: =B11*F11 -> 7329 | U11: =B11*G11 -> 0 | V11: =B11*H11 -> 0 | W11: =B11*I11 -> 0 | X11: =B11*J11 -> 0 | Y11: =K11*B11 -> 0 | Z11: =B11*L11 -> 0 | AA11: =B11*M11 -> 0 | AB11: =B11*N11 -> 0
A12: White Tea | B12: 349 | C12: ='COMMON ROOM'!C12+'COMMON ROOM'!O12+'COMMON ROOM'!AA12+'COMMON ROOM'!AM12+'COMMON ROOM'!AY12 -> 16 | D12: ='COMMON ROOM'!D12+'COMMON ROOM'!P12+'COMMON ROOM'!AB12+'COMMON ROOM'!AN12+'COMMON ROOM'!AZ12 -> 8 | E12: ='COMMON ROOM'!E12+'COMMON ROOM'!Q12+'COMMON ROOM'!AC12+'COMMON ROOM'!AO12+'COMMON ROOM'!BA12 -> 8 | F12: ='COMMON ROOM'!F12+'COMMON ROOM'!R12+'COMMON ROOM'!AD12+'COMMON ROOM'!AP12+'COMMON ROOM'!BB12 -> 22 | Q12: =B12*C12 -> 5584 | R12: =B12*D12 -> 2792 | S12: =B12*E12 -> 2792 | T12: =B12*F12 -> 7678 | U12: =B12*G12 -> 0 | V12: =B12*H12 -> 0 | W12: =B12*I12 -> 0 | X12: =B12*J12 -> 0 | Y12: =K12*B12 -> 0 | Z12: =B12*L12 -> 0 | AA12: =B12*M12 -> 0 | AB12: =B12*N12 -> 0
A13: Candy Cane | B13: 349 | C13: ='COMMON ROOM'!C13+'COMMON ROOM'!O13+'COMMON ROOM'!AA13+'COMMON ROOM'!AM13+'COMMON ROOM'!AY13 -> 0 | D13: ='COMMON ROOM'!D13+'COMMON ROOM'!P13+'COMMON ROOM'!AB13+'COMMON ROOM'!AN13+'COMMON ROOM'!AZ13 -> 2 | E13: ='COMMON ROOM'!E13+'COMMON ROOM'!Q13+'COMMON ROOM'!AC13+'COMMON ROOM'!AO13+'COMMON ROOM'!BA13 -> 3 | F13: ='COMMON ROOM'!F13+'COMMON ROOM'!R13+'COMMON ROOM'!AD13+'COMMON ROOM'!AP13+'COMMON ROOM'!BB13 -> 2 | Q13: =B13*C13 -> 0 | R13: =B13*D13 -> 698 | S13: =B13*E13 -> 1047 | T13: =B13*F13 -> 698 | U13: =B13*G13 -> 0 | V13: =B13*H13 -> 0 | W13: =B13*I13 -> 0 | X13: =B13*J13 -> 0 | Y13: =K13*B13 -> 0 | Z13: =B13*L13 -> 0 | AA13: =B13*M13 -> 0 | AB13: =B13*N13 -> 0
A14: Apple Cinnamon | B14: 349 | C14: ='COMMON ROOM'!C14+'COMMON ROOM'!O14+'COMMON ROOM'!AA14+'COMMON ROOM'!AM14+'COMMON ROOM'!AY14 -> 8 | D14: ='COMMON ROOM'!D14+'COMMON ROOM'!P14+'COMMON ROOM'!AB14+'COMMON ROOM'!AN14+'COMMON ROOM'!AZ14 -> 0 | E14: ='COMMON ROOM'!E14+'COMMON ROOM'!Q14+'COMMON ROOM'!AC14+'COMMON ROOM'!AO14+'COMMON ROOM'!BA14 -> 3 | F14: ='COMMON ROOM'!F14+'COMMON ROOM'!R14+'COMMON ROOM'!AD14+'COMMON ROOM'!AP14+'COMMON ROOM'!BB14 -> 0 | Q14: =B14*C14 -> 2792 | R14: =B14*D14 -> 0 | S14: =B14*E14 -> 1047 | T14: =B14*F14 -> 0 | U14: =B14*G14 -> 0 | V14: =B14*H14 -> 0 | W14: =B14*I14 -> 0 | X14: =B14*J14 -> 0 | Y14: =K14*B14 -> 0 | Z14: =B14*L14 -> 0 | AA14: =B14*M14 -> 0 | AB14: =B14*N14 -> 0
A15: Easy Drive | B15: 239 | C15: ='COMMON ROOM'!C15+'COMMON ROOM'!O15+'COMMON ROOM'!AA15+'COMMON ROOM'!AM15+'COMMON ROOM'!AY15 -> 2 | D15: ='COMMON ROOM'!D15+'COMMON ROOM'!P15+'COMMON ROOM'!AB15+'COMMON ROOM'!AN15+'COMMON ROOM'!AZ15 -> 4 | E15: ='COMMON ROOM'!E15+'COMMON ROOM'!Q15+'COMMON ROOM'!AC15+'COMMON ROOM'!AO15+'COMMON ROOM'!BA15 -> 4 | F15: ='COMMON ROOM'!F15+'COMMON ROOM'!R15+'COMMON ROOM'!AD15+'COMMON ROOM'!AP15+'COMMON ROOM'!BB15 -> 4 | Q15: =B15*C15 -> 478 | R15: =B15*D15 -> 956 | S15: =B15*E15 -> 956 | T15: =B15*F15 -> 956 | U15: =B15*G15 -> 0 | V15: =B15*H15 -> 0 | W15: =B15*I15 -> 0 | X15: =B15*J15 -> 0 | Y15: =K15*B15 -> 0 | Z15: =B15*L15 -> 0 | AA15: =B15*M15 -> 0 | AB15: =B15*N15 -> 0
A16: InLove | C16: ='COMMON ROOM'!C16+'COMMON ROOM'!O16+'COMMON ROOM'!AA16+'COMMON ROOM'!AM16+'COMMON ROOM'!AY16 -> 0 | D16: ='COMMON ROOM'!D16+'COMMON ROOM'!P16+'COMMON ROOM'!AB16+'COMMON ROOM'!AN16+'COMMON ROOM'!AZ16 -> 0 | E16: ='COMMON ROOM'!E16+'COMMON ROOM'!Q16+'COMMON ROOM'!AC16+'COMMON ROOM'!AO16+'COMMON ROOM'!BA16 -> 0 | F16: ='COMMON ROOM'!F16+'COMMON ROOM'!R16+'COMMON ROOM'!AD16+'COMMON ROOM'!AP16+'COMMON ROOM'!BB16 -> 0 | Q16: =B16*C16 -> 0 | R16: =B16*D16 -> 0 | S16: =B16*E16 -> 0 | T16: =B16*F16 -> 0 | U16: =B16*G16 -> 0 | V16: =B16*H16 -> 0 | W16: =B16*I16 -> 0 | X16: =B16*J16 -> 0 | Y16: =K16*B16 -> 0 | Z16: =B16*L16 -> 0 | AA16: =B16*M16 -> 0 | AB16: =B16*N16 -> 0
A17: Bright Mornings HW | C17: ='COMMON ROOM'!C17+'COMMON ROOM'!O17+'COMMON ROOM'!AA17+'COMMON ROOM'!AM17+'COMMON ROOM'!AY17 -> 0 | D17: ='COMMON ROOM'!D17+'COMMON ROOM'!P17+'COMMON ROOM'!AB17+'COMMON ROOM'!AN17+'COMMON ROOM'!AZ17 -> 0 | E17: ='COMMON ROOM'!E17+'COMMON ROOM'!Q17+'COMMON ROOM'!AC17+'COMMON ROOM'!AO17+'COMMON ROOM'!BA17 -> 0 | F17: ='COMMON ROOM'!F17+'COMMON ROOM'!R17+'COMMON ROOM'!AD17+'COMMON ROOM'!AP17+'COMMON ROOM'!BB17 -> 0 | Q17: =B17*C17 -> 0 | R17: =B17*D17 -> 0 | S17: =B17*E17 -> 0 | T17: =B17*F17 -> 0 | U17: =B17*G17 -> 0 | V17: =B17*H17 -> 0 | W17: =B17*I17 -> 0 | X17: =B17*J17 -> 0 | Y17: =K17*B17 -> 0 | Z17: =B17*L17 -> 0 | AA17: =B17*M17 -> 0 | AB17: =B17*N17 -> 0
C18: ='COMMON ROOM'!C18+'COMMON ROOM'!O18+'COMMON ROOM'!AA18+'COMMON ROOM'!AM18+'COMMON ROOM'!AY18 -> 0 | D18: ='COMMON ROOM'!D18+'COMMON ROOM'!P18+'COMMON ROOM'!AB18+'COMMON ROOM'!AN18+'COMMON ROOM'!AZ18 -> 0 | E18: ='COMMON ROOM'!E18+'COMMON ROOM'!Q18+'COMMON ROOM'!AC18+'COMMON ROOM'!AO18+'COMMON ROOM'!BA18 -> 0 | F18: ='COMMON ROOM'!F18+'COMMON ROOM'!R18+'COMMON ROOM'!AD18+'COMMON ROOM'!AP18+'COMMON ROOM'!BB18 -> 0 | Q18: =B18*C18 -> 0 | R18: =B18*D18 -> 0 | S18: =B18*E18 -> 0 | T18: =B18*F18 -> 0 | U18: =B18*G18 -> 0 | V18: =B18*H18 -> 0 | W18: =B18*I18 -> 0 | X18: =B18*J18 -> 0 | Y18: =K18*B18 -> 0 | Z18: =B18*L18 -> 0 | AA18: =B18*M18 -> 0 | AB18: =B18*N18 -> 0
A19: Lavender | B19: 259 | C19: ='COMMON ROOM'!C19+'COMMON ROOM'!O19+'COMMON ROOM'!AA19+'COMMON ROOM'!AM19+'COMMON ROOM'!AY19 -> 11 | D19: ='COMMON ROOM'!D19+'COMMON ROOM'!P19+'COMMON ROOM'!AB19+'COMMON ROOM'!AN19+'COMMON ROOM'!AZ19 -> 10 | E19: ='COMMON ROOM'!E19+'COMMON ROOM'!Q19+'COMMON ROOM'!AC19+'COMMON ROOM'!AO19+'COMMON ROOM'!BA19 -> 10 | F19: ='COMMON ROOM'!F19+'COMMON ROOM'!R19+'COMMON ROOM'!AD19+'COMMON ROOM'!AP19+'COMMON ROOM'!BB19 -> 3 | Q19: =B19*C19 -> 2849 | R19: =B19*D19 -> 2590 | S19: =B19*E19 -> 2590 | T19: =B19*F19 -> 777 | U19: =B19*G19 -> 0 | V19: =B19*H19 -> 0 | W19: =B19*I19 -> 0 | X19: =B19*J19 -> 0 | Y19: =K19*B19 -> 0 | Z19: =B19*L19 -> 0 | AA19: =B19*M19 -> 0 | AB19: =B19*N19 -> 0
A20: Eucalyptus | B20: 259 | C20: ='COMMON ROOM'!C20+'COMMON ROOM'!O20+'COMMON ROOM'!AA20+'COMMON ROOM'!AM20+'COMMON ROOM'!AY20 -> 9 | D20: ='COMMON ROOM'!D20+'COMMON ROOM'!P20+'COMMON ROOM'!AB20+'COMMON ROOM'!AN20+'COMMON ROOM'!AZ20 -> 7 | E20: ='COMMON ROOM'!E20+'COMMON ROOM'!Q20+'COMMON ROOM'!AC20+'COMMON ROOM'!AO20+'COMMON ROOM'!BA20 -> 9 | F20: ='COMMON ROOM'!F20+'COMMON ROOM'!R20+'COMMON ROOM'!AD20+'COMMON ROOM'!AP20+'COMMON ROOM'!BB20 -> 6 | Q20: =B20*C20 -> 2331 | R20: =B20*D20 -> 1813 | S20: =B20*E20 -> 2331 | T20: =B20*F20 -> 1554 | U20: =B20*G20 -> 0 | V20: =B20*H20 -> 0 | W20: =B20*I20 -> 0 | X20: =B20*J20 -> 0 | Y20: =K20*B20 -> 0 | Z20: =B20*L20 -> 0 | AA20: =B20*M20 -> 0 | AB20: =B20*N20 -> 0
A21: Peppermint | B21: 259 | C21: ='COMMON ROOM'!C21+'COMMON ROOM'!O21+'COMMON ROOM'!AA21+'COMMON ROOM'!AM21+'COMMON ROOM'!AY21 -> 13 | D21: ='COMMON ROOM'!D21+'COMMON ROOM'!P21+'COMMON ROOM'!AB21+'COMMON ROOM'!AN21+'COMMON ROOM'!AZ21 -> 1 | E21: ='COMMON ROOM'!E21+'COMMON ROOM'!Q21+'COMMON ROOM'!AC21+'COMMON ROOM'!AO21+'COMMON ROOM'!BA21 -> 9 | F21: ='COMMON ROOM'!F21+'COMMON ROOM'!R21+'COMMON ROOM'!AD21+'COMMON ROOM'!AP21+'COMMON ROOM'!BB21 -> 2 | Q21: =B21*C21 -> 3367 | R21: =B21*D21 -> 259 | S21: =B21*E21 -> 2331 | T21: =B21*F21 -> 518 | U21: =B21*G21 -> 0 | V21: =B21*H21 -> 0 | W21: =B21*I21 -> 0 | X21: =B21*J21 -> 0 | Y21: =K21*B21 -> 0 | Z21: =B21*L21 -> 0 | AA21: =B21*M21 -> 0 | AB21: =B21*N21 -> 0
A22: Fresh Bamboo FO | B22: 239 | C22: ='COMMON ROOM'!C22+'COMMON ROOM'!O22+'COMMON ROOM'!AA22+'COMMON ROOM'!AM22+'COMMON ROOM'!AY22 -> 9 | D22: ='COMMON ROOM'!D22+'COMMON ROOM'!P22+'COMMON ROOM'!AB22+'COMMON ROOM'!AN22+'COMMON ROOM'!AZ22 -> 22 | E22: ='COMMON ROOM'!E22+'COMMON ROOM'!Q22+'COMMON ROOM'!AC22+'COMMON ROOM'!AO22+'COMMON ROOM'!BA22 -> 7 | F22: ='COMMON ROOM'!F22+'COMMON ROOM'!R22+'COMMON ROOM'!AD22+'COMMON ROOM'!AP22+'COMMON ROOM'!BB22 -> 6 | Q22: =B22*C22 -> 2151 | R22: =B22*D22 -> 5258 | S22: =B22*E22 -> 1673 | T22: =B22*F22 -> 1434 | U22: =B22*G22 -> 0 | V22: =B22*H22 -> 0 | W22: =B22*I22 -> 0 | X22: =B22*J22 -> 0 | Y22: =K22*B22 -> 0 | Z22: =B22*L22 -> 0 | AA22: =B22*M22 -> 0 | AB22: =B22*N22 -> 0
A23: Beach Escape FO | B23: 239 | C23: ='COMMON ROOM'!C23+'COMMON ROOM'!O23+'COMMON ROOM'!AA23+'COMMON ROOM'!AM23+'COMMON ROOM'!AY23 -> 6 | D23: ='COMMON ROOM'!D23+'COMMON ROOM'!P23+'COMMON ROOM'!AB23+'COMMON ROOM'!AN23+'COMMON ROOM'!AZ23 -> 6 | E23: ='COMMON ROOM'!E23+'COMMON ROOM'!Q23+'COMMON ROOM'!AC23+'COMMON ROOM'!AO23+'COMMON ROOM'!BA23 -> 7 | F23: ='COMMON ROOM'!F23+'COMMON ROOM'!R23+'COMMON ROOM'!AD23+'COMMON ROOM'!AP23+'COMMON ROOM'!BB23 -> 7 | Q23: =B23*C23 -> 1434 | R23: =B23*D23 -> 1434 | S23: =B23*E23 -> 1673 | T23: =B23*F23 -> 1673 | U23: =B23*G23 -> 0 | V23: =B23*H23 -> 0 | W23: =B23*I23 -> 0 | X23: =B23*J23 -> 0 | Y23: =K23*B23 -> 0 | Z23: =B23*L23 -> 0 | AA23: =B23*M23 -> 0 | AB23: =B23*N23 -> 0
A24: White Tea FO | B24: 239 | C24: ='COMMON ROOM'!C24+'COMMON ROOM'!O24+'COMMON ROOM'!AA24+'COMMON ROOM'!AM24+'COMMON ROOM'!AY24 -> 3 | D24: ='COMMON ROOM'!D24+'COMMON ROOM'!P24+'COMMON ROOM'!AB24+'COMMON ROOM'!AN24+'COMMON ROOM'!AZ24 -> 3 | E24: ='COMMON ROOM'!E24+'COMMON ROOM'!Q24+'COMMON ROOM'!AC24+'COMMON ROOM'!AO24+'COMMON ROOM'!BA24 -> 1 | F24: ='COMMON ROOM'!F24+'COMMON ROOM'!R24+'COMMON ROOM'!AD24+'COMMON ROOM'!AP24+'COMMON ROOM'!BB24 -> 3 | Q24: =B24*C24 -> 717 | R24: =B24*D24 -> 717 | S24: =B24*E24 -> 239 | T24: =B24*F24 -> 717 | U24: =B24*G24 -> 0 | V24: =B24*H24 -> 0 | W24: =B24*I24 -> 0 | X24: =B24*J24 -> 0 | Y24: =K24*B24 -> 0 | Z24: =B24*L24 -> 0 | AA24: =B24*M24 -> 0 | AB24: =B24*N24 -> 0
A25: Bright Mornings FO | B25: 219 | C25: ='COMMON ROOM'!C25+'COMMON ROOM'!O25+'COMMON ROOM'!AA25+'COMMON ROOM'!AM25+'COMMON ROOM'!AY25 -> 0 | D25: ='COMMON ROOM'!D25+'COMMON ROOM'!P25+'COMMON ROOM'!AB25+'COMMON ROOM'!AN25+'COMMON ROOM'!AZ25 -> 0 | E25: ='COMMON ROOM'!E25+'COMMON ROOM'!Q25+'COMMON ROOM'!AC25+'COMMON ROOM'!AO25+'COMMON ROOM'!BA25 -> 0 | F25: ='COMMON ROOM'!F25+'COMMON ROOM'!R25+'COMMON ROOM'!AD25+'COMMON ROOM'!AP25+'COMMON ROOM'!BB25 -> 0 | Q25: =B25*C25 -> 0 | R25: =B25*D25 -> 0 | S25: =B25*E25 -> 0 | T25: =B25*F25 -> 0 | U25: =B25*G25 -> 0 | V25: =B25*H25 -> 0 | W25: =B25*I25 -> 0 | X25: =B25*J25 -> 0 | Y25: =K25*B25 -> 0 | Z25: =B25*L25 -> 0 | AA25: =B25*M25 -> 0 | AB25: =B25*N25 -> 0
A26: Quiet Elegance FO | B26: 219 | C26: ='COMMON ROOM'!C26+'COMMON ROOM'!O26+'COMMON ROOM'!AA26+'COMMON ROOM'!AM26+'COMMON ROOM'!AY26 -> 0 | D26: ='COMMON ROOM'!D26+'COMMON ROOM'!P26+'COMMON ROOM'!AB26+'COMMON ROOM'!AN26+'COMMON ROOM'!AZ26 -> 0 | E26: ='COMMON ROOM'!E26+'COMMON ROOM'!Q26+'COMMON ROOM'!AC26+'COMMON ROOM'!AO26+'COMMON ROOM'!BA26 -> 0 | F26: ='COMMON ROOM'!F26+'COMMON ROOM'!R26+'COMMON ROOM'!AD26+'COMMON ROOM'!AP26+'COMMON ROOM'!BB26 -> 0 | Q26: =B26*C26 -> 0 | R26: =B26*D26 -> 0 | S26: =B26*E26 -> 0 | T26: =B26*F26 -> 0 | U26: =B26*G26 -> 0 | V26: =B26*H26 -> 0 | W26: =B26*I26 -> 0 | X26: =B26*J26 -> 0 | Y26: =K26*B26 -> 0 | Z26: =B26*L26 -> 0 | AA26: =B26*M26 -> 0 | AB26: =B26*N26 -> 0
A27: Fresh Bamboo Diffuser | B27: 819 | C27: ='COMMON ROOM'!C27+'COMMON ROOM'!O27+'COMMON ROOM'!AA27+'COMMON ROOM'!AM27+'COMMON ROOM'!AY27 -> 0 | D27: ='COMMON ROOM'!D27+'COMMON ROOM'!P27+'COMMON ROOM'!AB27+'COMMON ROOM'!AN27+'COMMON ROOM'!AZ27 -> 0 | E27: ='COMMON ROOM'!E27+'COMMON ROOM'!Q27+'COMMON ROOM'!AC27+'COMMON ROOM'!AO27+'COMMON ROOM'!BA27 -> 0 | F27: ='COMMON ROOM'!F27+'COMMON ROOM'!R27+'COMMON ROOM'!AD27+'COMMON ROOM'!AP27+'COMMON ROOM'!BB27 -> 0 | Q27: =B27*C27 -> 0 | R27: =B27*D27 -> 0 | S27: =B27*E27 -> 0 | T27: =B27*F27 -> 0 | U27: =B27*G27 -> 0 | V27: =B27*H27 -> 0 | W27: =B27*I27 -> 0 | X27: =B27*J27 -> 0 | Y27: =K27*B27 -> 0 | Z27: =B27*L27 -> 0 | AA27: =B27*M27 -> 0 | AB27: =B27*N27 -> 0
A28: Clean Air | B28: 629 | C28: ='COMMON ROOM'!C28+'COMMON ROOM'!O28+'COMMON ROOM'!AA28+'COMMON ROOM'!AM28+'COMMON ROOM'!AY28 -> 3 | D28: ='COMMON ROOM'!D28+'COMMON ROOM'!P28+'COMMON ROOM'!AB28+'COMMON ROOM'!AN28+'COMMON ROOM'!AZ28 -> 3 | E28: ='COMMON ROOM'!E28+'COMMON ROOM'!Q28+'COMMON ROOM'!AC28+'COMMON ROOM'!AO28+'COMMON ROOM'!BA28 -> 4 | F28: ='COMMON ROOM'!F28+'COMMON ROOM'!R28+'COMMON ROOM'!AD28+'COMMON ROOM'!AP28+'COMMON ROOM'!BB28 -> 4 | Q28: =B28*C28 -> 1887 | R28: =B28*D28 -> 1887 | S28: =B28*E28 -> 2516 | T28: =B28*F28 -> 2516 | U28: =B28*G28 -> 0 | V28: =B28*H28 -> 0 | W28: =B28*I28 -> 0 | X28: =B28*J28 -> 0 | Y28: =K28*B28 -> 0 | Z28: =B28*L28 -> 0 | AA28: =B28*M28 -> 0 | AB28: =B28*N28 -> 0
A29: Cotton Clean | B29: 349 | C29: ='COMMON ROOM'!C29+'COMMON ROOM'!O29+'COMMON ROOM'!AA29+'COMMON ROOM'!AM29+'COMMON ROOM'!AY29 -> 13 | D29: ='COMMON ROOM'!D29+'COMMON ROOM'!P29+'COMMON ROOM'!AB29+'COMMON ROOM'!AN29+'COMMON ROOM'!AZ29 -> 7 | E29: ='COMMON ROOM'!E29+'COMMON ROOM'!Q29+'COMMON ROOM'!AC29+'COMMON ROOM'!AO29+'COMMON ROOM'!BA29 -> 1 | F29: ='COMMON ROOM'!F29+'COMMON ROOM'!R29+'COMMON ROOM'!AD29+'COMMON ROOM'!AP29+'COMMON ROOM'!BB29 -> 8 | Q29: =B29*C29 -> 4537 | R29: =B29*D29 -> 2443 | S29: =B29*E29 -> 349 | T29: =B29*F29 -> 2792 | U29: =B29*G29 -> 0 | V29: =B29*H29 -> 0 | W29: =B29*I29 -> 0 | X29: =B29*J29 -> 0 | Y29: =K29*B29 -> 0 | Z29: =B29*L29 -> 0 | AA29: =B29*M29 -> 0 | AB29: =B29*N29 -> 0
A30: Brighter Days | B30: 349 | C30: ='COMMON ROOM'!C30+'COMMON ROOM'!O30+'COMMON ROOM'!AA30+'COMMON ROOM'!AM30+'COMMON ROOM'!AY30 -> 0 | D30: ='COMMON ROOM'!D30+'COMMON ROOM'!P30+'COMMON ROOM'!AB30+'COMMON ROOM'!AN30+'COMMON ROOM'!AZ30 -> 0 | E30: ='COMMON ROOM'!E30+'COMMON ROOM'!Q30+'COMMON ROOM'!AC30+'COMMON ROOM'!AO30+'COMMON ROOM'!BA30 -> 0 | F30: ='COMMON ROOM'!F30+'COMMON ROOM'!R30+'COMMON ROOM'!AD30+'COMMON ROOM'!AP30+'COMMON ROOM'!BB30 -> 0 | Q30: =B30*C30 -> 0 | R30: =B30*D30 -> 0 | S30: =B30*E30 -> 0 | T30: =B30*F30 -> 0 | U30: =B30*G30 -> 0 | V30: =B30*H30 -> 0 | W30: =B30*I30 -> 0 | X30: =B30*J30 -> 0 | Y30: =K30*B30 -> 0 | Z30: =B30*L30 -> 0 | AA30: =B30*M30 -> 0 | AB30: =B30*N30 -> 0
... A48: Simoy ng Pahiyas | B48: 0 | C48: ='COMMON ROOM'!C48+'COMMON ROOM'!O48+'COMMON ROOM'!AA48+'COMMON ROOM'!AM48+'COMMON ROOM'!AY48 -> 0 | D48: ='COMMON ROOM'!D48+'COMMON ROOM'!P48+'COMMON ROOM'!AB48+'COMMON ROOM'!AN48+'COMMON ROOM'!AZ48 -> 0 | E48: ='COMMON ROOM'!E48+'COMMON ROOM'!Q48+'COMMON ROOM'!AC48+'COMMON ROOM'!AO48+'COMMON ROOM'!BA48 -> 0 | F48: ='COMMON ROOM'!F48+'COMMON ROOM'!R48+'COMMON ROOM'!AD48+'COMMON ROOM'!AP48+'COMMON ROOM'!BB48 -> 0 | Q48: =B48*C48 -> 0 | R48: =B48*D48 -> 0 | S48: =B48*E48 -> 0 | T48: =B48*F48 -> 0 | U48: =B48*G48 -> 0 | V48: =B48*H48 -> 0 | W48: =B48*I48 -> 0 | X48: =B48*J48 -> 0 | Y48: =K48*B48 -> 0 | Z48: =B48*L48 -> 0 | AA48: =B48*M48 -> 0 | AB48: =B48*N48 -> 0
C49: ='COMMON ROOM'!C49+'COMMON ROOM'!O49+'COMMON ROOM'!AA49+'COMMON ROOM'!AM49+'COMMON ROOM'!AY49 -> 0 | D49: ='COMMON ROOM'!D49+'COMMON ROOM'!P49+'COMMON ROOM'!AB49+'COMMON ROOM'!AN49+'COMMON ROOM'!AZ49 -> 0 | E49: ='COMMON ROOM'!E49+'COMMON ROOM'!Q49+'COMMON ROOM'!AC49+'COMMON ROOM'!AO49+'COMMON ROOM'!BA49 -> 0 | F49: ='COMMON ROOM'!F49+'COMMON ROOM'!R49+'COMMON ROOM'!AD49+'COMMON ROOM'!AP49+'COMMON ROOM'!BB49 -> 0 | Q49: =B49*C49 -> 0 | R49: =B49*D49 -> 0 | S49: =B49*E49 -> 0 | T49: =B49*F49 -> 0 | U49: =B49*G49 -> 0 | V49: =B49*H49 -> 0 | W49: =B49*I49 -> 0 | X49: =B49*J49 -> 0 | Y49: =K49*B49 -> 0 | Z49: =B49*L49 -> 0 | AA49: =B49*M49 -> 0 | AB49: =B49*N49 -> 0
A50: Fresh Bamboo 500ml | B50: 629 | C50: ='COMMON ROOM'!C50+'COMMON ROOM'!O50+'COMMON ROOM'!AA50+'COMMON ROOM'!AM50+'COMMON ROOM'!AY50 -> 24 | D50: ='COMMON ROOM'!D50+'COMMON ROOM'!P50+'COMMON ROOM'!AB50+'COMMON ROOM'!AN50+'COMMON ROOM'!AZ50 -> 22 | E50: ='COMMON ROOM'!E50+'COMMON ROOM'!Q50+'COMMON ROOM'!AC50+'COMMON ROOM'!AO50+'COMMON ROOM'!BA50 -> 6 | F50: ='COMMON ROOM'!F50+'COMMON ROOM'!R50+'COMMON ROOM'!AD50+'COMMON ROOM'!AP50+'COMMON ROOM'!BB50 -> 18 | Q50: =B50*C50 -> 15096 | R50: =B50*D50 -> 13838 | S50: =B50*E50 -> 3774 | T50: =B50*F50 -> 11322 | U50: =B50*G50 -> 0 | V50: =B50*H50 -> 0 | W50: =B50*I50 -> 0 | X50: =B50*J50 -> 0 | Y50: =K50*B50 -> 0 | Z50: =B50*L50 -> 0 | AA50: =B50*M50 -> 0 | AB50: =B50*N50 -> 0
A51: White Tea 500ml | B51: 629 | C51: ='COMMON ROOM'!C51+'COMMON ROOM'!O51+'COMMON ROOM'!AA51+'COMMON ROOM'!AM51+'COMMON ROOM'!AY51 -> 12 | D51: ='COMMON ROOM'!D51+'COMMON ROOM'!P51+'COMMON ROOM'!AB51+'COMMON ROOM'!AN51+'COMMON ROOM'!AZ51 -> 18 | E51: ='COMMON ROOM'!E51+'COMMON ROOM'!Q51+'COMMON ROOM'!AC51+'COMMON ROOM'!AO51+'COMMON ROOM'!BA51 -> 8 | F51: ='COMMON ROOM'!F51+'COMMON ROOM'!R51+'COMMON ROOM'!AD51+'COMMON ROOM'!AP51+'COMMON ROOM'!BB51 -> 9 | Q51: =B51*C51 -> 7548 | R51: =B51*D51 -> 11322 | S51: =B51*E51 -> 5032 | T51: =B51*F51 -> 5661 | U51: =B51*G51 -> 0 | V51: =B51*H51 -> 0 | W51: =B51*I51 -> 0 | X51: =B51*J51 -> 0 | Y51: =K51*B51 -> 0 | Z51: =B51*L51 -> 0 | AA51: =B51*M51 -> 0 | AB51: =B51*N51 -> 0
A52: Tropical Paradise 200ml | B52: 349 | C52: ='COMMON ROOM'!C52+'COMMON ROOM'!O52+'COMMON ROOM'!AA52+'COMMON ROOM'!AM52+'COMMON ROOM'!AY52 -> 2 | D52: ='COMMON ROOM'!D52+'COMMON ROOM'!P52+'COMMON ROOM'!AB52+'COMMON ROOM'!AN52+'COMMON ROOM'!AZ52 -> 1 | E52: ='COMMON ROOM'!E52+'COMMON ROOM'!Q52+'COMMON ROOM'!AC52+'COMMON ROOM'!AO52+'COMMON ROOM'!BA52 -> 0 | F52: ='COMMON ROOM'!F52+'COMMON ROOM'!R52+'COMMON ROOM'!AD52+'COMMON ROOM'!AP52+'COMMON ROOM'!BB52 -> 0 | Q52: =B52*C52 -> 698 | R52: =B52*D52 -> 349 | S52: =B52*E52 -> 0 | T52: =B52*F52 -> 0 | U52: =B52*G52 -> 0 | V52: =B52*H52 -> 0 | W52: =B52*I52 -> 0 | X52: =B52*J52 -> 0 | Y52: =K52*B52 -> 0 | Z52: =B52*L52 -> 0 | AA52: =B52*M52 -> 0 | AB52: =B52*N52 -> 0
A53: RN Wash 100ml | B53: 199 | C53: ='COMMON ROOM'!C53+'COMMON ROOM'!O53+'COMMON ROOM'!AA53+'COMMON ROOM'!AM53+'COMMON ROOM'!AY53 -> 0 | D53: ='COMMON ROOM'!D53+'COMMON ROOM'!P53+'COMMON ROOM'!AB53+'COMMON ROOM'!AN53+'COMMON ROOM'!AZ53 -> 0 | E53: ='COMMON ROOM'!E53+'COMMON ROOM'!Q53+'COMMON ROOM'!AC53+'COMMON ROOM'!AO53+'COMMON ROOM'!BA53 -> 0 | F53: ='COMMON ROOM'!F53+'COMMON ROOM'!R53+'COMMON ROOM'!AD53+'COMMON ROOM'!AP53+'COMMON ROOM'!BB53 -> 0 | Q53: =B53*C53 -> 0 | R53: =B53*D53 -> 0 | S53: =B53*E53 -> 0 | T53: =B53*F53 -> 0 | U53: =B53*G53 -> 0 | V53: =B53*H53 -> 0 | W53: =B53*I53 -> 0 | X53: =B53*J53 -> 0 | Y53: =K53*B53 -> 0 | Z53: =B53*L53 -> 0 | AA53: =B53*M53 -> 0 | AB53: =B53*N53 -> 0
A54: CB Wash 100ml | B54: 199 | C54: ='COMMON ROOM'!C54+'COMMON ROOM'!O54+'COMMON ROOM'!AA54+'COMMON ROOM'!AM54+'COMMON ROOM'!AY54 -> 0 | D54: ='COMMON ROOM'!D54+'COMMON ROOM'!P54+'COMMON ROOM'!AB54+'COMMON ROOM'!AN54+'COMMON ROOM'!AZ54 -> 0 | E54: ='COMMON ROOM'!E54+'COMMON ROOM'!Q54+'COMMON ROOM'!AC54+'COMMON ROOM'!AO54+'COMMON ROOM'!BA54 -> 0 | F54: ='COMMON ROOM'!F54+'COMMON ROOM'!R54+'COMMON ROOM'!AD54+'COMMON ROOM'!AP54+'COMMON ROOM'!BB54 -> 0 | Q54: =B54*C54 -> 0 | R54: =B54*D54 -> 0 | S54: =B54*E54 -> 0 | T54: =B54*F54 -> 0 | U54: =B54*G54 -> 0 | V54: =B54*H54 -> 0 | W54: =B54*I54 -> 0 | X54: =B54*J54 -> 0 | Y54: =K54*B54 -> 0 | Z54: =B54*L54 -> 0 | AA54: =B54*M54 -> 0 | AB54: =B54*N54 -> 0
A55: Travel With Me | B55: 599 | C55: ='COMMON ROOM'!C55+'COMMON ROOM'!O55+'COMMON ROOM'!AA55+'COMMON ROOM'!AM55+'COMMON ROOM'!AY55 -> 0 | D55: ='COMMON ROOM'!D55+'COMMON ROOM'!P55+'COMMON ROOM'!AB55+'COMMON ROOM'!AN55+'COMMON ROOM'!AZ55 -> 0 | E55: ='COMMON ROOM'!E55+'COMMON ROOM'!Q55+'COMMON ROOM'!AC55+'COMMON ROOM'!AO55+'COMMON ROOM'!BA55 -> 0 | F55: ='COMMON ROOM'!F55+'COMMON ROOM'!R55+'COMMON ROOM'!AD55+'COMMON ROOM'!AP55+'COMMON ROOM'!BB55 -> 0 | Q55: =B55*C55 -> 0 | R55: =B55*D55 -> 0 | S55: =B55*E55 -> 0 | T55: =B55*F55 -> 0 | U55: =B55*G55 -> 0 | V55: =B55*H55 -> 0 | W55: =B55*I55 -> 0 | X55: =B55*J55 -> 0 | Y55: =K55*B55 -> 0 | Z55: =B55*L55 -> 0 | AA55: =B55*M55 -> 0 | AB55: =B55*N55 -> 0
A56: Handwash: Relaxing Naturals Gallon | B56: 1499 | C56: ='COMMON ROOM'!C56+'COMMON ROOM'!O56+'COMMON ROOM'!AA56+'COMMON ROOM'!AM56+'COMMON ROOM'!AY56 -> 0 | D56: ='COMMON ROOM'!D56+'COMMON ROOM'!P56+'COMMON ROOM'!AB56+'COMMON ROOM'!AN56+'COMMON ROOM'!AZ56 -> 0 | E56: ='COMMON ROOM'!E56+'COMMON ROOM'!Q56+'COMMON ROOM'!AC56+'COMMON ROOM'!AO56+'COMMON ROOM'!BA56 -> 0 | F56: ='COMMON ROOM'!F56+'COMMON ROOM'!R56+'COMMON ROOM'!AD56+'COMMON ROOM'!AP56+'COMMON ROOM'!BB56 -> 0 | Q56: =B56*C56 -> 0 | R56: =B56*D56 -> 0 | S56: =B56*E56 -> 0 | T56: =B56*F56 -> 0 | U56: =B56*G56 -> 0 | V56: =B56*H56 -> 0 | W56: =B56*I56 -> 0 | X56: =B56*J56 -> 0 | Y56: =K56*B56 -> 0 | Z56: =B56*L56 -> 0 | AA56: =B56*M56 -> 0 | AB56: =B56*N56 -> 0
C57: ='COMMON ROOM'!C57+'COMMON ROOM'!O57+'COMMON ROOM'!AA57+'COMMON ROOM'!AM57+'COMMON ROOM'!AY57 -> 0 | D57: ='COMMON ROOM'!D57+'COMMON ROOM'!P57+'COMMON ROOM'!AB57+'COMMON ROOM'!AN57+'COMMON ROOM'!AZ57 -> 0 | E57: ='COMMON ROOM'!E57+'COMMON ROOM'!Q57+'COMMON ROOM'!AC57+'COMMON ROOM'!AO57+'COMMON ROOM'!BA57 -> 0 | F57: ='COMMON ROOM'!F57+'COMMON ROOM'!R57+'COMMON ROOM'!AD57+'COMMON ROOM'!AP57+'COMMON ROOM'!BB57 -> 0 | Q57: =B57*C57 -> 0 | R57: =B57*D57 -> 0 | S57: =B57*E57 -> 0 | T57: =B57*F57 -> 0 | U57: =B57*G57 -> 0 | V57: =B57*H57 -> 0 | W57: =B57*I57 -> 0 | X57: =B57*J57 -> 0 | Y57: =K57*B57 -> 0 | Z57: =B57*L57 -> 0 | AA57: =B57*M57 -> 0 | AB57: =B57*N57 -> 0
A58: Creamy Matcha | B58: 349 | C58: ='COMMON ROOM'!C58+'COMMON ROOM'!O58+'COMMON ROOM'!AA58+'COMMON ROOM'!AM58+'COMMON ROOM'!AY58 -> 7 | D58: ='COMMON ROOM'!D58+'COMMON ROOM'!P58+'COMMON ROOM'!AB58+'COMMON ROOM'!AN58+'COMMON ROOM'!AZ58 -> 9 | E58: ='COMMON ROOM'!E58+'COMMON ROOM'!Q58+'COMMON ROOM'!AC58+'COMMON ROOM'!AO58+'COMMON ROOM'!BA58 -> 5 | F58: ='COMMON ROOM'!F58+'COMMON ROOM'!R58+'COMMON ROOM'!AD58+'COMMON ROOM'!AP58+'COMMON ROOM'!BB58 -> 1 | Q58: =B58*C58 -> 2443 | R58: =B58*D58 -> 3141 | S58: =B58*E58 -> 1745 | T58: =B58*F58 -> 349 | U58: =B58*G58 -> 0 | V58: =B58*H58 -> 0 | W58: =B58*I58 -> 0 | X58: =B58*J58 -> 0 | Y58: =K58*B58 -> 0 | Z58: =B58*L58 -> 0 | AA58: =B58*M58 -> 0 | AB58: =B58*N58 -> 0
A59: White Lavender | B59: 349 | C59: ='COMMON ROOM'!C59+'COMMON ROOM'!O59+'COMMON ROOM'!AA59+'COMMON ROOM'!AM59+'COMMON ROOM'!AY59 -> 12 | D59: ='COMMON ROOM'!D59+'COMMON ROOM'!P59+'COMMON ROOM'!AB59+'COMMON ROOM'!AN59+'COMMON ROOM'!AZ59 -> 10 | E59: ='COMMON ROOM'!E59+'COMMON ROOM'!Q59+'COMMON ROOM'!AC59+'COMMON ROOM'!AO59+'COMMON ROOM'!BA59 -> 7 | F59: ='COMMON ROOM'!F59+'COMMON ROOM'!R59+'COMMON ROOM'!AD59+'COMMON ROOM'!AP59+'COMMON ROOM'!BB59 -> 4 | Q59: =B59*C59 -> 4188 | R59: =B59*D59 -> 3490 | S59: =B59*E59 -> 2443 | T59: =B59*F59 -> 1396 | U59: =B59*G59 -> 0 | V59: =B59*H59 -> 0 | W59: =B59*I59 -> 0 | X59: =B59*J59 -> 0 | Y59: =K59*B59 -> 0 | Z59: =B59*L59 -> 0 | AA59: =B59*M59 -> 0 | AB59: =B59*N59 -> 0
A60: Green Tea | B60: 349 | C60: ='COMMON ROOM'!C60+'COMMON ROOM'!O60+'COMMON ROOM'!AA60+'COMMON ROOM'!AM60+'COMMON ROOM'!AY60 -> 20 | D60: ='COMMON ROOM'!D60+'COMMON ROOM'!P60+'COMMON ROOM'!AB60+'COMMON ROOM'!AN60+'COMMON ROOM'!AZ60 -> 21 | E60: ='COMMON ROOM'!E60+'COMMON ROOM'!Q60+'COMMON ROOM'!AC60+'COMMON ROOM'!AO60+'COMMON ROOM'!BA60 -> 11 | F60: ='COMMON ROOM'!F60+'COMMON ROOM'!R60+'COMMON ROOM'!AD60+'COMMON ROOM'!AP60+'COMMON ROOM'!BB60 -> 4 | Q60: =B60*C60 -> 6980 | R60: =B60*D60 -> 7329 | S60: =B60*E60 -> 3839 | T60: =B60*F60 -> 1396 | U60: =B60*G60 -> 0 | V60: =B60*H60 -> 0 | W60: =B60*I60 -> 0 | X60: =B60*J60 -> 0 | Y60: =K60*B60 -> 0 | Z60: =B60*L60 -> 0 | AA60: =B60*M60 -> 0 | AB60: =B60*N60 -> 0
A61: Clean Air 100ml | B61: 269 | C61: ='COMMON ROOM'!C61+'COMMON ROOM'!O61+'COMMON ROOM'!AA61+'COMMON ROOM'!AM61+'COMMON ROOM'!AY61 -> 2 | D61: ='COMMON ROOM'!D61+'COMMON ROOM'!P61+'COMMON ROOM'!AB61+'COMMON ROOM'!AN61+'COMMON ROOM'!AZ61 -> 4 | E61: ='COMMON ROOM'!E61+'COMMON ROOM'!Q61+'COMMON ROOM'!AC61+'COMMON ROOM'!AO61+'COMMON ROOM'!BA61 -> 4 | F61: ='COMMON ROOM'!F61+'COMMON ROOM'!R61+'COMMON ROOM'!AD61+'COMMON ROOM'!AP61+'COMMON ROOM'!BB61 -> 0 | Q61: =B61*C61 -> 538 | R61: =B61*D61 -> 1076 | S61: =B61*E61 -> 1076 | T61: =B61*F61 -> 0 | U61: =B61*G61 -> 0 | V61: =B61*H61 -> 0 | W61: =B61*I61 -> 0 | X61: =B61*J61 -> 0 | Y61: =K61*B61 -> 0 | Z61: =B61*L61 -> 0 | AA61: =B61*M61 -> 0 | AB61: =B61*N61 -> 0
A62: Creamy Matcha Diffuser Refill | B62: 459 | C62: ='COMMON ROOM'!C62+'COMMON ROOM'!O62+'COMMON ROOM'!AA62+'COMMON ROOM'!AM62+'COMMON ROOM'!AY62 -> 2 | D62: ='COMMON ROOM'!D62+'COMMON ROOM'!P62+'COMMON ROOM'!AB62+'COMMON ROOM'!AN62+'COMMON ROOM'!AZ62 -> 0 | E62: ='COMMON ROOM'!E62+'COMMON ROOM'!Q62+'COMMON ROOM'!AC62+'COMMON ROOM'!AO62+'COMMON ROOM'!BA62 -> 1 | F62: ='COMMON ROOM'!F62+'COMMON ROOM'!R62+'COMMON ROOM'!AD62+'COMMON ROOM'!AP62+'COMMON ROOM'!BB62 -> 0 | Q62: =B62*C62 -> 918 | R62: =B62*D62 -> 0 | S62: =B62*E62 -> 459 | T62: =B62*F62 -> 0 | U62: =B62*G62 -> 0 | V62: =B62*H62 -> 0 | W62: =B62*I62 -> 0 | X62: =B62*J62 -> 0 | Y62: =K62*B62 -> 0 | Z62: =B62*L62 -> 0 | AA62: =B62*M62 -> 0 | AB62: =B62*N62 -> 0
A63: White Lavender Diffuser Refill | B63: 459 | C63: ='COMMON ROOM'!C63+'COMMON ROOM'!O63+'COMMON ROOM'!AA63+'COMMON ROOM'!AM63+'COMMON ROOM'!AY63 -> 5 | D63: ='COMMON ROOM'!D63+'COMMON ROOM'!P63+'COMMON ROOM'!AB63+'COMMON ROOM'!AN63+'COMMON ROOM'!AZ63 -> 1 | E63: ='COMMON ROOM'!E63+'COMMON ROOM'!Q63+'COMMON ROOM'!AC63+'COMMON ROOM'!AO63+'COMMON ROOM'!BA63 -> 3 | F63: ='COMMON ROOM'!F63+'COMMON ROOM'!R63+'COMMON ROOM'!AD63+'COMMON ROOM'!AP63+'COMMON ROOM'!BB63 -> 2 | Q63: =B63*C63 -> 2295 | R63: =B63*D63 -> 459 | S63: =B63*E63 -> 1377 | T63: =B63*F63 -> 918 | U63: =B63*G63 -> 0 | V63: =B63*H63 -> 0 | W63: =B63*I63 -> 0 | X63: =B63*J63 -> 0 | Y63: =K63*B63 -> 0 | Z63: =B63*L63 -> 0 | AA63: =B63*M63 -> 0 | AB63: =B63*N63 -> 0
A64: Green Tea Diffuser Refill | B64: 459 | C64: ='COMMON ROOM'!C64+'COMMON ROOM'!O64+'COMMON ROOM'!AA64+'COMMON ROOM'!AM64+'COMMON ROOM'!AY64 -> 1 | D64: ='COMMON ROOM'!D64+'COMMON ROOM'!P64+'COMMON ROOM'!AB64+'COMMON ROOM'!AN64+'COMMON ROOM'!AZ64 -> 4 | E64: ='COMMON ROOM'!E64+'COMMON ROOM'!Q64+'COMMON ROOM'!AC64+'COMMON ROOM'!AO64+'COMMON ROOM'!BA64 -> 0 | F64: ='COMMON ROOM'!F64+'COMMON ROOM'!R64+'COMMON ROOM'!AD64+'COMMON ROOM'!AP64+'COMMON ROOM'!BB64 -> 1 | Q64: =B64*C64 -> 459 | R64: =B64*D64 -> 1836 | S64: =B64*E64 -> 0 | T64: =B64*F64 -> 459 | U64: =B64*G64 -> 0 | V64: =B64*H64 -> 0 | W64: =B64*I64 -> 0 | X64: =B64*J64 -> 0 | Y64: =K64*B64 -> 0 | Z64: =B64*L64 -> 0 | AA64: =B64*M64 -> 0 | AB64: =B64*N64 -> 0
A65: Creamy Matcha Diffuser | B65: 799 | C65: ='COMMON ROOM'!C65+'COMMON ROOM'!O65+'COMMON ROOM'!AA65+'COMMON ROOM'!AM65+'COMMON ROOM'!AY65 -> 0 | D65: ='COMMON ROOM'!D65+'COMMON ROOM'!P65+'COMMON ROOM'!AB65+'COMMON ROOM'!AN65+'COMMON ROOM'!AZ65 -> 0 | E65: ='COMMON ROOM'!E65+'COMMON ROOM'!Q65+'COMMON ROOM'!AC65+'COMMON ROOM'!AO65+'COMMON ROOM'!BA65 -> 0 | F65: ='COMMON ROOM'!F65+'COMMON ROOM'!R65+'COMMON ROOM'!AD65+'COMMON ROOM'!AP65+'COMMON ROOM'!BB65 -> 0 | Q65: =B65*C65 -> 0 | R65: =B65*D65 -> 0 | S65: =B65*E65 -> 0 | T65: =B65*F65 -> 0 | U65: =B65*G65 -> 0 | V65: =B65*H65 -> 0 | W65: =B65*I65 -> 0 | X65: =B65*J65 -> 0 | Y65: =K65*B65 -> 0 | Z65: =B65*L65 -> 0 | AA65: =B65*M65 -> 0 | AB65: =B65*N65 -> 0
A66: White Lavender Diffuser | B66: 799 | C66: ='COMMON ROOM'!C66+'COMMON ROOM'!O66+'COMMON ROOM'!AA66+'COMMON ROOM'!AM66+'COMMON ROOM'!AY66 -> 0 | D66: ='COMMON ROOM'!D66+'COMMON ROOM'!P66+'COMMON ROOM'!AB66+'COMMON ROOM'!AN66+'COMMON ROOM'!AZ66 -> 0 | E66: ='COMMON ROOM'!E66+'COMMON ROOM'!Q66+'COMMON ROOM'!AC66+'COMMON ROOM'!AO66+'COMMON ROOM'!BA66 -> 0 | F66: ='COMMON ROOM'!F66+'COMMON ROOM'!R66+'COMMON ROOM'!AD66+'COMMON ROOM'!AP66+'COMMON ROOM'!BB66 -> 0 | Q66: =B66*C66 -> 0 | R66: =B66*D66 -> 0 | S66: =B66*E66 -> 0 | T66: =B66*F66 -> 0 | U66: =B66*G66 -> 0 | V66: =B66*H66 -> 0 | W66: =B66*I66 -> 0 | X66: =B66*J66 -> 0 | Y66: =K66*B66 -> 0 | Z66: =B66*L66 -> 0 | AA66: =B66*M66 -> 0 | AB66: =B66*N66 -> 0
A67: Green Tea Diffuser | B67: 799 | C67: ='COMMON ROOM'!C67+'COMMON ROOM'!O67+'COMMON ROOM'!AA67+'COMMON ROOM'!AM67+'COMMON ROOM'!AY67 -> 0 | D67: ='COMMON ROOM'!D67+'COMMON ROOM'!P67+'COMMON ROOM'!AB67+'COMMON ROOM'!AN67+'COMMON ROOM'!AZ67 -> 0 | E67: ='COMMON ROOM'!E67+'COMMON ROOM'!Q67+'COMMON ROOM'!AC67+'COMMON ROOM'!AO67+'COMMON ROOM'!BA67 -> 0 | F67: ='COMMON ROOM'!F67+'COMMON ROOM'!R67+'COMMON ROOM'!AD67+'COMMON ROOM'!AP67+'COMMON ROOM'!BB67 -> 0 | Q67: =B67*C67 -> 0 | R67: =B67*D67 -> 0 | S67: =B67*E67 -> 0 | T67: =B67*F67 -> 0 | U67: =B67*G67 -> 0 | V67: =B67*H67 -> 0 | W67: =B67*I67 -> 0 | X67: =B67*J67 -> 0 | Y67: =K67*B67 -> 0 | Z67: =B67*L67 -> 0 | AA67: =B67*M67 -> 0 | AB67: =B67*N67 -> 0
A68: Creamy Matcha + Roomspray | B68: 1299 | C68: ='COMMON ROOM'!C68+'COMMON ROOM'!O68+'COMMON ROOM'!AA68+'COMMON ROOM'!AM68+'COMMON ROOM'!AY68 -> 0 | D68: ='COMMON ROOM'!D68+'COMMON ROOM'!P68+'COMMON ROOM'!AB68+'COMMON ROOM'!AN68+'COMMON ROOM'!AZ68 -> 0 | E68: ='COMMON ROOM'!E68+'COMMON ROOM'!Q68+'COMMON ROOM'!AC68+'COMMON ROOM'!AO68+'COMMON ROOM'!BA68 -> 0 | F68: ='COMMON ROOM'!F68+'COMMON ROOM'!R68+'COMMON ROOM'!AD68+'COMMON ROOM'!AP68+'COMMON ROOM'!BB68 -> 0 | Q68: =B68*C68 -> 0 | R68: =B68*D68 -> 0 | S68: =B68*E68 -> 0 | T68: =B68*F68 -> 0 | U68: =B68*G68 -> 0 | V68: =B68*H68 -> 0 | W68: =B68*I68 -> 0 | X68: =B68*J68 -> 0 | Y68: =K68*B68 -> 0 | Z68: =B68*L68 -> 0 | AA68: =B68*M68 -> 0 | AB68: =B68*N68 -> 0
A69: White Lavender + Roomspray | B69: 1299 | C69: ='COMMON ROOM'!C69+'COMMON ROOM'!O69+'COMMON ROOM'!AA69+'COMMON ROOM'!AM69+'COMMON ROOM'!AY69 -> 0 | D69: ='COMMON ROOM'!D69+'COMMON ROOM'!P69+'COMMON ROOM'!AB69+'COMMON ROOM'!AN69+'COMMON ROOM'!AZ69 -> 0 | E69: ='COMMON ROOM'!E69+'COMMON ROOM'!Q69+'COMMON ROOM'!AC69+'COMMON ROOM'!AO69+'COMMON ROOM'!BA69 -> 0 | F69: ='COMMON ROOM'!F69+'COMMON ROOM'!R69+'COMMON ROOM'!AD69+'COMMON ROOM'!AP69+'COMMON ROOM'!BB69 -> 0 | Q69: =B69*C69 -> 0 | R69: =B69*D69 -> 0 | S69: =B69*E69 -> 0 | T69: =B69*F69 -> 0 | U69: =B69*G69 -> 0 | V69: =B69*H69 -> 0 | W69: =B69*I69 -> 0 | X69: =B69*J69 -> 0 | Y69: =K69*B69 -> 0 | Z69: =B69*L69 -> 0 | AA69: =B69*M69 -> 0 | AB69: =B69*N69 -> 0
... A74: Urban Oasis Reed Diffuser | B74: 1619 | C74: ='COMMON ROOM'!C74+'COMMON ROOM'!O74+'COMMON ROOM'!AA74+'COMMON ROOM'!AM74+'COMMON ROOM'!AY74 -> 2 | D74: ='COMMON ROOM'!D74+'COMMON ROOM'!P74+'COMMON ROOM'!AB74+'COMMON ROOM'!AN74+'COMMON ROOM'!AZ74 -> 3 | E74: ='COMMON ROOM'!E74+'COMMON ROOM'!Q74+'COMMON ROOM'!AC74+'COMMON ROOM'!AO74+'COMMON ROOM'!BA74 -> 0 | F74: ='COMMON ROOM'!F74+'COMMON ROOM'!R74+'COMMON ROOM'!AD74+'COMMON ROOM'!AP74+'COMMON ROOM'!BB74 -> 0 | Q74: =B74*C74 -> 3238 | R74: =B74*D74 -> 4857 | S74: =B74*E74 -> 0 | T74: =B74*F74 -> 0 | U74: =B74*G74 -> 0 | V74: =B74*H74 -> 0 | W74: =B74*I74 -> 0 | X74: =B74*J74 -> 0 | Y74: =K74*B74 -> 0 | Z74: =B74*L74 -> 0 | AA74: =B74*M74 -> 0 | AB74: =B74*N74 -> 0
A75: Clean Air Gallon | C75: ='COMMON ROOM'!C75+'COMMON ROOM'!O75+'COMMON ROOM'!AA75+'COMMON ROOM'!AM75+'COMMON ROOM'!AY75 -> 2 | D75: ='COMMON ROOM'!D75+'COMMON ROOM'!P75+'COMMON ROOM'!AB75+'COMMON ROOM'!AN75+'COMMON ROOM'!AZ75 -> 0 | E75: ='COMMON ROOM'!E75+'COMMON ROOM'!Q75+'COMMON ROOM'!AC75+'COMMON ROOM'!AO75+'COMMON ROOM'!BA75 -> 0 | F75: ='COMMON ROOM'!F75+'COMMON ROOM'!R75+'COMMON ROOM'!AD75+'COMMON ROOM'!AP75+'COMMON ROOM'!BB75 -> 0 | Q75: =B75*C75 -> 0 | R75: =B75*D75 -> 0 | S75: =B75*E75 -> 0 | T75: =B75*F75 -> 0 | U75: =B75*G75 -> 0 | V75: =B75*H75 -> 0 | W75: =B75*I75 -> 0 | X75: =B75*J75 -> 0 | Y75: =K75*B75 -> 0 | Z75: =B75*L75 -> 0 | AA75: =B75*M75 -> 0 | AB75: =B75*N75 -> 0
C76: ='COMMON ROOM'!C76+'COMMON ROOM'!O76+'COMMON ROOM'!AA76+'COMMON ROOM'!AM76+'COMMON ROOM'!AY76 -> 0 | D76: ='COMMON ROOM'!D76+'COMMON ROOM'!P76+'COMMON ROOM'!AB76+'COMMON ROOM'!AN76+'COMMON ROOM'!AZ76 -> 0 | E76: ='COMMON ROOM'!E76+'COMMON ROOM'!Q76+'COMMON ROOM'!AC76+'COMMON ROOM'!AO76+'COMMON ROOM'!BA76 -> 0 | F76: ='COMMON ROOM'!F76+'COMMON ROOM'!R76+'COMMON ROOM'!AD76+'COMMON ROOM'!AP76+'COMMON ROOM'!BB76 -> 0 | Q76: =B76*C76 -> 0 | R76: =B76*D76 -> 0 | S76: =B76*E76 -> 0 | T76: =B76*F76 -> 0 | U76: =B76*G76 -> 0 | V76: =B76*H76 -> 0 | W76: =B76*I76 -> 0 | X76: =B76*J76 -> 0 | Y76: =K76*B76 -> 0 | Z76: =B76*L76 -> 0 | AA76: =B76*M76 -> 0 | AB76: =B76*N76 -> 0
A77: Holiday Hugs 200ml | B77: 399 | C77: ='COMMON ROOM'!C77+'COMMON ROOM'!O77+'COMMON ROOM'!AA77+'COMMON ROOM'!AM77+'COMMON ROOM'!AY77 -> 1 | D77: ='COMMON ROOM'!D77+'COMMON ROOM'!P77+'COMMON ROOM'!AB77+'COMMON ROOM'!AN77+'COMMON ROOM'!AZ77 -> 1 | E77: ='COMMON ROOM'!E77+'COMMON ROOM'!Q77+'COMMON ROOM'!AC77+'COMMON ROOM'!AO77+'COMMON ROOM'!BA77 -> 0 | F77: ='COMMON ROOM'!F77+'COMMON ROOM'!R77+'COMMON ROOM'!AD77+'COMMON ROOM'!AP77+'COMMON ROOM'!BB77 -> 0 | Q77: =B77*C77 -> 399 | R77: =B77*D77 -> 399 | S77: =B77*E77 -> 0 | T77: =B77*F77 -> 0 | U77: =B77*G77 -> 0 | V77: =B77*H77 -> 0 | W77: =B77*I77 -> 0 | X77: =B77*J77 -> 0 | Y77: =K77*B77 -> 0 | Z77: =B77*L77 -> 0 | AA77: =B77*M77 -> 0 | AB77: =B77*N77 -> 0
A78: Holiday Hugs Diffuser Set | B78: 799 | C78: ='COMMON ROOM'!C78+'COMMON ROOM'!O78+'COMMON ROOM'!AA78+'COMMON ROOM'!AM78+'COMMON ROOM'!AY78 -> 0 | D78: ='COMMON ROOM'!D78+'COMMON ROOM'!P78+'COMMON ROOM'!AB78+'COMMON ROOM'!AN78+'COMMON ROOM'!AZ78 -> 0 | E78: ='COMMON ROOM'!E78+'COMMON ROOM'!Q78+'COMMON ROOM'!AC78+'COMMON ROOM'!AO78+'COMMON ROOM'!BA78 -> 0 | F78: ='COMMON ROOM'!F78+'COMMON ROOM'!R78+'COMMON ROOM'!AD78+'COMMON ROOM'!AP78+'COMMON ROOM'!BB78 -> 0 | Q78: =B78*C78 -> 0 | R78: =B78*D78 -> 0 | S78: =B78*E78 -> 0 | T78: =B78*F78 -> 0 | U78: =B78*G78 -> 0 | V78: =B78*H78 -> 0 | W78: =B78*I78 -> 0 | X78: =B78*J78 -> 0 | Y78: =K78*B78 -> 0 | Z78: =B78*L78 -> 0 | AA78: =B78*M78 -> 0 | AB78: =B78*N78 -> 0
A79: Holiday Hugs Refill | B79: 459 | C79: ='COMMON ROOM'!C79+'COMMON ROOM'!O79+'COMMON ROOM'!AA79+'COMMON ROOM'!AM79+'COMMON ROOM'!AY79 -> 2 | D79: ='COMMON ROOM'!D79+'COMMON ROOM'!P79+'COMMON ROOM'!AB79+'COMMON ROOM'!AN79+'COMMON ROOM'!AZ79 -> 0 | E79: ='COMMON ROOM'!E79+'COMMON ROOM'!Q79+'COMMON ROOM'!AC79+'COMMON ROOM'!AO79+'COMMON ROOM'!BA79 -> 0 | F79: ='COMMON ROOM'!F79+'COMMON ROOM'!R79+'COMMON ROOM'!AD79+'COMMON ROOM'!AP79+'COMMON ROOM'!BB79 -> 1 | Q79: =B79*C79 -> 918 | R79: =B79*D79 -> 0 | S79: =B79*E79 -> 0 | T79: =B79*F79 -> 459 | U79: =B79*G79 -> 0 | V79: =B79*H79 -> 0 | W79: =B79*I79 -> 0 | X79: =B79*J79 -> 0 | Y79: =K79*B79 -> 0 | Z79: =B79*L79 -> 0 | AA79: =B79*M79 -> 0 | AB79: =B79*N79 -> 0
A80: Bathroom Kit | B80: 599 | C80: ='COMMON ROOM'!C80+'COMMON ROOM'!O80+'COMMON ROOM'!AA80+'COMMON ROOM'!AM80+'COMMON ROOM'!AY80 -> 0 | D80: ='COMMON ROOM'!D80+'COMMON ROOM'!P80+'COMMON ROOM'!AB80+'COMMON ROOM'!AN80+'COMMON ROOM'!AZ80 -> 0 | E80: ='COMMON ROOM'!E80+'COMMON ROOM'!Q80+'COMMON ROOM'!AC80+'COMMON ROOM'!AO80+'COMMON ROOM'!BA80 -> 0 | F80: ='COMMON ROOM'!F80+'COMMON ROOM'!R80+'COMMON ROOM'!AD80+'COMMON ROOM'!AP80+'COMMON ROOM'!BB80 -> 0 | Q80: =B80*C80 -> 0 | R80: =B80*D80 -> 0 | S80: =B80*E80 -> 0 | T80: =B80*F80 -> 0 | U80: =B80*G80 -> 0 | V80: =B80*H80 -> 0 | W80: =B80*I80 -> 0 | X80: =B80*J80 -> 0 | Y80: =K80*B80 -> 0 | Z80: =B80*L80 -> 0 | AA80: =B80*M80 -> 0 | AB80: =B80*N80 -> 0
A81: Flushie 50ml | B81: 249 | C81: ='COMMON ROOM'!C81+'COMMON ROOM'!O81+'COMMON ROOM'!AA81+'COMMON ROOM'!AM81+'COMMON ROOM'!AY81 -> 8 | D81: ='COMMON ROOM'!D81+'COMMON ROOM'!P81+'COMMON ROOM'!AB81+'COMMON ROOM'!AN81+'COMMON ROOM'!AZ81 -> 1 | E81: ='COMMON ROOM'!E81+'COMMON ROOM'!Q81+'COMMON ROOM'!AC81+'COMMON ROOM'!AO81+'COMMON ROOM'!BA81 -> 2 | F81: ='COMMON ROOM'!F81+'COMMON ROOM'!R81+'COMMON ROOM'!AD81+'COMMON ROOM'!AP81+'COMMON ROOM'!BB81 -> 3 | Q81: =B81*C81 -> 1992 | R81: =B81*D81 -> 249 | S81: =B81*E81 -> 498 | T81: =B81*F81 -> 747 | U81: =B81*G81 -> 0 | V81: =B81*H81 -> 0 | W81: =B81*I81 -> 0 | X81: =B81*J81 -> 0 | Y81: =K81*B81 -> 0 | Z81: =B81*L81 -> 0 | AA81: =B81*M81 -> 0 | AB81: =B81*N81 -> 0
A82: Easy Drive Grapefuit | B82: 239 | C82: ='COMMON ROOM'!C82+'COMMON ROOM'!O82+'COMMON ROOM'!AA82+'COMMON ROOM'!AM82+'COMMON ROOM'!AY82 -> 0 | D82: ='COMMON ROOM'!D82+'COMMON ROOM'!P82+'COMMON ROOM'!AB82+'COMMON ROOM'!AN82+'COMMON ROOM'!AZ82 -> 1 | E82: ='COMMON ROOM'!E82+'COMMON ROOM'!Q82+'COMMON ROOM'!AC82+'COMMON ROOM'!AO82+'COMMON ROOM'!BA82 -> 1 | F82: ='COMMON ROOM'!F82+'COMMON ROOM'!R82+'COMMON ROOM'!AD82+'COMMON ROOM'!AP82+'COMMON ROOM'!BB82 -> 0 | Q82: =B82*C82 -> 0 | R82: =B82*D82 -> 239 | S82: =B82*E82 -> 239 | T82: =B82*F82 -> 0 | U82: =B82*G82 -> 0 | V82: =B82*H82 -> 0 | W82: =B82*I82 -> 0 | X82: =B82*J82 -> 0 | Y82: =K82*B82 -> 0 | Z82: =B82*L82 -> 0 | AA82: =B82*M82 -> 0 | AB82: =B82*N82 -> 0
A83: Fresh Bamboo Diffuser + Roomspray | B83: 1299 | C83: ='COMMON ROOM'!C83+'COMMON ROOM'!O83+'COMMON ROOM'!AA83+'COMMON ROOM'!AM83+'COMMON ROOM'!AY83 -> 0 | D83: ='COMMON ROOM'!D83+'COMMON ROOM'!P83+'COMMON ROOM'!AB83+'COMMON ROOM'!AN83+'COMMON ROOM'!AZ83 -> 0 | E83: ='COMMON ROOM'!E83+'COMMON ROOM'!Q83+'COMMON ROOM'!AC83+'COMMON ROOM'!AO83+'COMMON ROOM'!BA83 -> 0 | F83: ='COMMON ROOM'!F83+'COMMON ROOM'!R83+'COMMON ROOM'!AD83+'COMMON ROOM'!AP83+'COMMON ROOM'!BB83 -> 0 | Q83: =B83*C83 -> 0 | R83: =B83*D83 -> 0 | S83: =B83*E83 -> 0 | T83: =B83*F83 -> 0 | U83: =B83*G83 -> 0 | V83: =B83*H83 -> 0 | W83: =B83*I83 -> 0 | X83: =B83*J83 -> 0 | Y83: =K83*B83 -> 0 | Z83: =B83*L83 -> 0 | AA83: =B83*M83 -> 0 | AB83: =B83*N83 -> 0
A84: White Tea Diffuser + Roomspray | B84: 1299 | C84: ='COMMON ROOM'!C84+'COMMON ROOM'!O84+'COMMON ROOM'!AA84+'COMMON ROOM'!AM84+'COMMON ROOM'!AY84 -> 0 | D84: ='COMMON ROOM'!D84+'COMMON ROOM'!P84+'COMMON ROOM'!AB84+'COMMON ROOM'!AN84+'COMMON ROOM'!AZ84 -> 0 | E84: ='COMMON ROOM'!E84+'COMMON ROOM'!Q84+'COMMON ROOM'!AC84+'COMMON ROOM'!AO84+'COMMON ROOM'!BA84 -> 0 | F84: ='COMMON ROOM'!F84+'COMMON ROOM'!R84+'COMMON ROOM'!AD84+'COMMON ROOM'!AP84+'COMMON ROOM'!BB84 -> 0 | Q84: =B84*C84 -> 0 | R84: =B84*D84 -> 0 | S84: =B84*E84 -> 0 | T84: =B84*F84 -> 0 | U84: =B84*G84 -> 0 | V84: =B84*H84 -> 0 | W84: =B84*I84 -> 0 | X84: =B84*J84 -> 0 | Y84: =K84*B84 -> 0 | Z84: =B84*L84 -> 0 | AA84: =B84*M84 -> 0 | AB84: =B84*N84 -> 0
A85: Cotton Clean Diffuser + Roomspray | B85: 1299 | C85: ='COMMON ROOM'!C85+'COMMON ROOM'!O85+'COMMON ROOM'!AA85+'COMMON ROOM'!AM85+'COMMON ROOM'!AY85 -> 0 | D85: ='COMMON ROOM'!D85+'COMMON ROOM'!P85+'COMMON ROOM'!AB85+'COMMON ROOM'!AN85+'COMMON ROOM'!AZ85 -> 0 | E85: ='COMMON ROOM'!E85+'COMMON ROOM'!Q85+'COMMON ROOM'!AC85+'COMMON ROOM'!AO85+'COMMON ROOM'!BA85 -> 0 | F85: ='COMMON ROOM'!F85+'COMMON ROOM'!R85+'COMMON ROOM'!AD85+'COMMON ROOM'!AP85+'COMMON ROOM'!BB85 -> 0 | Q85: =B85*C85 -> 0 | R85: =B85*D85 -> 0 | S85: =B85*E85 -> 0 | T85: =B85*F85 -> 0 | U85: =B85*G85 -> 0 | V85: =B85*H85 -> 0 | W85: =B85*I85 -> 0 | X85: =B85*J85 -> 0 | Y85: =K85*B85 -> 0 | Z85: =B85*L85 -> 0 | AA85: =B85*M85 -> 0 | AB85: =B85*N85 -> 0
A86: Holiday Hugs Diffuser + Roomspray | B86: 1299 | C86: ='COMMON ROOM'!C86+'COMMON ROOM'!O86+'COMMON ROOM'!AA86+'COMMON ROOM'!AM86+'COMMON ROOM'!AY86 -> 0 | D86: ='COMMON ROOM'!D86+'COMMON ROOM'!P86+'COMMON ROOM'!AB86+'COMMON ROOM'!AN86+'COMMON ROOM'!AZ86 -> 0 | E86: ='COMMON ROOM'!E86+'COMMON ROOM'!Q86+'COMMON ROOM'!AC86+'COMMON ROOM'!AO86+'COMMON ROOM'!BA86 -> 0 | F86: ='COMMON ROOM'!F86+'COMMON ROOM'!R86+'COMMON ROOM'!AD86+'COMMON ROOM'!AP86+'COMMON ROOM'!BB86 -> 0 | Q86: =B86*C86 -> 0 | R86: =B86*D86 -> 0 | S86: =B86*E86 -> 0 | T86: =B86*F86 -> 0 | U86: =B86*G86 -> 0 | V86: =B86*H86 -> 0 | W86: =B86*I86 -> 0 | X86: =B86*J86 -> 0 | Y86: =K86*B86 -> 0 | Z86: =B86*L86 -> 0 | AA86: =B86*M86 -> 0 | AB86: =B86*N86 -> 0
C87: ='COMMON ROOM'!C87+'COMMON ROOM'!O87+'COMMON ROOM'!AA87+'COMMON ROOM'!AM87+'COMMON ROOM'!AY87 -> 0 | D87: ='COMMON ROOM'!D87+'COMMON ROOM'!P87+'COMMON ROOM'!AB87+'COMMON ROOM'!AN87+'COMMON ROOM'!AZ87 -> 0 | E87: ='COMMON ROOM'!E87+'COMMON ROOM'!Q87+'COMMON ROOM'!AC87+'COMMON ROOM'!AO87+'COMMON ROOM'!BA87 -> 0 | F87: ='COMMON ROOM'!F87+'COMMON ROOM'!R87+'COMMON ROOM'!AD87+'COMMON ROOM'!AP87+'COMMON ROOM'!BB87 -> 0 | Q87: =B87*C87 -> 0 | R87: =B87*D87 -> 0 | S87: =B87*E87 -> 0 | T87: =B87*F87 -> 0 | U87: =B87*G87 -> 0 | V87: =B87*H87 -> 0 | W87: =B87*I87 -> 0 | X87: =B87*J87 -> 0 | Y87: =K87*B87 -> 0 | Z87: =B87*L87 -> 0 | AA87: =B87*M87 -> 0 | AB87: =B87*N87 -> 0
A88: Sleep All Day | B88: 679 | C88: ='COMMON ROOM'!C88+'COMMON ROOM'!O88+'COMMON ROOM'!AA88+'COMMON ROOM'!AM88+'COMMON ROOM'!AY88 -> 0 | D88: ='COMMON ROOM'!D88+'COMMON ROOM'!P88+'COMMON ROOM'!AB88+'COMMON ROOM'!AN88+'COMMON ROOM'!AZ88 -> 0 | E88: ='COMMON ROOM'!E88+'COMMON ROOM'!Q88+'COMMON ROOM'!AC88+'COMMON ROOM'!AO88+'COMMON ROOM'!BA88 -> 0 | F88: ='COMMON ROOM'!F88+'COMMON ROOM'!R88+'COMMON ROOM'!AD88+'COMMON ROOM'!AP88+'COMMON ROOM'!BB88 -> 0 | Q88: =B88*C88 -> 0 | R88: =B88*D88 -> 0 | S88: =B88*E88 -> 0 | T88: =B88*F88 -> 0 | U88: =B88*G88 -> 0 | V88: =B88*H88 -> 0 | W88: =B88*I88 -> 0 | X88: =B88*J88 -> 0 | Y88: =K88*B88 -> 0 | Z88: =B88*L88 -> 0 | AA88: =B88*M88 -> 0 | AB88: =B88*N88 -> 0
A89: One Way Ticket | B89: 679 | C89: ='COMMON ROOM'!C89+'COMMON ROOM'!O89+'COMMON ROOM'!AA89+'COMMON ROOM'!AM89+'COMMON ROOM'!AY89 -> 0 | D89: ='COMMON ROOM'!D89+'COMMON ROOM'!P89+'COMMON ROOM'!AB89+'COMMON ROOM'!AN89+'COMMON ROOM'!AZ89 -> 0 | E89: ='COMMON ROOM'!E89+'COMMON ROOM'!Q89+'COMMON ROOM'!AC89+'COMMON ROOM'!AO89+'COMMON ROOM'!BA89 -> 0 | F89: ='COMMON ROOM'!F89+'COMMON ROOM'!R89+'COMMON ROOM'!AD89+'COMMON ROOM'!AP89+'COMMON ROOM'!BB89 -> 0 | Q89: =B89*C89 -> 0 | R89: =B89*D89 -> 0 | S89: =B89*E89 -> 0 | T89: =B89*F89 -> 0 | U89: =B89*G89 -> 0 | V89: =B89*H89 -> 0 | W89: =B89*I89 -> 0 | X89: =B89*J89 -> 0 | Y89: =K89*B89 -> 0 | Z89: =B89*L89 -> 0 | AA89: =B89*M89 -> 0 | AB89: =B89*N89 -> 0
A90: Holiday Cheer | B90: 679 | C90: ='COMMON ROOM'!C90+'COMMON ROOM'!O90+'COMMON ROOM'!AA90+'COMMON ROOM'!AM90+'COMMON ROOM'!AY90 -> 0 | D90: ='COMMON ROOM'!D90+'COMMON ROOM'!P90+'COMMON ROOM'!AB90+'COMMON ROOM'!AN90+'COMMON ROOM'!AZ90 -> 0 | E90: ='COMMON ROOM'!E90+'COMMON ROOM'!Q90+'COMMON ROOM'!AC90+'COMMON ROOM'!AO90+'COMMON ROOM'!BA90 -> 0 | F90: ='COMMON ROOM'!F90+'COMMON ROOM'!R90+'COMMON ROOM'!AD90+'COMMON ROOM'!AP90+'COMMON ROOM'!BB90 -> 0 | Q90: =B90*C90 -> 0 | R90: =B90*D90 -> 0 | S90: =B90*E90 -> 0 | T90: =B90*F90 -> 0 | U90: =B90*G90 -> 0 | V90: =B90*H90 -> 0 | W90: =B90*I90 -> 0 | X90: =B90*J90 -> 0 | Y90: =K90*B90 -> 0 | Z90: =B90*L90 -> 0 | AA90: =B90*M90 -> 0 | AB90: =B90*N90 -> 0
C91: ='COMMON ROOM'!C91+'COMMON ROOM'!O91+'COMMON ROOM'!AA91+'COMMON ROOM'!AM91+'COMMON ROOM'!AY91 -> 0 | D91: ='COMMON ROOM'!D91+'COMMON ROOM'!P91+'COMMON ROOM'!AB91+'COMMON ROOM'!AN91+'COMMON ROOM'!AZ91 -> 0 | E91: ='COMMON ROOM'!E91+'COMMON ROOM'!Q91+'COMMON ROOM'!AC91+'COMMON ROOM'!AO91+'COMMON ROOM'!BA91 -> 0 | F91: ='COMMON ROOM'!F91+'COMMON ROOM'!R91+'COMMON ROOM'!AD91+'COMMON ROOM'!AP91+'COMMON ROOM'!BB91 -> 0 | Q91: =B91*C91 -> 0 | R91: =B91*D91 -> 0 | S91: =B91*E91 -> 0 | T91: =B91*F91 -> 0 | U91: =B91*G91 -> 0 | V91: =B91*H91 -> 0 | W91: =B91*I91 -> 0 | X91: =B91*J91 -> 0 | Y91: =K91*B91 -> 0 | Z91: =B91*L91 -> 0 | AA91: =B91*M91 -> 0 | AB91: =B91*N91 -> 0
A92: High Enery Gift Set (Essential Oils) | B92: 490 | C92: ='COMMON ROOM'!C92+'COMMON ROOM'!O92+'COMMON ROOM'!AA92+'COMMON ROOM'!AM92+'COMMON ROOM'!AY92 -> 0 | D92: ='COMMON ROOM'!D92+'COMMON ROOM'!P92+'COMMON ROOM'!AB92+'COMMON ROOM'!AN92+'COMMON ROOM'!AZ92 -> 0 | E92: ='COMMON ROOM'!E92+'COMMON ROOM'!Q92+'COMMON ROOM'!AC92+'COMMON ROOM'!AO92+'COMMON ROOM'!BA92 -> 0 | F92: ='COMMON ROOM'!F92+'COMMON ROOM'!R92+'COMMON ROOM'!AD92+'COMMON ROOM'!AP92+'COMMON ROOM'!BB92 -> 0 | Q92: =B92*C92 -> 0 | R92: =B92*D92 -> 0 | S92: =B92*E92 -> 0 | T92: =B92*F92 -> 0 | U92: =B92*G92 -> 0 | V92: =B92*H92 -> 0 | W92: =B92*I92 -> 0 | X92: =B92*J92 -> 0 | Y92: =K92*B92 -> 0 | Z92: =B92*L92 -> 0 | AA92: =B92*M92 -> 0 | AB92: =B92*N92 -> 0
A93: Romantic Date Gift Set (Essential Oils) | B93: 490 | C93: ='COMMON ROOM'!C93+'COMMON ROOM'!O93+'COMMON ROOM'!AA93+'COMMON ROOM'!AM93+'COMMON ROOM'!AY93 -> 0 | D93: ='COMMON ROOM'!D93+'COMMON ROOM'!P93+'COMMON ROOM'!AB93+'COMMON ROOM'!AN93+'COMMON ROOM'!AZ93 -> 0 | E93: ='COMMON ROOM'!E93+'COMMON ROOM'!Q93+'COMMON ROOM'!AC93+'COMMON ROOM'!AO93+'COMMON ROOM'!BA93 -> 0 | F93: ='COMMON ROOM'!F93+'COMMON ROOM'!R93+'COMMON ROOM'!AD93+'COMMON ROOM'!AP93+'COMMON ROOM'!BB93 -> 0 | Q93: =B93*C93 -> 0 | R93: =B93*D93 -> 0 | S93: =B93*E93 -> 0 | T93: =B93*F93 -> 0 | U93: =B93*G93 -> 0 | V93: =B93*H93 -> 0 | W93: =B93*I93 -> 0 | X93: =B93*J93 -> 0 | Y93: =K93*B93 -> 0 | Z93: =B93*L93 -> 0 | AA93: =B93*M93 -> 0 | AB93: =B93*N93 -> 0
A94: One Way Ticket Gift Set (Fragrance Oils) | B94: 450 | C94: ='COMMON ROOM'!C94+'COMMON ROOM'!O94+'COMMON ROOM'!AA94+'COMMON ROOM'!AM94+'COMMON ROOM'!AY94 -> 0 | D94: ='COMMON ROOM'!D94+'COMMON ROOM'!P94+'COMMON ROOM'!AB94+'COMMON ROOM'!AN94+'COMMON ROOM'!AZ94 -> 0 | E94: ='COMMON ROOM'!E94+'COMMON ROOM'!Q94+'COMMON ROOM'!AC94+'COMMON ROOM'!AO94+'COMMON ROOM'!BA94 -> 0 | F94: ='COMMON ROOM'!F94+'COMMON ROOM'!R94+'COMMON ROOM'!AD94+'COMMON ROOM'!AP94+'COMMON ROOM'!BB94 -> 0 | Q94: =B94*C94 -> 0 | R94: =B94*D94 -> 0 | S94: =B94*E94 -> 0 | T94: =B94*F94 -> 0 | U94: =B94*G94 -> 0 | V94: =B94*H94 -> 0 | W94: =B94*I94 -> 0 | X94: =B94*J94 -> 0 | Y94: =K94*B94 -> 0 | Z94: =B94*L94 -> 0 | AA94: =B94*M94 -> 0 | AB94: =B94*N94 -> 0
A95: Family Reunion Gift Set (Fragrance Oils) | B95: 450 | C95: ='COMMON ROOM'!C95+'COMMON ROOM'!O95+'COMMON ROOM'!AA95+'COMMON ROOM'!AM95+'COMMON ROOM'!AY95 -> 0 | D95: ='COMMON ROOM'!D95+'COMMON ROOM'!P95+'COMMON ROOM'!AB95+'COMMON ROOM'!AN95+'COMMON ROOM'!AZ95 -> 0 | E95: ='COMMON ROOM'!E95+'COMMON ROOM'!Q95+'COMMON ROOM'!AC95+'COMMON ROOM'!AO95+'COMMON ROOM'!BA95 -> 0 | F95: ='COMMON ROOM'!F95+'COMMON ROOM'!R95+'COMMON ROOM'!AD95+'COMMON ROOM'!AP95+'COMMON ROOM'!BB95 -> 0 | Q95: =B95*C95 -> 0 | R95: =B95*D95 -> 0 | S95: =B95*E95 -> 0 | T95: =B95*F95 -> 0 | U95: =B95*G95 -> 0 | V95: =B95*H95 -> 0 | W95: =B95*I95 -> 0 | X95: =B95*J95 -> 0 | Y95: =K95*B95 -> 0 | Z95: =B95*L95 -> 0 | AA95: =B95*M95 -> 0 | AB95: =B95*N95 -> 0
C96: ='COMMON ROOM'!C96+'COMMON ROOM'!O96+'COMMON ROOM'!AA96+'COMMON ROOM'!AM96+'COMMON ROOM'!AY96 -> 0 | D96: ='COMMON ROOM'!D96+'COMMON ROOM'!P96+'COMMON ROOM'!AB96+'COMMON ROOM'!AN96+'COMMON ROOM'!AZ96 -> 0 | E96: ='COMMON ROOM'!E96+'COMMON ROOM'!Q96+'COMMON ROOM'!AC96+'COMMON ROOM'!AO96+'COMMON ROOM'!BA96 -> 0 | F96: ='COMMON ROOM'!F96+'COMMON ROOM'!R96+'COMMON ROOM'!AD96+'COMMON ROOM'!AP96+'COMMON ROOM'!BB96 -> 0 | Q96: =B96*C96 -> 0 | R96: =B96*D96 -> 0 | S96: =B96*E96 -> 0 | T96: =B96*F96 -> 0 | U96: =B96*G96 -> 0 | V96: =B96*H96 -> 0 | AA96: =B96*M96 -> 0 | AB96: =B96*N96 -> 0
A97: Fresh Start Kit | B97: 1054 | C97: ='COMMON ROOM'!C97+'COMMON ROOM'!O97+'COMMON ROOM'!AA97+'COMMON ROOM'!AM97+'COMMON ROOM'!AY97 -> 0 | D97: ='COMMON ROOM'!D97+'COMMON ROOM'!P97+'COMMON ROOM'!AB97+'COMMON ROOM'!AN97+'COMMON ROOM'!AZ97 -> 0 | E97: ='COMMON ROOM'!E97+'COMMON ROOM'!Q97+'COMMON ROOM'!AC97+'COMMON ROOM'!AO97+'COMMON ROOM'!BA97 -> 0 | F97: ='COMMON ROOM'!F97+'COMMON ROOM'!R97+'COMMON ROOM'!AD97+'COMMON ROOM'!AP97+'COMMON ROOM'!BB97 -> 0 | Q97: =B97*C97 -> 0 | R97: =C97*D97 -> 0 | S97: =D97*E97 -> 0 | T97: =E97*F97 -> 0 | U97: =F97*G97 -> 0 | V97: =G97*H97 -> 0 | W97: =H97*I97 -> 0 | X97: =I97*J97 -> 0 | ... AB97: =M97*N97 -> 0
A98: Quite Olive RLS | B98: 349 | C98: ='COMMON ROOM'!C98+'COMMON ROOM'!O98+'COMMON ROOM'!AA98+'COMMON ROOM'!AM98+'COMMON ROOM'!AY98 -> 0 | D98: ='COMMON ROOM'!D98+'COMMON ROOM'!P98+'COMMON ROOM'!AB98+'COMMON ROOM'!AN98+'COMMON ROOM'!AZ98 -> 0 | E98: ='COMMON ROOM'!E98+'COMMON ROOM'!Q98+'COMMON ROOM'!AC98+'COMMON ROOM'!AO98+'COMMON ROOM'!BA98 -> 15 | F98: ='COMMON ROOM'!F98+'COMMON ROOM'!R98+'COMMON ROOM'!AD98+'COMMON ROOM'!AP98+'COMMON ROOM'!BB98 -> 20
A99: Quite Olive Refill | B99: 459 | C99: ='COMMON ROOM'!C99+'COMMON ROOM'!O99+'COMMON ROOM'!AA99+'COMMON ROOM'!AM99+'COMMON ROOM'!AY99 -> 0 | D99: ='COMMON ROOM'!D99+'COMMON ROOM'!P99+'COMMON ROOM'!AB99+'COMMON ROOM'!AN99+'COMMON ROOM'!AZ99 -> 0 | E99: ='COMMON ROOM'!E99+'COMMON ROOM'!Q99+'COMMON ROOM'!AC99+'COMMON ROOM'!AO99+'COMMON ROOM'!BA99 -> 4 | F99: ='COMMON ROOM'!F99+'COMMON ROOM'!R99+'COMMON ROOM'!AD99+'COMMON ROOM'!AP99+'COMMON ROOM'!BB99 -> 5
A100: Quite Olive Reed Set | B100: 799 | C100: ='COMMON ROOM'!C100+'COMMON ROOM'!O100+'COMMON ROOM'!AA100+'COMMON ROOM'!AM100+'COMMON ROOM'!AY100 -> 0 | D100: ='COMMON ROOM'!D100+'COMMON ROOM'!P100+'COMMON ROOM'!AB100+'COMMON ROOM'!AN100+'COMMON ROOM'!AZ100 -> 0 | E100: ='COMMON ROOM'!E100+'COMMON ROOM'!Q100+'COMMON ROOM'!AC100+'COMMON ROOM'!AO100+'COMMON ROOM'!BA100 -> 0 | F100: ='COMMON ROOM'!F100+'COMMON ROOM'!R100+'COMMON ROOM'!AD100+'COMMON ROOM'!AP100+'COMMON ROOM'!BB100 -> 0
A101: Custom Order | Q101: =B101*C101 -> 0 | R101: =C101*D101 -> 0 | S101: =D101*E101 -> 0 | T101: =E101*F101 -> 0 | U101: =F101*G101 -> 0 | V101: =G101*H101 -> 0 | W101: =H101*I101 -> 0 | X101: =I101*J101 -> 0 | ... AB101: =M101*N101 -> 0
Q102: ='COMMON ROOM'!C102+'COMMON ROOM'!O102+'COMMON ROOM'!AA102+'COMMON ROOM'!AM102+'COMMON ROOM'!AY102 -> 146221 | R102: ='COMMON ROOM'!D102+'COMMON ROOM'!P102+'COMMON ROOM'!AB102+'COMMON ROOM'!AN102+'COMMON ROOM'!AZ102 -> 95644 | S102: ='COMMON ROOM'!E102+'COMMON ROOM'!Q102+'COMMON ROOM'!AC102+'COMMON ROOM'!AO102+'COMMON ROOM'!BA102 -> 81630 | T102: ='COMMON ROOM'!F102+'COMMON ROOM'!R102+'COMMON ROOM'!AD102+'COMMON ROOM'!AP102+'COMMON ROOM'!BB102 -> 96378 | U102: ='COMMON ROOM'!G102+'COMMON ROOM'!S102+'COMMON ROOM'!AE102+'COMMON ROOM'!AQ102+'COMMON ROOM'!BC102 -> 0 | V102: ='COMMON ROOM'!H102+'COMMON ROOM'!T102+'COMMON ROOM'!AF102+'COMMON ROOM'!AR102+'COMMON ROOM'!BD102 -> 0 | W102: ='COMMON ROOM'!I102+'COMMON ROOM'!U102+'COMMON ROOM'!AG102+'COMMON ROOM'!AS102+'COMMON ROOM'!BE102 -> 0 | X102: ='COMMON ROOM'!J102+'COMMON ROOM'!V102+'COMMON ROOM'!AH102+'COMMON ROOM'!AT102+'COMMON ROOM'!BF102 -> 0 | ... AC102: ='COMMON ROOM'!O102+'COMMON ROOM'!AA102+'COMMON ROOM'!AM102+'COMMON ROOM'!AY102+'COMMON ROOM'!BK102 -> 119220
Q103: 147139
Q104: =Q102-Q103 -> -918

Sheet COMMON ROOM
C2: ATC | O2: ROCKWELL | AA2: AYALA BAY | AM2: UPTC | AY2: ATRIUM
A3: VARIANT | B3: PRICE | C3: Jan | D3: Feb | E3: Mar | F3: Apr | G3: May | H3: Jun | I3: Jul | J3: Aug | K3: Sep | L3: Oct | M3: Nov | N3: Dec | O3: Jan | P3: Feb | Q3: Mar | R3: Apr | S3: May | T3: Jun | U3: Jul | V3: Aug | W3: Sep | X3: Oct | Y3: Nov | Z3: Dec | AA3: Jan | AB3: Feb | AC3: Mar | AD3: Apr | AE3: May | AF3: Jun | AG3: Jul | AH3: Aug | AI3: Sep | AJ3: Oct | AK3: Nov | AL3: Dec | AM3: Jan | AN3: Feb | AO3: Mar | AP3: Apr | AQ3: May | AR3: Jun | AS3: Jul | AT3: Aug | AU3: Sep | AV3: Oct | AW3: Nov | AX3: Dec | AY3: Jan | AZ3: Feb | BA3: Mar | BB3: Apr | BC3: May | BD3: Jun | BE3: Jul | BF3: Aug | BG3: Sep | BH3: Oct | BI3: Nov | BJ3: Dec
A5: Quiet Elegance | B5: 349
A6: Charming Home | B6: 349
A7: Bright Mornings | B7: 349
A8: Relaxing Naturals | B8: 349 | C8: 13 | D8: 5 | E8: 5 | F8: 4 | O8: 15 | P8: 2 | Q8: 2 | R8: 6 | AA8: 4 | AB8: 4 | AC8: 2 | AD8: 2 | AM8: 5 | AN8: 3 | AO8: 3 | AP8: 3 | AY8: 1 | AZ8: 3 | BA8: 1
A9: Mountain Breeze | B9: 349
A10: Fresh Bamboo | B10: 349 | C10: 6 | E10: 3 | F10: 11 | O10: 8 | Q10: 5 | R10: 11 | AA10: 1 | AB10: 1 | AC10: 1 | AD10: 7 | AM10: 5 | AP10: 2 | AY10: 3 | AZ10: 2 | BB10: 3
A11: Beach Escape | B11: 349 | C11: 8 | E11: 2 | F11: 2 | O11: 8 | Q11: 3 | R11: 7 | AA11: 3 | AB11: 2 | AD11: 7 | AM11: 5 | AO11: 6 | AP11: 2 | BB11: 3
A12: White Tea | B12: 349 | E12: 3 | F12: 5 | O12: 9 | P12: 2 | Q12: 3 | R12: 11 | AA12: 4 | AC12: 2 | AD12: 3 | AN12: 4 | AP12: 3 | AY12: 3 | AZ12: 2
A13: Candy Cane | B13: 349 | AC13: 1 | AD13: 2 | AN13: 2 | BA13: 2
A14: Apple Cinnamon | B14: 349 | O14: 4 | AA14: 4 | BA14: 3
A15: Easy Drive | B15: 239 | F15: 3 | AA15: 1 | AB15: 3 | AM15: 1 | AN15: 1 | AO15: 4 | AP15: 1
A16: InLove
A17: Bright Mornings HW
A19: Lavender | B19: 259 | O19: 5 | Q19: 8 | AA19: 1 | AB19: 7 | AC19: 1 | AM19: 2 | AN19: 2 | AO19: 1 | AP19: 3 | AY19: 3 | AZ19: 1
A20: Eucalyptus | B20: 259 | C20: 2 | D20: 1 | E20: 1 | O20: 4 | Q20: 1 | R20: 5 | AA20: 1 | AB20: 4 | AC20: 3 | AD20: 1 | AM20: 2 | AN20: 1 | AO20: 2 | AZ20: 1 | BA20: 2
A21: Peppermint | B21: 259 | C21: 5 | E21: 1 | F21: 1 | O21: 3 | Q21: 6 | R21: 1 | AA21: 3 | AC21: 2 | AN21: 1 | AY21: 2
A22: Fresh Bamboo FO | B22: 239 | C22: 4 | D22: 5 | E22: 1 | F22: 3 | O22: 1 | P22: 5 | Q22: 2 | AA22: 3 | AB22: 6 | AC22: 2 | AM22: 1 | AN22: 4 | AO22: 2 | AP22: 3 | AZ22: 2
A23: Beach Escape FO | B23: 239 | C23: 2 | E23: 3 | F23: 1 | P23: 3 | Q23: 1 | R23: 3 | AA23: 1 | AB23: 2 | AC23: 1 | AM23: 2 | AN23: 1 | AO23: 2 | AP23: 2 | AY23: 1 | BB23: 1
A24: White Tea FO | B24: 239 | P24: 2 | Q24: 1 | R24: 3 | AA24: 3 | AN24: 1
A25: Bright Mornings FO
A26: Quiet Elegance FO
A27: Fresh Bamboo Diffuser | B27: 819
A28: Clean Air | B28: 629 | C28: 1 | D28: 1 | F28: 1 | Q28: 2 | R28: 1 | AA28: 1 | AB28: 1 | AC28: 1 | AD28: 2 | AM28: 1 | AN28: 1 | BA28: 1
A29: Cotton Clean | B29: 349 | C29: 3 | D29: 5 | R29: 5 | AA29: 3 | AC29: 1 | AD29: 1 | AM29: 6 | AN29: 2 | AY29: 1 | BB29: 2
A30: Brighter Days | B30: 349
A31: Cotton Clean FO | B31: 239 | C31: 1 | E31: 2 | F31: 2 | P31: 1 | Q31: 1 | R31: 4 | AA31: 1 | AB31: 2 | AC31: 1 | AD31: 3 | AN31: 1 | AO31: 2 | AP31: 1 | AY31: 1 | BA31: 1
A32: Brighter Days EO | B32: 239
A33: Fresh Bamboo Refill | B33: 459 | C33: 1 | D33: 4 | E33: 4 | O33: 1 | R33: 1 | AA33: 1 | AB33: 2 | AC33: 1 | AD33: 1 | AM33: 1 | AO33: 1 | AP33: 1
A34: Clean Air Refill 1000ml | B34: 899
A35: Waterbased: Fresh Bamboo | B35: 569 | C35: 1 | D35: 2 | E35: 1 | O35: 1 | Q35: 1 | AA35: 4 | AM35: 4
A36: Waterbased: Cotton Clean | B36: 569 | C36: 2 | E36: 1 | O36: 3 | Q36: 1 | AA36: 1 | AB36: 2 | AC36: 3 | AD36: 1
A37: Waterbased: White Tea | B37: 569 | O37: 1 | P37: 3 | AA37: 1 | AN37: 1
A38: White Tea Diffuser | B38: 819
A39: Cotton Clean Diffuser | B39: 819
A40: White Tea Diffuser Refill | B40: 459 | C40: 1 | E40: 1 | O40: 3 | P40: 1 | R40: 1 | AA40: 2 | AC40: 3 | AO40: 1 | AP40: 1
A41: Cotton Clean Diffuser Refill | B41: 459 | C41: 1 | R41: 2 | AC41: 1 | AM41: 2
A42: Reed Sticks | B42: 60
A43: Relaxing Naturals 500ml | B43: 629 | C43: 5 | D43: 1 | F43: 5 | O43: 4 | P43: 3 | Q43: 6 | R43: 1 | AA43: 2 | AB43: 1 | AD43: 1 | AN43: 3 | AO43: 3 | AP43: 3 | AY43: 1 | AZ43: 1
A44: Hand Wash Relaxing Naturals 500ml | B44: 399 | O44: 1 | Q44: 2 | R44: 1 | AD44: 1
A45: Hand Wash Clean & Bright 500ml | B45: 399 | O45: 1 | AB45: 1
A46: Keep it Clean Gift Set | B46: 1299
A47: Relax With Me | B47: 1299
A48: Simoy ng Pahiyas | B48: 0
A50: Fresh Bamboo 500ml | B50: 629 | C50: 3 | D50: 5 | E50: 1 | F50: 6 | O50: 9 | P50: 2 | Q50: 2 | AA50: 5 | AB50: 4 | AC50: 1 | AD50: 2 | AM50: 6 | AN50: 9 | AO50: 2 | AP50: 9 | AY50: 1 | AZ50: 2 | BB50: 1
A51: White Tea 500ml | B51: 629 | C51: 2 | D51: 1 | E51: 2 | F51: 5 | O51: 8 | P51: 9 | Q51: 1 | AA51: 1 | AB51: 4 | AC51: 3 | AM51: 1 | AN51: 4 | AO51: 2 | AP51: 4
A52: Tropical Paradise 200ml | B52: 349 | AB52: 1 | AM52: 2
A53: RN Wash 100ml | B53: 199
A54: CB Wash 100ml | B54: 199
A55: Travel With Me | B55: 599
A56: Handwash: Relaxing Naturals Gallon | B56: 1499
A58: Creamy Matcha | B58: 349 | D58: 4 | E58: 1 | O58: 5 | P58: 3 | AA58: 1 | AC58: 4 | AD58: 1 | AM58: 1 | AN58: 2
A59: White Lavender | B59: 349 | O59: 8 | AA59: 3 | AC59: 5 | AD59: 3 | AN59: 7 | AY59: 1 | AZ59: 3 | BA59: 2 | BB59: 1
A60: Green Tea | B60: 349 | C60: 4 | D60: 3 | O60: 5 | P60: 9 | Q60: 2 | AA60: 6 | AB60: 5 | AC60: 5 | AM60: 3 | AN60: 4 | AO60: 4 | AY60: 2 | BB60: 4
A61: Clean Air 100ml | B61: 269 | C61: 1 | E61: 2 | P61: 4 | Q61: 2 | AA61: 1
A62: Creamy Matcha Diffuser Refill | B62: 459 | O62: 1 | Q62: 1 | AA62: 1
A63: White Lavender Diffuser Refill | B63: 459 | C63: 3 | E63: 1 | O63: 1 | P63: 1 | R63: 1 | AA63: 1 | AC63: 1 | AD63: 1 | AO63: 1
A64: Green Tea Diffuser Refill | B64: 459 | D64: 1 | O64: 1 | R64: 1 | AB64: 2 | AN64: 1
A65: Creamy Matcha Diffuser | B65: 819
A66: White Lavender Diffuser | B66: 819
A67: Green Tea Diffuser | B67: 819
A68: Creamy Matcha + Roomspray | B68: 1299
A69: White Lavender + Roomspray | B69: 1299
